Workbook

Sheet BSNC (2)
A1: # | B1: Company | C1: Source | D1: Type | E1: Waiver Code | F1: Previous Waiver code | G1: Name of vulnerable asset | H1: Internal Identification Code | I1: Identification Code External | J1: Vulnerability description | K1: CWE Category | L1: State | M1: Criticity | N1: CVSS / Vendor Severity | O1: Code CVE (Common Vulnerabilities and Exposures) | P1: IP | Q1: Hostname | R1: Port | S1: Port Type | T1: Reported Date | U1: Days that reported | V1: Expiration day according to SLA | W1: SLA State | X1: Waiver | Y1: Date of application for Waiver | Z1: End date of Waiver | AA1: Remediation Date | AB1: Details | AC1: Recommendation | AD1: Risks Derived | AE1: Date of attention | AF1: Commentary | AG1: Owner
A2: 1 | B2: BSNC | C2: Deloitte | D2: Wep App | E2: BSNC-2019-021 | F2: BSNC-2019-005 BSNC-2019-007 | G2: Web de Proveedores | H2: MAN-b00ec668 | I2: CO-001-003 | J2: Vulnerabilidad de directorio transversal | L2: Dismissed | M2: Critical | N2: 7.6999998 | P2: 170.169.33.48 | Q2: confirming.santander.com.co | R2: 443 | T2: 42941 | U2: =TODAY()-T2 -> 3268 | V2: =IF(M2="Critical",T2+10,IF(M2="High",T2+30,IF(M2="Bad",T2+30,IF(M2="Medium",T2+90,IF(M2="Warm",T2+90,IF(M2="Low",T2+120,IF(M2="Fair",T2+120,IF(M2="Neutral",T2+120,"")))))))) -> 42951 | W2: =IF(M2="Critical",IF(U2>10,"SLA Vencido","En SLA"),IF(M2="High",IF(U2>30,"SLA Vencido","En SLA"),IF(M2="Bad",IF(U2>30,"SLA Vencido","En SLA"),IF(M2="Medium",IF(U2>90,"SLA Vencido","En SLA"),IF(M2="Warm",IF(U2>90,"SLA Vencido","En SLA"),IF(M2="Low",IF(U2>120,"SLA Vencido","En SLA"),IF(M2="Fair",IF(U2>120,"SLA Vencido","En SLA"),IF(M2="Neutral",IF(U2>120,"SLA Vencido","En SLA"),"Error")))))))) -> SLA Vencido | X2: Waiver | Y2: 1ª Fecha: 25/07/2017 2ª Fecha: 31/07/2019 3ª Fecha: 21/12/2019 4ª Fecha: 13/04/2020 | Z2: 1ª Fecha: 31/07/2019 2ª Fecha: 29/11/2019 3ª Fecha: 30/04/2020 4ª Fecha: 30/06/2020 | AA2: 44025 | AD2: Un directorio transversal (o path traversal) consiste en explotar una vulnerabilidad informática que ocurre cuando no existe suficiente seguridad en cuanto a la validación de un usuario, permitiéndole acceder a cualquier tipo de directorio superior (padre) sin ningún control. | AE2: 44012 | AF2: Fue dado de baja el Lunes 13 de Julio del 2020 | AH2: =IFERROR(VLOOKUP(H2,hoja1!A:A,1,),"N/A") -> N/A
A3: 2 | B3: BSNC | C3: Deloitte | D3: Wep App | E3: BSNC-2019-022 | F3: BSNC-2019-008 | G3: Web de Proveedores | H3: MAN-b00ec669 | I3: CO-005-002 | J3: Cross Site Request Forgery | L3: Dismissed | M3: Critical | N3: 7.5999999 | P3: 170.169.33.48 | Q3: confirming.santander.com.co | R3: 443 | T3: 42941 | U3: =TODAY()-T3 -> 3268 | V3: =IF(M3="Critical",T3+10,IF(M3="High",T3+30,IF(M3="Bad",T3+30,IF(M3="Medium",T3+90,IF(M3="Warm",T3+90,IF(M3="Low",T3+120,IF(M3="Fair",T3+120,IF(M3="Neutral",T3+120,"")))))))) -> 42951 | W3: =IF(M3="Critical",IF(U3>10,"SLA Vencido","En SLA"),IF(M3="High",IF(U3>30,"SLA Vencido","En SLA"),IF(M3="Bad",IF(U3>30,"SLA Vencido","En SLA"),IF(M3="Medium",IF(U3>90,"SLA Vencido","En SLA"),IF(M3="Warm",IF(U3>90,"SLA Vencido","En SLA"),IF(M3="Low",IF(U3>120,"SLA Vencido","En SLA"),IF(M3="Fair",IF(U3>120,"SLA Vencido","En SLA"),IF(M3="Neutral",IF(U3>120,"SLA Vencido","En SLA"),"Error")))))))) -> SLA Vencido | X3: Waiver | Y3: 1ª Fecha: 23/07/2019 2ª Fecha: 21/12/2019 3ª Fecha: 13/04/2020 | Z3: 1ª Fecha: 29/11/2019 2ª Fecha: 30/04/2020 3ª Fecha: 30/06/2020 | AA3: 44025 | AD3: Los ataques de tipo "Cross-site Request Forgery" fuerzan a un usuario a realizar acciones no deseadas en aplicativos web, aprovechando que los usuarios legítimos se encuentran previamente autenticados en la plataforma. De esta manera, un atacante malintencionado podría confeccionar peticiones HTTP que realizasen alguna acción concreta de la aplicación, por ejemplo, cambiar la contraseña del usuario legítimo, hacer una transacción bancaria, etc. Una vez confeccionadas estas peticiones se forzaría al usuario a realizarlas, en este paso interviene un componente de ingeniería social, ya que se ha de hacer llegar al usuario un link con la acción confeccionada por el atacante para que el usuario la ejecute. Por ejemplo, simular una campaña de publicidad de la compañía via e-mail con un enlace a la acción confeccionada por el atacante. Por otro lado, para camuflar el enlace se puede esconder el mismo modificando el texto del hipervínculo, el típico "pulse aquí" o, incluso, utilizar acortadores de URL. De esta manera, cuando el usuario acceda al enlace enviado por correo electrónico se intentará ejecutar la acción deseada dentro de la sesión del usuario en la aplicación, sin que éste se de cuenta. En numerosas ocasiones, si el usuario no se encuentra previamente autenticado, al intentar realizar una acción privilegiada como cambiar la contraseña, el propio aplicativo web presentará al usuario el formulario de inicio de sesión para que éste se autentique y posteriormente realizar la acción diseñada por el atacante. | AE3: 44012 | AF3: Fue dado de baja el Lunes 13 de Julio del 2020 | AH3: =IFERROR(VLOOKUP(H3,hoja1!A:A,1,),"N/A") -> N/A
A4: 3 | B4: BSNC | C4: Deloitte | D4: Wep App | E4: BSNC-2019-013 | G4: Web de Proveedores | H4: MAN-28ad454c | I4: CO-017-002 | J4: Debilidad en el mecanismo de CAPTCHA | L4: Dismissed | M4: Medium | N4: 6.5 | P4: 170.169.33.48 | Q4: confirming.santander.com.co | R4: 443 | T4: 42746 | U4: =TODAY()-T4 -> 3463 | V4: =IF(M4="Critical",T4+10,IF(M4="High",T4+30,IF(M4="Bad",T4+30,IF(M4="Medium",T4+90,IF(M4="Warm",T4+90,IF(M4="Low",T4+120,IF(M4="Fair",T4+120,IF(M4="Neutral",T4+120,"")))))))) -> 42836 | W4: =IF(M4="Critical",IF(U4>10,"SLA Vencido","En SLA"),IF(M4="High",IF(U4>30,"SLA Vencido","En SLA"),IF(M4="Bad",IF(U4>30,"SLA Vencido","En SLA"),IF(M4="Medium",IF(U4>90,"SLA Vencido","En SLA"),IF(M4="Warm",IF(U4>90,"SLA Vencido","En SLA"),IF(M4="Low",IF(U4>120,"SLA Vencido","En SLA"),IF(M4="Fair",IF(U4>120,"SLA Vencido","En SLA"),IF(M4="Neutral",IF(U4>120,"SLA Vencido","En SLA"),"Error")))))))) -> SLA Vencido | X4: Waiver | Y4: 1ª Fecha: 21/12/2019 2ª Fecha: 13/04/2020 | Z4: 1ª Fecha: 30/04/2020 2ª Fecha: 30/06/2020 | AA4: 44025 | AD4: Ataque de fuerza bruta | AE4: 44012 | AF4: Fue dado de baja el Lunes 13 de Julio del 2020 | AH4: =IFERROR(VLOOKUP(H4,hoja1!A:A,1,),"N/A") -> N/A
A5: 4 | B5: BSNC | C5: Deloitte | D5: Wep App | E5: BSNC-2019-023 | G5: Web de Proveedores | H5: MAN-18af2324 | I5: CO-19-AUTO-02-CO-001 | J5: Uso de librerias desactualizadas | L5: Dismissed | M5: Medium | N5: 5.5999999 | P5: 170.169.33.48 | Q5: confirming.santander.com.co | R5: 443 | T5: 43719 | U5: =TODAY()-T5 -> 2490 | V5: =IF(M5="Critical",T5+10,IF(M5="High",T5+30,IF(M5="Bad",T5+30,IF(M5="Medium",T5+90,IF(M5="Warm",T5+90,IF(M5="Low",T5+120,IF(M5="Fair",T5+120,IF(M5="Neutral",T5+120,"")))))))) -> 43809 | W5: =IF(M5="Critical",IF(U5>10,"SLA Vencido","En SLA"),IF(M5="High",IF(U5>30,"SLA Vencido","En SLA"),IF(M5="Bad",IF(U5>30,"SLA Vencido","En SLA"),IF(M5="Medium",IF(U5>90,"SLA Vencido","En SLA"),IF(M5="Warm",IF(U5>90,"SLA Vencido","En SLA"),IF(M5="Low",IF(U5>120,"SLA Vencido","En SLA"),IF(M5="Fair",IF(U5>120,"SLA Vencido","En SLA"),IF(M5="Neutral",IF(U5>120,"SLA Vencido","En SLA"),"Error")))))))) -> SLA Vencido | X5: Waiver | Y5: 1ª Fecha: 21/12/2019 2ª Fecha: 13/04/2020 | Z5: 1ª Fecha: 30/04/2020 2ª Fecha: 30/06/2020 | AA5: 44025 | AB5: Se encuentra el uso de funciones de Modernizr 2.6.2: /WebProveedoresNala/proveedores/js/vendor/modernizr-2.6.2.min.js | AC5: Se recomienda utilizar versiones actualizadas del software y/o plataformas tecnológicas utilizadas, en caso de no ser posible aplicar todas las actualizaciones de seguridad publicadas para la versión utilizada. | AD5: El software o plataforma utilizada no se encuentra actualizado a la última versión disponible. Esto implica que podría ser susceptible de poder ser comprometido mediante vulnerabilidades conocidas que pudieran poner en riesgo el activo afectado. | AE5: 44012 | AF5: Fue dado de baja el Lunes 13 de Julio del 2020 | AH5: =IFERROR(VLOOKUP(H5,hoja1!A:A,1,),"N/A") -> N/A
A6: 5 | B6: BSNC | C6: Deloitte | D6: Wep App | E6: BSNC-2019-014 | G6: Web de Proveedores | H6: MAN-28ad454d | I6: CO-037-001 | J6: Revelación de información a través de SSL/TLS (BEAST) | L6: Dismissed | M6: Medium | N6: 5.3000002 | P6: 170.169.33.48 | Q6: confirming.santander.com.co | R6: 443 | T6: 42879 | U6: =TODAY()-T6 -> 3330 | V6: =IF(M6="Critical",T6+10,IF(M6="High",T6+30,IF(M6="Bad",T6+30,IF(M6="Medium",T6+90,IF(M6="Warm",T6+90,IF(M6="Low",T6+120,IF(M6="Fair",T6+120,IF(M6="Neutral",T6+120,"")))))))) -> 42969 | W6: =IF(M6="Critical",IF(U6>10,"SLA Vencido","En SLA"),IF(M6="High",IF(U6>30,"SLA Vencido","En SLA"),IF(M6="Bad",IF(U6>30,"SLA Vencido","En SLA"),IF(M6="Medium",IF(U6>90,"SLA Vencido","En SLA"),IF(M6="Warm",IF(U6>90,"SLA Vencido","En SLA"),IF(M6="Low",IF(U6>120,"SLA Vencido","En SLA"),IF(M6="Fair",IF(U6>120,"SLA Vencido","En SLA"),IF(M6="Neutral",IF(U6>120,"SLA Vencido","En SLA"),"Error")))))))) -> SLA Vencido | X6: Waiver | Y6: 1ª Fecha: 21/12/2019 2ª Fecha: 13/04/2020 | Z6: 1ª Fecha: 30/04/2020 2ª Fecha: 30/06/2020 | AA6: 44025 | AD6: Existe un fallo de diseño en los protocolos SSL 3.0 y TLS 1.0 al utilizar cifrado de bloque en modo CBC. Esto podría ser utilizado por un atacante remoto para revelar información sensible a través de ataques Man in The Middle. | AE6: 44012 | AF6: Fue dado de baja el Lunes 13 de Julio del 2020 | AH6: =IFERROR(VLOOKUP(H6,hoja1!A:A,1,),"N/A") -> N/A
A7: 6 | B7: BSNC | C7: Deloitte | D7: Wep App | E7: BSNC-2019-012 | G7: Web de Proveedores | H7: MAN-7446a64b | I7: CO-009-008 | J7: Fuga de información de servidor y versión | L7: Dismissed | M7: Medium | N7: 5.3000002 | P7: 170.169.33.48 | Q7: confirming.santander.com.co | R7: 443 | T7: 43207 | U7: =TODAY()-T7 -> 3002 | V7: =IF(M7="Critical",T7+10,IF(M7="High",T7+30,IF(M7="Bad",T7+30,IF(M7="Medium",T7+90,IF(M7="Warm",T7+90,IF(M7="Low",T7+120,IF(M7="Fair",T7+120,IF(M7="Neutral",T7+120,"")))))))) -> 43297 | W7: =IF(M7="Critical",IF(U7>10,"SLA Vencido","En SLA"),IF(M7="High",IF(U7>30,"SLA Vencido","En SLA"),IF(M7="Bad",IF(U7>30,"SLA Vencido","En SLA"),IF(M7="Medium",IF(U7>90,"SLA Vencido","En SLA"),IF(M7="Warm",IF(U7>90,"SLA Vencido","En SLA"),IF(M7="Low",IF(U7>120,"SLA Vencido","En SLA"),IF(M7="Fair",IF(U7>120,"SLA Vencido","En SLA"),IF(M7="Neutral",IF(U7>120,"SLA Vencido","En SLA"),"Error")))))))) -> SLA Vencido | X7: Waiver | Y7: 1ª Fecha: 21/12/2019 2ª Fecha: 13/04/2020 | Z7: 1ª Fecha: 30/04/2020 2ª Fecha: 30/06/2020 | AA7: 44025 | AB7: Durante la realización de las pruebas se ha detectado que en las respuestas del servidor se muestra información sobre el tipo de servidor donde se aloja la aplicación | AC7: Se recomienda evitar que la aplicación devuelva al usuario información relativa a la estructura interna de la misma, así como de las tecnologías utilizadas para el desarrollo de la misma o de la infraestructura que la sustenta. Este tipo de información puede ser accesible a través de las cabeceras de respuesta de la aplicación, mensajes de error y/o páginas por defecto. | AD7: Se ha detectado que la aplicación devuelve información acerca de las tecnologías utilizadas para desarrollar la aplicación y/o de la infraestructura utilizada para sustentar la misma. Esta información podría ser utilizada por un atacante con el objetivo de recabar información para ataques futuros. | AE7: 44012 | AF7: Fue dado de baja el Lunes 13 de Julio del 2020 | AH7: =IFERROR(VLOOKUP(H7,hoja1!A:A,1,),"N/A") -> N/A
A8: 7 | B8: BSNC | C8: Deloitte | D8: Wep App | E8: BSNC-2019-011 | G8: Web de Proveedores | H8: MAN-28ad4540 | I8: CO-004-001 | J8: Divulgación de información httpOnly Cookie en el Servidor Apache HTTP | L8: Dismissed | M8: Medium | N8: 5.3000002 | P8: 170.169.33.48 | Q8: confirming.santander.com.co | R8: 443 | T8: 42608 | U8: =TODAY()-T8 -> 3601 | V8: =IF(M8="Critical",T8+10,IF(M8="High",T8+30,IF(M8="Bad",T8+30,IF(M8="Medium",T8+90,IF(M8="Warm",T8+90,IF(M8="Low",T8+120,IF(M8="Fair",T8+120,IF(M8="Neutral",T8+120,"")))))))) -> 42698 | W8: =IF(M8="Critical",IF(U8>10,"SLA Vencido","En SLA"),IF(M8="High",IF(U8>30,"SLA Vencido","En SLA"),IF(M8="Bad",IF(U8>30,"SLA Vencido","En SLA"),IF(M8="Medium",IF(U8>90,"SLA Vencido","En SLA"),IF(M8="Warm",IF(U8>90,"SLA Vencido","En SLA"),IF(M8="Low",IF(U8>120,"SLA Vencido","En SLA"),IF(M8="Fair",IF(U8>120,"SLA Vencido","En SLA"),IF(M8="Neutral",IF(U8>120,"SLA Vencido","En SLA"),"Error")))))))) -> SLA Vencido | X8: Waiver | Y8: 1ª Fecha: 21/12/2019 2ª Fecha: 13/04/2020 | Z8: 1ª Fecha: 30/04/2020 2ª Fecha: 30/06/2020 | AA8: 44025 | AD8: La exposición de información acerca de las funcionalidades o rutas internas de la aplicación puede implicar a un atacante obtener una mayor comprensión del sistema en uso y, potencialmente, desarrollar más ataques para apuntar a la aplicación web. | AE8: 44012 | AF8: Fue dado de baja el Lunes 13 de Julio del 2020 | AH8: =IFERROR(VLOOKUP(H8,hoja1!A:A,1,),"N/A") -> N/A
A9: 8 | B9: BSNC | C9: Deloitte | D9: Wep App | E9: Wep App | G9: Web de Proveedores | H9: MAN-cc489697 | I9: CO-19-AUTO-01-CO-001 | J9: Uso de Software desactualizado | L9: Dismissed | M9: Medium | N9: 5.3000002 | P9: 170.169.33.48 | Q9: confirming.santander.com.co | R9: 443 | T9: 43580 | U9: =TODAY()-T9 -> 2629 | V9: =IF(M9="Critical",T9+10,IF(M9="High",T9+30,IF(M9="Bad",T9+30,IF(M9="Medium",T9+90,IF(M9="Warm",T9+90,IF(M9="Low",T9+120,IF(M9="Fair",T9+120,IF(M9="Neutral",T9+120,"")))))))) -> 43670 | W9: =IF(M9="Critical",IF(U9>10,"SLA Vencido","En SLA"),IF(M9="High",IF(U9>30,"SLA Vencido","En SLA"),IF(M9="Bad",IF(U9>30,"SLA Vencido","En SLA"),IF(M9="Medium",IF(U9>90,"SLA Vencido","En SLA"),IF(M9="Warm",IF(U9>90,"SLA Vencido","En SLA"),IF(M9="Low",IF(U9>120,"SLA Vencido","En SLA"),IF(M9="Fair",IF(U9>120,"SLA Vencido","En SLA"),IF(M9="Neutral",IF(U9>120,"SLA Vencido","En SLA"),"Error")))))))) -> SLA Vencido | X9: Waiver | Y9: 1ª Fecha: 21/12/2019 2ª Fecha: 13/04/2020 | Z9: 1ª Fecha: 30/04/2020 2ª Fecha: 30/06/2020 | AA9: 44025 | AB9: Las librerias Javascript utilizadas se encuentran desactualizadas. [+]Request: GET https://confirming.santander.com.co /WebProveedoresNala/common/js/prototype.js HTTP/1.1 Pragma: no-cache Cache-Control: no-cache Referer: https://confirming.santander.com.co/WebProveedoresNala/WebPipe Acunetix-Aspect: enabled Acunetix-Aspect-Password: 082119f75623eb7abd7bf357698ff66c Acunetix-Aspect-Queries: filelist;aspectalerts Host: confirming.santander.com.co Connection: Keep-alive Accept-Encoding: gzip,deflate User-Agent: Mozilla/5.0 (Windows NT 6.1; WOW64) AppleWebKit/537.36 (KHTML, like Gecko) Chrome/28.0.1500.63 Safari/537.36 Accept: */* [+]Response: HTTP/1.1 200 OK Date: Fri, 22 Mar 2019 07:12:48 GMT Server: Apache Strict-Transport-Security: max-age=63072000; includeSubdomains; X-Frame-Options: SAMEORIGIN X-XSS-Protection: 1; mode=block Last-Modified: Tue, 14 Oct 2014 17:19:04 GMT Content-Length: 124136 Keep-Alive: timeout=10, max=185 Connection: Keep-Alive Content-Type: application/x-javascript Content-Language: en-US /* Prototype JavaScript framework, version 1.6.0 * (c) 2005-2007 Sam Stephenson * * Prototype is freely distributable under the terms of an MIT-style license. * For details, see the Prototype web site: http://www.prototypejs.org/ * *--------------------------------------------------------------------------*/ | AC9: Se recomienda utilizar versiones actualizadas del software y/o plataformas tecnológicas utilizadas, en caso de no ser posible aplicar todas las actualizaciones de seguridad publicadas para la versión utilizada. | AD9: El software o plataforma utilizada no se encuentra actualizado a la última versión disponible. Esto implica que podría ser susceptible de poder ser comprometido mediante vulnerabilidades conocidas que pudieran poner en riesgo el activo afectado. | AE9: 44012 | AF9: Fue dado de baja el Lunes 13 de Julio del 2020 | AH9: =IFERROR(VLOOKUP(H9,hoja1!A:A,1,),"N/A") -> N/A
A10: 9 | B10: BSNC | C10: Deloitte | D10: Wep App | E10: BSNC-2019-017 | G10: Web de Proveedores | H10: MAN-73a2e320 | I10: CO-19-MANU-01-AP-002 | J10: Uso de cifrado 3DES | L10: Dismissed | M10: Medium | N10: 4.3000002 | P10: 170.169.33.48 | Q10: confirming.santander.com.co | T10: 43609 | U10: =TODAY()-T10 -> 2600 | V10: =IF(M10="Critical",T10+10,IF(M10="High",T10+30,IF(M10="Bad",T10+30,IF(M10="Medium",T10+90,IF(M10="Warm",T10+90,IF(M10="Low",T10+120,IF(M10="Fair",T10+120,IF(M10="Neutral",T10+120,"")))))))) -> 43699 | W10: =IF(M10="Critical",IF(U10>10,"SLA Vencido","En SLA"),IF(M10="High",IF(U10>30,"SLA Vencido","En SLA"),IF(M10="Bad",IF(U10>30,"SLA Vencido","En SLA"),IF(M10="Medium",IF(U10>90,"SLA Vencido","En SLA"),IF(M10="Warm",IF(U10>90,"SLA Vencido","En SLA"),IF(M10="Low",IF(U10>120,"SLA Vencido","En SLA"),IF(M10="Fair",IF(U10>120,"SLA Vencido","En SLA"),IF(M10="Neutral",IF(U10>120,"SLA Vencido","En SLA"),"Error")))))))) -> SLA Vencido | X10: Waiver | Y10: 1ª Fecha: 21/12/2019 2ª Fecha: 13/04/2020 | Z10: 1ª Fecha: 30/04/2020 2ª Fecha: 30/06/2020 | AA10: 44025 | AB10: El activo "confirming.santander.com" permite el uso del algoritmo de cifrado 3DES | AC10: Se recomienda deshabilitar el uso del algoritmo de cifrado 3DES y reconfigurar el servicio afectado para restringir los métodos de cifrado a aquellos que ofrezcan un nivel de seguridad alto. | AD10: El host analizado permite el uso de cifrados SSL de seguridad media basados en el algoritmo de cifrado 3DES. Este algoritmo de cifrado es vulnerable a un ataque conocido como Sweet32. Debido a que 3DES tiene un tamaño de bloque de 64 bits, existe una alta probabilidad de que, dados los bloques 2^32, se encuentren dos bloques que colisionen. Una vez que se ha encontrado una colisión entre dos bloques en texto cifrado, se puede averiguar cómo se relacionan los bloques en texto plano correspondientes. Este conocimiento combinado con varios otros atributos permite el descifrado del texto cifrado. | AE10: 44012 | AF10: Fue dado de baja el Lunes 13 de Julio del 2020 | AH10: =IFERROR(VLOOKUP(H10,hoja1!A:A,1,),"N/A") -> N/A
A11: 10 | B11: BSNC | C11: Deloitte | D11: Wep App | E11: BSNC-2019-019 | G11: Web de Proveedores | H11: MAN-73a2e322 | I11: CO-19-MANU-01-CO-004 | J11: Módulo SSL/TLS Diffie-Hellman < = 1024 Bits (LogJam) | L11: Dismissed | M11: Medium | N11: 4 | P11: 170.169.33.48 | Q11: confirming.santander.com.co | T11: 43609 | U11: =TODAY()-T11 -> 2600 | V11: =IF(M11="Critical",T11+10,IF(M11="High",T11+30,IF(M11="Bad",T11+30,IF(M11="Medium",T11+90,IF(M11="Warm",T11+90,IF(M11="Low",T11+120,IF(M11="Fair",T11+120,IF(M11="Neutral",T11+120,"")))))))) -> 43699 | W11: =IF(M11="Critical",IF(U11>10,"SLA Vencido","En SLA"),IF(M11="High",IF(U11>30,"SLA Vencido","En SLA"),IF(M11="Bad",IF(U11>30,"SLA Vencido","En SLA"),IF(M11="Medium",IF(U11>90,"SLA Vencido","En SLA"),IF(M11="Warm",IF(U11>90,"SLA Vencido","En SLA"),IF(M11="Low",IF(U11>120,"SLA Vencido","En SLA"),IF(M11="Fair",IF(U11>120,"SLA Vencido","En SLA"),IF(M11="Neutral",IF(U11>120,"SLA Vencido","En SLA"),"Error")))))))) -> SLA Vencido | X11: Waiver | Y11: 1ª Fecha: 21/12/2019 2ª Fecha: 13/04/2020 | Z11: 1ª Fecha: 30/04/2020 2ª Fecha: 30/06/2020 | AA11: 44025 | AB11: El activo "confirming.santander.com.co" es vulnerable a LogJam | AC11: Se recomienda configurar el servicio para usar un único módulo de Diffie-Hellman de 2048 bits o mayor. | AD11: El servidor permite conexiones SSL/TLS con uno o más modulos Diffie-Hellman menor o igual a 1024 bits. A través de Criptoanálisis, un usuario malintencionado podría ser capaz de encontrar la clave compartida en un corto periodo de tiempo (dependiendo del tamaño del módulo y de los recursos del atacante). Esto podría permitir al atacante recupera la información en texto plano o violar la integridad de las conexiones. | AE11: 44012 | AF11: Fue dado de baja el Lunes 13 de Julio del 2020 | AH11: =IFERROR(VLOOKUP(H11,hoja1!A:A,1,),"N/A") -> N/A
A12: 11 | B12: BSNC | C12: Deloitte | D12: Wep App | E12: BSNC-2019-015 | G12: Web de Proveedores | H12: MAN-a6e6676b | I12: CO-174-001 | J12: Activo vulnerable a Lucky13 (CVE-2013-0169) | L12: Dismissed | M12: Low | N12: 3.7 | O12: CVE-2013-0169 | P12: 170.169.33.48 | Q12: confirming.santander.com.co | R12: 443 | T12: 43207 | U12: =TODAY()-T12 -> 3002 | V12: =IF(M12="Critical",T12+10,IF(M12="High",T12+30,IF(M12="Bad",T12+30,IF(M12="Medium",T12+90,IF(M12="Warm",T12+90,IF(M12="Low",T12+120,IF(M12="Fair",T12+120,IF(M12="Neutral",T12+120,"")))))))) -> 43327 | W12: =IF(M12="Critical",IF(U12>10,"SLA Vencido","En SLA"),IF(M12="High",IF(U12>30,"SLA Vencido","En SLA"),IF(M12="Bad",IF(U12>30,"SLA Vencido","En SLA"),IF(M12="Medium",IF(U12>90,"SLA Vencido","En SLA"),IF(M12="Warm",IF(U12>90,"SLA Vencido","En SLA"),IF(M12="Low",IF(U12>120,"SLA Vencido","En SLA"),IF(M12="Fair",IF(U12>120,"SLA Vencido","En SLA"),IF(M12="Neutral",IF(U12>120,"SLA Vencido","En SLA"),"Error")))))))) -> SLA Vencido | X12: Waiver | Y12: 1ª Fecha: 21/12/2019 2ª Fecha: 13/04/2020 | Z12: 1ª Fecha: 30/04/2020 2ª Fecha: 30/06/2020 | AA12: 44025 | AB12: se ha detectado que el certificado del servidor (www.santander.com.co) ofrece algortimos de cifrado en modo bloque (CBC) | AC12: Deshabilitar el uso de algoritmos cifrado de bloques (CBC) en el servidor remoto. | AD12: El servidor usa algoritmos de cifrado CBC sobre TLS por lo que está afectado por una vulnerabilidad conocida como Lucky13. Según se ha podido determinar el servidor utiliza cifrados CBC sobre TLS, lo que permitiría a un atacante situado en mitad de las comunicaciones (MiTM) implementar una variante del ataque conocido como Padding de Oracle (POODLE). CVEs Asociados •CVE-2013-0169 | AE12: 44012 | AF12: Fue dado de baja el Lunes 13 de Julio del 2020 | AH12: =IFERROR(VLOOKUP(H12,hoja1!A:A,1,),"N/A") -> N/A
A13: 12 | B13: BSNC | C13: Deloitte | D13: Wep App | E13: BSNC-2019-010 | G13: Web de Proveedores | H13: MAN-647bb2ad | I13: CO-19-MANU-02-AP-007 | J13: Ausencia de Cabecera CSP (Content-security-Policy) | L13: Dismissed | M13: Low | N13: 3.5 | P13: 170.169.33.48 | Q13: confirming.santander.com.co | T13: 43784 | U13: =TODAY()-T13 -> 2425 | V13: =IF(M13="Critical",T13+10,IF(M13="High",T13+30,IF(M13="Bad",T13+30,IF(M13="Medium",T13+90,IF(M13="Warm",T13+90,IF(M13="Low",T13+120,IF(M13="Fair",T13+120,IF(M13="Neutral",T13+120,"")))))))) -> 43904 | W13: =IF(M13="Critical",IF(U13>10,"SLA Vencido","En SLA"),IF(M13="High",IF(U13>30,"SLA Vencido","En SLA"),IF(M13="Bad",IF(U13>30,"SLA Vencido","En SLA"),IF(M13="Medium",IF(U13>90,"SLA Vencido","En SLA"),IF(M13="Warm",IF(U13>90,"SLA Vencido","En SLA"),IF(M13="Low",IF(U13>120,"SLA Vencido","En SLA"),IF(M13="Fair",IF(U13>120,"SLA Vencido","En SLA"),IF(M13="Neutral",IF(U13>120,"SLA Vencido","En SLA"),"Error")))))))) -> SLA Vencido | X13: Waiver | Y13: 1ª Fecha: 21/12/2019 2ª Fecha: 13/04/2020 | Z13: 1ª Fecha: 30/04/2020 2ª Fecha: 30/06/2020 | AA13: 44025 | AB13: se ha identificado la ausencia de la cabecera CSP (Content_Security_Policy) mediante las cabeceras de respuesta http | AC13: Configure el servidor web para devolver la cabecera Content-Security-Policy HTTP. Es recomendable que se establezca la política “default-src ‘self’ para que el contenido provenga del mismo origen del sitio. Un ejemplo de la política sería: Content-Security-Policy: default-src 'self' | AD13: CSP (Content Security Policy) es una capa añadida de seguridad que ayuda a detectar y mitigar determinados tipos de ataques, incluyendo ataques Cross-Site Scripting (XSS) y de inyección de datos. Estos ataques se pueden utilizar para realizar todo tipo de técnicas, desde el robo de datos hasta site defacement, pasando por la distribución de malware. CSP proporciona una serie de cabeceras HTTP estándar que permiten que los propietarios de los sitios web declaren que fuentes de contenido se consideran legitimas para que los puedan usarlas. Por ejemplo, JavaScript, CSS, tramas HTML, fuentes, imágenes y archivos incrustables como applets Java, ActiveX y archivos de audio y vídeo. | AE13: 44012 | AF13: Fue dado de baja el Lunes 13 de Julio del 2020 | AH13: =IFERROR(VLOOKUP(H13,hoja1!A:A,1,),"N/A") -> N/A
A14: 13 | B14: BSNC | C14: Deloitte | D14: Wep App | E14: BSNC-2019-018 | G14: Web de Proveedores | H14: MAN-73a2e327 | I14: CO-19-MANU-01-AP-008 | J14: Fuga de información de rutas internas | L14: Dismissed | M14: Low | N14: 3.2 | P14: 170.169.33.48 | Q14: confirming.santander.com.co | T14: 43609 | U14: =TODAY()-T14 -> 2600 | V14: =IF(M14="Critical",T14+10,IF(M14="High",T14+30,IF(M14="Bad",T14+30,IF(M14="Medium",T14+90,IF(M14="Warm",T14+90,IF(M14="Low",T14+120,IF(M14="Fair",T14+120,IF(M14="Neutral",T14+120,"")))))))) -> 43729 | W14: =IF(M14="Critical",IF(U14>10,"SLA Vencido","En SLA"),IF(M14="High",IF(U14>30,"SLA Vencido","En SLA"),IF(M14="Bad",IF(U14>30,"SLA Vencido","En SLA"),IF(M14="Medium",IF(U14>90,"SLA Vencido","En SLA"),IF(M14="Warm",IF(U14>90,"SLA Vencido","En SLA"),IF(M14="Low",IF(U14>120,"SLA Vencido","En SLA"),IF(M14="Fair",IF(U14>120,"SLA Vencido","En SLA"),IF(M14="Neutral",IF(U14>120,"SLA Vencido","En SLA"),"Error")))))))) -> SLA Vencido | X14: Waiver | Y14: 1ª Fecha: 21/12/2019 2ª Fecha: 13/04/2020 | Z14: 1ª Fecha: 30/04/2020 2ª Fecha: 30/06/2020 | AA14: 44025 | AB14: Se ha detectado que la aplicación devuelve información acerca de rutas internas del sistema de ficheros del servidor. Esta información podría ser utilizada por un atacante con el objetivo de recabar información para ataques futuros. | AC14: Se recomienda evitar que la aplicación devuelva al usuario información relativa al funcionamiento interno del servidor, como pueden ser rutas internas o ubicación de ficheros o directorios dentro del mismo. Para ello, se recomienda modificar la página de error "404 not found". | AD14: Se ha detectado que la aplicación devuelve información acerca de rutas internas del sistema de ficheros del servidor. Esta información podría ser utilizada por un atacante con el objetivo de recabar información para ataques futuros. | AE14: 44012 | AF14: Fue dado de baja el Lunes 13 de Julio del 2020 | AH14: =IFERROR(VLOOKUP(H14,hoja1!A:A,1,),"N/A") -> N/A
A15: 14 | B15: BSNC | C15: Deloitte | D15: Wep App | E15: BSNC-2019-020 | G15: Web de Proveedores | H15: MAN-73a2e326 | I15: CO-19-MANU-01-CO-007 | J15: Suite de cifrado SSL de 64-bit Soportada (SWEET32) | L15: Dismissed | M15: Low | N15: 2.5999999 | P15: 170.169.33.48 | Q15: confirming.santander.com.co | T15: 43609 | U15: =TODAY()-T15 -> 2600 | V15: =IF(M15="Critical",T15+10,IF(M15="High",T15+30,IF(M15="Bad",T15+30,IF(M15="Medium",T15+90,IF(M15="Warm",T15+90,IF(M15="Low",T15+120,IF(M15="Fair",T15+120,IF(M15="Neutral",T15+120,"")))))))) -> 43729 | W15: =IF(M15="Critical",IF(U15>10,"SLA Vencido","En SLA"),IF(M15="High",IF(U15>30,"SLA Vencido","En SLA"),IF(M15="Bad",IF(U15>30,"SLA Vencido","En SLA"),IF(M15="Medium",IF(U15>90,"SLA Vencido","En SLA"),IF(M15="Warm",IF(U15>90,"SLA Vencido","En SLA"),IF(M15="Low",IF(U15>120,"SLA Vencido","En SLA"),IF(M15="Fair",IF(U15>120,"SLA Vencido","En SLA"),IF(M15="Neutral",IF(U15>120,"SLA Vencido","En SLA"),"Error")))))))) -> SLA Vencido | X15: Waiver | Y15: 1ª Fecha: 21/12/2019 2ª Fecha: 13/04/2020 | Z15: 1ª Fecha: 30/04/2020 2ª Fecha: 30/06/2020 | AA15: 44025 | AB15: El activo "confirming.santander.com.co " es vulnerable a SWEET32 | AC15: Se recomienda reconfigurar la aplicación afectada, si es posible, para evitar el uso de todos los cifrados de bloques de 64 bits. Como alternativa, coloque limitaciones en el número de solicitudes que se permiten procesar sobre la misma conexión TLS para mitigar esta vulnerabilidad. | AD15: El servidor admite el uso de un cifrado de bloque con bloques de 64 bits en una o más suites de cifrado. Está afectado por una vulnerabilidad, conocida como SWEET32, debido al uso de cifrados débiles. Un ataque Man in the Middle con recursos suficientes puede explotar esta vulnerabilidad. | AE15: 44012 | AF15: Fue dado de baja el Lunes 13 de Julio del 2020 | AH15: =IFERROR(VLOOKUP(H15,hoja1!A:A,1,),"N/A") -> N/A
A16: 15 | B16: BSNC | C16: Deloitte | D16: Wep App | E16: A2 20190509_2.3.1.c_CO_20200728_N_06 | G16: Confirming & Factoring\Bot | H16: MAN-18af2323 | I16: CO-19-AUTO-02-CO-002 | J16: Uso de librerias desactualizadas | L16: Solved | M16: Medium | N16: 5.5999999 | P16: 64.76.90.137 | Q16: confirming-factoring.santander.com.co | R16: 443 | T16: 43719 | U16: =TODAY()-T16 -> 2490 | V16: =IF(M16="Critical",T16+10,IF(M16="High",T16+30,IF(M16="Bad",T16+30,IF(M16="Medium",T16+90,IF(M16="Warm",T16+90,IF(M16="Low",T16+120,IF(M16="Fair",T16+120,IF(M16="Neutral",T16+120,"")))))))) -> 43809 | W16: =IF(M16="Critical",IF(U16>10,"SLA Vencido","En SLA"),IF(M16="High",IF(U16>30,"SLA Vencido","En SLA"),IF(M16="Bad",IF(U16>30,"SLA Vencido","En SLA"),IF(M16="Medium",IF(U16>90,"SLA Vencido","En SLA"),IF(M16="Warm",IF(U16>90,"SLA Vencido","En SLA"),IF(M16="Low",IF(U16>120,"SLA Vencido","En SLA"),IF(M16="Fair",IF(U16>120,"SLA Vencido","En SLA"),IF(M16="Neutral",IF(U16>120,"SLA Vencido","En SLA"),"Error")))))))) -> SLA Vencido | X16: Waiver | Y16: 1ª Fecha: 28/12/2020 | Z16: 1ª Fecha: 18/12/2020 | AA16: 44089 | AB16: Se encuentra el uso de funciones de Zoom Search Engine 5.0: /factoring/ayuda/zoom_search.js | AC16: Se recomienda utilizar versiones actualizadas del software y/o plataformas tecnológicas utilizadas, en caso de no ser posible aplicar todas las actualizaciones de seguridad publicadas para la versión utilizada. | AD16: El software o plataforma utilizada no se encuentra actualizado a la última versión disponible. Esto implica que podría ser susceptible de poder ser comprometido mediante vulnerabilidades conocidas que pudieran poner en riesgo el activo afectado. | AE16: Sin definir | AF16: Certificada | AG16: Jaime Orlando Vargas Martinez | AH16: =IFERROR(VLOOKUP(H16,hoja1!A:A,1,),"N/A") -> N/A
A17: 16 | B17: BSNC | C17: Deloitte | D17: Wep App | E17: A2 20190509_2.3.1.c_CO_20200728_N_05 | G17: Confirming & Factoring\Bot | H17: MAN-18af2329 | I17: CO-19-AUTO-02-CO-008 | J17: Renegociación segura de SSL iniciada por el cliente | L17: Solved | M17: Medium | N17: 4.3000002 | P17: 64.76.90.137 | Q17: confirming-factoring.santander.com.co | R17: 443 | T17: 43719 | U17: =TODAY()-T17 -> 2490 | V17: =IF(M17="Critical",T17+10,IF(M17="High",T17+30,IF(M17="Bad",T17+30,IF(M17="Medium",T17+90,IF(M17="Warm",T17+90,IF(M17="Low",T17+120,IF(M17="Fair",T17+120,IF(M17="Neutral",T17+120,"")))))))) -> 43809 | W17: =IF(M17="Critical",IF(U17>10,"SLA Vencido","En SLA"),IF(M17="High",IF(U17>30,"SLA Vencido","En SLA"),IF(M17="Bad",IF(U17>30,"SLA Vencido","En SLA"),IF(M17="Medium",IF(U17>90,"SLA Vencido","En SLA"),IF(M17="Warm",IF(U17>90,"SLA Vencido","En SLA"),IF(M17="Low",IF(U17>120,"SLA Vencido","En SLA"),IF(M17="Fair",IF(U17>120,"SLA Vencido","En SLA"),IF(M17="Neutral",IF(U17>120,"SLA Vencido","En SLA"),"Error")))))))) -> SLA Vencido | X17: Waiver | Y17: 1ª Fecha: 28/12/2020 | Z17: 1ª Fecha: 18/12/2020 | AA17: 44181 | AC17: Se recomienda actualizar el servidor web a la última versión, ya que las últimas versiones de Apache y nginx no permiten la renegociación SSL iniciada por el cliente. | AD17: El proceso de negociación del cifrado SSL utiliza significativamente más recursos en el servidor que en el cliente. Si el cliente puede iniciar el proceso de renegociación, un atacante puede hacer que el servidor deje de estar disponible con un ataque de denegación de servicio. | AF17: Certificada | AG17: Jaime Orlando Vargas Martinez | AH17: =IFERROR(VLOOKUP(H17,hoja1!A:A,1,),"N/A") -> N/A
A18: 17 | B18: BSNC | C18: Deloitte | D18: Wep App | E18: A2 20190509_2.3.1.c_CO_20200728_N_03 | G18: Confirming & Factoring\Bot | H18: MAN-647bb2aa | I18: CO-19-MANU-02-AP-004 | J18: Librerías de JavaScript desactualizadas | L18: Solved | M18: Low | N18: 3.5 | P18: 64.76.90.137 | Q18: confirming-factoring.santander.com.co | T18: 43784 | U18: =TODAY()-T18 -> 2425 | V18: =IF(M18="Critical",T18+10,IF(M18="High",T18+30,IF(M18="Bad",T18+30,IF(M18="Medium",T18+90,IF(M18="Warm",T18+90,IF(M18="Low",T18+120,IF(M18="Fair",T18+120,IF(M18="Neutral",T18+120,"")))))))) -> 43904 | W18: =IF(M18="Critical",IF(U18>10,"SLA Vencido","En SLA"),IF(M18="High",IF(U18>30,"SLA Vencido","En SLA"),IF(M18="Bad",IF(U18>30,"SLA Vencido","En SLA"),IF(M18="Medium",IF(U18>90,"SLA Vencido","En SLA"),IF(M18="Warm",IF(U18>90,"SLA Vencido","En SLA"),IF(M18="Low",IF(U18>120,"SLA Vencido","En SLA"),IF(M18="Fair",IF(U18>120,"SLA Vencido","En SLA"),IF(M18="Neutral",IF(U18>120,"SLA Vencido","En SLA"),"Error")))))))) -> SLA Vencido | X18: Waiver | Y18: 1ª Fecha: 28/12/2020 | Z18: 1ª Fecha: 18/12/2020 | AA18: 44235 | AB18: Durante la auditoria se ha identificado la librería de JavaScript jQuery en su versión 1.3.2 la cual contiene vulnerabilidades, con CVE asociado, conocidas como:  CVE-2019-11358  CVE-2016-10707  CVE-2016-7103  CVE-2015-9251  CVE-2014-6071  CVE-2012-6708  CVE-2011-4969  CVE-2007-2379 Adicionalmente, se ha identificado el Framework de JavaScript “Prototype” en su versión 1.6.0.3 la cual contiene vulnerabilidades, con CVE asociado, conocidas como:  CVE-2008-7220  CVE-2007-2383 | AC18: Se recomienda analizar la posibilidad de actualizar la librería afectada a la última versión disponible. En concreto:  Prototype. Última versión estable 1.7.3 (http://prototypejs.org/)  jQuery. Última versión estable 3.4.1 (https://jquery.com/download/) Adicionalmente se recomienda realizar el monitoreo regular de las actualizaciones de las librerías en uso para todas las aplicaciones y asegurarse de instalarlas en un tiempo prudencial. | AD18: Un individuo malicioso podría comprometer con mayor facilidad las librerías afectadas, ya que las versiones observadas poseen vulnerabilidades y/o debilidades de seguridad previamente reportadas. Las vulnerabilidades mencionadas son de conocimiento público y los detalles de las mismas se encuentran disponibles. En consecuencia, un individuo malicioso podría intentar explotarlas para comprometer a los usuarios de la aplicación. | AE18: 44219 | AF18: Certificada | AG18: Jaime Orlando Vargas Martinez | AH18: =IFERROR(VLOOKUP(H18,hoja1!A:A,1,),"N/A") -> N/A
A19: 18 | B19: BSNC | C19: Deloitte | D19: Wep App | E19: A2 20190509_2.3.1.c_CO_20200728_N_04 | G19: Confirming & Factoring\Bot | H19: MAN-647bb2ab | I19: CO-19-MANU-02-AP-005 | J19: Errores no controlados | L19: Solved | M19: Low | N19: 3.5 | P19: 64.76.90.137 | Q19: confirming-factoring.santander.com.co | T19: 43784 | U19: =TODAY()-T19 -> 2425 | V19: =IF(M19="Critical",T19+10,IF(M19="High",T19+30,IF(M19="Bad",T19+30,IF(M19="Medium",T19+90,IF(M19="Warm",T19+90,IF(M19="Low",T19+120,IF(M19="Fair",T19+120,IF(M19="Neutral",T19+120,"")))))))) -> 43904 | W19: =IF(M19="Critical",IF(U19>10,"SLA Vencido","En SLA"),IF(M19="High",IF(U19>30,"SLA Vencido","En SLA"),IF(M19="Bad",IF(U19>30,"SLA Vencido","En SLA"),IF(M19="Medium",IF(U19>90,"SLA Vencido","En SLA"),IF(M19="Warm",IF(U19>90,"SLA Vencido","En SLA"),IF(M19="Low",IF(U19>120,"SLA Vencido","En SLA"),IF(M19="Fair",IF(U19>120,"SLA Vencido","En SLA"),IF(M19="Neutral",IF(U19>120,"SLA Vencido","En SLA"),"Error")))))))) -> SLA Vencido | X19: Waiver | Y19: 1ª Fecha: 28/12/2020 | Z19: 1ª Fecha: 18/12/2020 | AA19: 44089 | AB19: se ha identificado que, al modificar la petición original, el servidor responde con un error, mostrando una función interna de la aplicación. En concreto:  https://confirming-factoring.santander.com.co  Menú: Consultar ejecuciones Generales /Procesos Automáticos Al realizar una búsqueda, se para la petición mediante un proxy intermedio (BurpSuite) y se modifica el campo “formSearchCiclo%3Afecha_desdeField%3Aecha_inicioInputCurrentDate” introduciendo un valor no esperado por la aplicación, por ejemplo, una comilla simple, la aplicación responde mostrando información interna de la aplicación, en concreto una función de Java | AC19: Se deben controlar todas las entradas o valores que el aplicativo recibe por parte del cliente, y realizar un tratamiento seguro de sus valores evitando proporcionar información útil a un posible atacante. Adicionalmente para no proporcionar información al atacante se recomienda personalizar las páginas de error para que no sean descriptivas. | AD19: El servidor Web al recibir una petición no esperada reacciona mostrando una página de error que revela información sensible de la plataforma subyacente. Con esta información un atacante puede realizar ataques dirigidos con mayor criticidad y éxito sobre los sistemas y aplicaciones. | AE19: Sin definir | AF19: Certificada | AG19: Jaime Orlando Vargas Martinez | AH19: =IFERROR(VLOOKUP(H19,hoja1!A:A,1,),"N/A") -> N/A
A20: 19 | B20: BSNC | C20: Deloitte | D20: Wep App | E20: BSNC-2019-101 | G20: Portal Web | H20: MAN-4c3ceca0 | I20: CO-19-MANU-01-VE-009 | J20: Librerias de Javascript vulnerables | L20: Solved | M20: Critical | N20: 7.6999998 | P20: 170.169.33.93 | Q20: www.santander.com.co | R20: 443 | T20: 43697 | U20: =TODAY()-T20 -> 2512 | V20: =IF(M20="Critical",T20+10,IF(M20="High",T20+30,IF(M20="Bad",T20+30,IF(M20="Medium",T20+90,IF(M20="Warm",T20+90,IF(M20="Low",T20+120,IF(M20="Fair",T20+120,IF(M20="Neutral",T20+120,"")))))))) -> 43707 | W20: =IF(M20="Critical",IF(U20>10,"SLA Vencido","En SLA"),IF(M20="High",IF(U20>30,"SLA Vencido","En SLA"),IF(M20="Bad",IF(U20>30,"SLA Vencido","En SLA"),IF(M20="Medium",IF(U20>90,"SLA Vencido","En SLA"),IF(M20="Warm",IF(U20>90,"SLA Vencido","En SLA"),IF(M20="Low",IF(U20>120,"SLA Vencido","En SLA"),IF(M20="Fair",IF(U20>120,"SLA Vencido","En SLA"),IF(M20="Neutral",IF(U20>120,"SLA Vencido","En SLA"),"Error")))))))) -> SLA Vencido | X20: Waiver | Y20: 1ª Fecha: 2ª Fecha: | Z20: 1ª Fecha: 2ª Fecha:23/08/2020 | AA20: 44117 | AB20: La confirmación del uso de una versión vulnerable de la biblioteca javascript Https://www.santander.com.co/js/jquery-1.10,2.min.js Version: Jquery 1.10.2 | AC20: Actualizar las librerias de JavaScript a la última versión | AD20: Se detectaron bibliotecas Java Script Jquery obsoletas, las cuales pueden ser explotadas mediante secuencias de comandos entre sitios (XSS). | AE20: 44119 | AF20: Certificada | AG20: Jaime Orlando Vargas Martinez | AH20: =IFERROR(VLOOKUP(H20,hoja1!A:A,1,),"N/A") -> N/A
A21: 20 | B21: BSNC | C21: Deloitte | D21: Wep App | E21: A2 20190509_2.3.1.c_CO_20200611_R | F21: BSNC-2019-102 | G21: Portal Web | H21: MAN-4c3ced42 | I21: CO-19-MANU-01-VE-010 | J21: Librerias de Bootstrap vulnerables | L21: Solved | M21: Critical | N21: 7.6999998 | P21: 170.169.33.93 | Q21: www.santander.com.co | R21: 443 | T21: 43700 | U21: =TODAY()-T21 -> 2509 | V21: =IF(M21="Critical",T21+10,IF(M21="High",T21+30,IF(M21="Bad",T21+30,IF(M21="Medium",T21+90,IF(M21="Warm",T21+90,IF(M21="Low",T21+120,IF(M21="Fair",T21+120,IF(M21="Neutral",T21+120,"")))))))) -> 43710 | W21: =IF(M21="Critical",IF(U21>10,"SLA Vencido","En SLA"),IF(M21="High",IF(U21>30,"SLA Vencido","En SLA"),IF(M21="Bad",IF(U21>30,"SLA Vencido","En SLA"),IF(M21="Medium",IF(U21>90,"SLA Vencido","En SLA"),IF(M21="Warm",IF(U21>90,"SLA Vencido","En SLA"),IF(M21="Low",IF(U21>120,"SLA Vencido","En SLA"),IF(M21="Fair",IF(U21>120,"SLA Vencido","En SLA"),IF(M21="Neutral",IF(U21>120,"SLA Vencido","En SLA"),"Error")))))))) -> SLA Vencido | X21: Waiver | Y21: 1ª Fecha: 17/12/2019 2ª Fecha: 11/06/2020 | Z21: 1ª Fecha: 30/04/2020 2ª Fecha: 04/09/2020 | AA21: 44071 | AB21: La confirmación del uso de una versión vulnerable de la biblioteca javascript https://www.santander.com.co/js/bootstrap.min.js Versión:Bootstrap 3.0.2 | AC21: Actualizar las librerias de Bootstrap a la última versión | AD21: Se detectaron bibliotecas Bootstrap obsoletas, las cuales pueden ser explotadas mediante secuencias de comandos entre sitios (XSS). Esto puede conducir a diferentes problemas para los usuarios de la aplicación. | AE21: 44078 | AF21: Certificada | AG21: Jaime Orlando Vargas Martinez | AH21: =IFERROR(VLOOKUP(H21,hoja1!A:A,1,),"N/A") -> N/A
A22: 21 | B22: BSNC | C22: Deloitte | D22: Wep App | G22: Portal Web | H22: MAN-647bb2a7 | I22: CO-19-MANU-02-AP-001 | J22: Información sensible en Metadatos de Ficheros | L22: Solved | M22: Medium | N22: 5 | P22: 170.169.33.93 | Q22: www.santander.com.co | T22: 43784 | U22: =TODAY()-T22 -> 2425 | V22: =IF(M22="Critical",T22+10,IF(M22="High",T22+30,IF(M22="Bad",T22+30,IF(M22="Medium",T22+90,IF(M22="Warm",T22+90,IF(M22="Low",T22+120,IF(M22="Fair",T22+120,IF(M22="Neutral",T22+120,"")))))))) -> 43874 | W22: =IF(M22="Critical",IF(U22>10,"SLA Vencido","En SLA"),IF(M22="High",IF(U22>30,"SLA Vencido","En SLA"),IF(M22="Bad",IF(U22>30,"SLA Vencido","En SLA"),IF(M22="Medium",IF(U22>90,"SLA Vencido","En SLA"),IF(M22="Warm",IF(U22>90,"SLA Vencido","En SLA"),IF(M22="Low",IF(U22>120,"SLA Vencido","En SLA"),IF(M22="Fair",IF(U22>120,"SLA Vencido","En SLA"),IF(M22="Neutral",IF(U22>120,"SLA Vencido","En SLA"),"Error")))))))) -> SLA Vencido | AA22: 44014 | AB22: Se ha evidenciado una serie de nombres de usuarios en los metadatos de los ficheros PDF, los cuales se han identificado dentro de las páginas webs del alcance. | AC22: Se recomienda eliminar toda la información contenida en los metadatos de los documentos generados y/o publicados en la aplicación. Adicionalmente, se recomienda implementar un procedimiento para controlar los documentos a publicar para garantizar que los mismos no contengan información sensible de la organización en sus metadatos. | AD22: Los metadatos de un fichero o documento pueden revelar tanta o más información que el contenido de las comunicaciones. Las fugas de información sensible son realizadas, en numerosas ocasiones, a través de los metadatos de los ficheros publicados, que desvelan entre otros datos, usuarios o nombres de personas de la empresa. | AE22: 44036 | AF22: Certificada | AG22: Jaime Orlando Vargas Martinez | AH22: =IFERROR(VLOOKUP(H22,hoja1!A:A,1,),"N/A") -> N/A
A23: 22 | B23: BSNC | C23: Deloitte | D23: Wep App | E23: BSNC-2020-002 | G23: Portal Web | H23: MAN-18af232a | I23: CO-19-AUTO-02-CO-007 | J23: Renegociación segura de SSL iniciada por el cliente | L23: Dismissed | M23: Medium | N23: 4.3000002 | P23: 170.169.33.93 | Q23: www.santander.com.co | R23: 443 | T23: 43719 | U23: =TODAY()-T23 -> 2490 | V23: =IF(M23="Critical",T23+10,IF(M23="High",T23+30,IF(M23="Bad",T23+30,IF(M23="Medium",T23+90,IF(M23="Warm",T23+90,IF(M23="Low",T23+120,IF(M23="Fair",T23+120,IF(M23="Neutral",T23+120,"")))))))) -> 43809 | W23: =IF(M23="Critical",IF(U23>10,"SLA Vencido","En SLA"),IF(M23="High",IF(U23>30,"SLA Vencido","En SLA"),IF(M23="Bad",IF(U23>30,"SLA Vencido","En SLA"),IF(M23="Medium",IF(U23>90,"SLA Vencido","En SLA"),IF(M23="Warm",IF(U23>90,"SLA Vencido","En SLA"),IF(M23="Low",IF(U23>120,"SLA Vencido","En SLA"),IF(M23="Fair",IF(U23>120,"SLA Vencido","En SLA"),IF(M23="Neutral",IF(U23>120,"SLA Vencido","En SLA"),"Error")))))))) -> SLA Vencido | AA23: 43917 | AC23: Se recomienda actualizar el servidor web a la última versión, ya que las últimas versiones de Apache y nginx no permiten la renegociación SSL iniciada por el cliente. | AD23: El proceso de negociación del cifrado SSL utiliza significativamente más recursos en el servidor que en el cliente. Si el cliente puede iniciar el proceso de renegociación, un atacante puede hacer que el servidor deje de estar disponible con un ataque de denegación de servicio. | AF23: Corresponde a un Falso Positivo | AG23: Jaime Orlando Vargas Martinez | AH23: =IFERROR(VLOOKUP(H23,hoja1!A:A,1,),"N/A") -> N/A
A24: 23 | B24: BSNC | C24: Deloitte | D24: Wep App | E24: A2 20190509_2.3.1.c_CO_20200612_N_08 | G24: Portal Web | H24: MAN-647bb2ac | I24: CO-19-MANU-02-AP-006 | J24: Métodos HTTP no seguros permitidos | L24: Solved | M24: Low | N24: 3.5 | P24: 170.169.33.93 | Q24: www.santander.com.co | T24: 43784 | U24: =TODAY()-T24 -> 2425 | V24: =IF(M24="Critical",T24+10,IF(M24="High",T24+30,IF(M24="Bad",T24+30,IF(M24="Medium",T24+90,IF(M24="Warm",T24+90,IF(M24="Low",T24+120,IF(M24="Fair",T24+120,IF(M24="Neutral",T24+120,"")))))))) -> 43904 | W24: =IF(M24="Critical",IF(U24>10,"SLA Vencido","En SLA"),IF(M24="High",IF(U24>30,"SLA Vencido","En SLA"),IF(M24="Bad",IF(U24>30,"SLA Vencido","En SLA"),IF(M24="Medium",IF(U24>90,"SLA Vencido","En SLA"),IF(M24="Warm",IF(U24>90,"SLA Vencido","En SLA"),IF(M24="Low",IF(U24>120,"SLA Vencido","En SLA"),IF(M24="Fair",IF(U24>120,"SLA Vencido","En SLA"),IF(M24="Neutral",IF(U24>120,"SLA Vencido","En SLA"),"Error")))))))) -> SLA Vencido | X24: Waiver | Y24: 1ª Fecha: 12/06/2020 | Z24: 2ª Fecha: 13/11/2020 | AA24: 44117 | AB24: se han identificado métodos http los cuales no son seguros y podrían suponer un riesgo para el servidor, en concreto, se han detectado los métodos: PUT, DELETE, TRACE y PATCH. | AC24: Se recomienda analizar la posibilidad de evaluar si el método HTTP extendido identificado es requerido por razones de negocio y deshabilitarlo en caso de no ser requerido. Asimismo, se recomienda analizar la posibilidad de revisar los estándares de configuración de los sistemas, para asegurar que métodos potencialmente peligrosos se encuentren deshabilitados y asegurar su consistencia en toda la organización. | AD24: Los servidores Web utilizan ciertos métodos o funciones propias del protocolo HTTP para funcionar siendo los más utilizados GET, POST y HEAD. Como resultado del análisis de los servicios Web internos se ha detectado que los recursos afectados permiten utilizar métodos HTTP adicionales (OPTIONS, TRACE, GET, HEAD, DELETE, PUT, POST, COPY, MOVE, MKCOL, PROPFIND, PROPPATCH, LOCK, UNLOCK, SEARCH) los cuales podrían no ser requeridos debilitando la seguridad de dichos servicios Web. | AE24: 44148 | AF24: Certificada | AG24: Jaime Orlando Vargas Martinez | AH24: =IFERROR(VLOOKUP(H24,hoja1!A:A,1,),"N/A") -> N/A
A25: 24 | B25: BSNC | C25: Deloitte | D25: Wep App | E25: BSNC-2020-001 | G25: Portal Web | H25: MAN-73a2e325 | I25: CO-19-MANU-01-AP-006 | J25: Fuga de información de aplicación y versión | L25: Solved | M25: Low | N25: 3.2 | P25: 170.169.33.93 | Q25: www.santander.com.co | T25: 43609 | U25: =TODAY()-T25 -> 2600 | V25: =IF(M25="Critical",T25+10,IF(M25="High",T25+30,IF(M25="Bad",T25+30,IF(M25="Medium",T25+90,IF(M25="Warm",T25+90,IF(M25="Low",T25+120,IF(M25="Fair",T25+120,IF(M25="Neutral",T25+120,"")))))))) -> 43729 | W25: =IF(M25="Critical",IF(U25>10,"SLA Vencido","En SLA"),IF(M25="High",IF(U25>30,"SLA Vencido","En SLA"),IF(M25="Bad",IF(U25>30,"SLA Vencido","En SLA"),IF(M25="Medium",IF(U25>90,"SLA Vencido","En SLA"),IF(M25="Warm",IF(U25>90,"SLA Vencido","En SLA"),IF(M25="Low",IF(U25>120,"SLA Vencido","En SLA"),IF(M25="Fair",IF(U25>120,"SLA Vencido","En SLA"),IF(M25="Neutral",IF(U25>120,"SLA Vencido","En SLA"),"Error")))))))) -> SLA Vencido | AA25: 43908 | AB25: Durante las pruebas realizadas, se ha comprobado que la página de error "404 not found" por defecto de Tomcat muestra información interna acerca de la aplicación utilizada. | AC25: Se recomienda modificar la página por defecto "404 not found" para evitar que la aplicación devuelva al usuario información relativa a la naturaleza y versión de la misma. | AD25: Se ha detectado que la aplicación devuelve información acerca de la versión y aplicación utilizadas. Esta información podría ser utilizada por un atacante con el objetivo de recabar información para ataques futuros. | AF25: Certificada | AG25: Jaime Orlando Vargas Martinez | AH25: =IFERROR(VLOOKUP(H25,hoja1!A:A,1,),"N/A") -> N/A
A26: 25 | B26: BSNC | C26: Deloitte | D26: Wep App | E26: BSNC-2020-003 | G26: Portal Web | H26: MAN-18af232d | I26: CO-19-AUTO-02-CO-010 | J26: Ausencia de HTTP Strict Transport Security (HSTS) | L26: Solved | M26: Low | N26: 3.0999999 | P26: 170.169.33.93 | Q26: www.santander.com.co | R26: 443 | T26: 43719 | U26: =TODAY()-T26 -> 2490 | V26: =IF(M26="Critical",T26+10,IF(M26="High",T26+30,IF(M26="Bad",T26+30,IF(M26="Medium",T26+90,IF(M26="Warm",T26+90,IF(M26="Low",T26+120,IF(M26="Fair",T26+120,IF(M26="Neutral",T26+120,"")))))))) -> 43839 | W26: =IF(M26="Critical",IF(U26>10,"SLA Vencido","En SLA"),IF(M26="High",IF(U26>30,"SLA Vencido","En SLA"),IF(M26="Bad",IF(U26>30,"SLA Vencido","En SLA"),IF(M26="Medium",IF(U26>90,"SLA Vencido","En SLA"),IF(M26="Warm",IF(U26>90,"SLA Vencido","En SLA"),IF(M26="Low",IF(U26>120,"SLA Vencido","En SLA"),IF(M26="Fair",IF(U26>120,"SLA Vencido","En SLA"),IF(M26="Neutral",IF(U26>120,"SLA Vencido","En SLA"),"Error")))))))) -> SLA Vencido | AA26: 43921 | AB26: Las url afectadas son: /js/bootstrap-paginator.js /js/cookiesUtils.js /recursos/imagenes/home_142.jpg /recursos/imagenes/home_63.jpg | AC26: Se recomienda configurar el servidor remoto para que en las cabeceras de respuesta se incluya la cabecera HSTS incluyendo un período de validez estimado de la política en el propio navegador. | AD26: La política HSTS o HTTP Strict Transport Security es un mecanismo soportado por los principales servidores web –Apache, NGNIX- y la mayoría de navegadores, que reduce las posibilidades de que un atacante pueda interceptar nuestras comunicaciones y recopilar cookies y datos similares intercambiados durante la sesión. El estándar permite que el servidor y el navegador web interactúen de manera más fiable, empleando protocolos de transporte cifrados como TSL/SSL. Así, es capaz de acabar con variados ataques de red y también con algunos errores cometidos por los desarrolladores de los distintos sites (por ejemplo, el uso de conexiones no seguras para descargar recursos de la web). De esta manera y al margen de determinar cómo deben actuar el navegador y el servidor, HSTS incorpora una cabecera HSTS (Strict-Transport-Security), que fuerza a utilizar un canal cifrado, HTTPS, para la comunicación entre el navegador del usuario y el servidor. A partir del momento en el que el navegador recibe una cabecera HSTS en las cabeceras de respuesta del servidor, todas las peticiones a este dominio y subdominios serán realizadas mediante HTTPS. Asimismo, las cabeceras HSTS, quedarán almacenadas en el navegador (en forma de lista), algo que se aplicará durante un tiempo determinado que se establece en la propia cabecera de respuesta. | AF26: Certificada | AG26: Jaime Orlando Vargas Martinez | AH26: =IFERROR(VLOOKUP(H26,hoja1!A:A,1,),"N/A") -> N/A
A27: 26 | B27: BSNC | C27: Qualys | D27: Wep App | E27: BSNC-2020-004 | G27: Web de Proveedores | H27: QA-1701663040 | J27: SSL/TLS Server supports TLSv1.0 | L27: Dismissed | M27: Medium | N27: Vendor | P27: 170.169.33.48 | Q27: confirming.santander.com.co | R27: 443 | S27: TCP | T27: 43816 | U27: =TODAY()-T27 -> 2393 | V27: =IF(M27="Critical",T27+10,IF(M27="High",T27+30,IF(M27="Bad",T27+30,IF(M27="Medium",T27+90,IF(M27="Warm",T27+90,IF(M27="Low",T27+120,IF(M27="Fair",T27+120,IF(M27="Neutral",T27+120,"")))))))) -> 43906 | W27: =IF(M27="Critical",IF(U27>10,"SLA Vencido","En SLA"),IF(M27="High",IF(U27>30,"SLA Vencido","En SLA"),IF(M27="Bad",IF(U27>30,"SLA Vencido","En SLA"),IF(M27="Medium",IF(U27>90,"SLA Vencido","En SLA"),IF(M27="Warm",IF(U27>90,"SLA Vencido","En SLA"),IF(M27="Low",IF(U27>120,"SLA Vencido","En SLA"),IF(M27="Fair",IF(U27>120,"SLA Vencido","En SLA"),IF(M27="Neutral",IF(U27>120,"SLA Vencido","En SLA"),"Error")))))))) -> SLA Vencido | X27: Waiver | Y27: 1ª Fecha: 2ª Fecha: | Z27: 1ª Fecha: 2ª Fecha: | AA27: 44025 | AC27: Deshabilite el uso del protocolo TLSv1.0 a favor de un protocolo criptográficamente más fuerte como TLSv1.2. Los siguientes comandos de openssl se pueden usar para hacer una prueba manual: openssl s_client -connect ip: puerto -tls1 Si la prueba es exitosa, entonces el objetivo | AD27: Un atacante puede explotar defectos criptográficos para realizar ataques de tipo intermediario o para descifrar comunicaciones. <P> Por ejemplo: un atacante podría forzar una degradación del protocolo TLS al antiguo protocolo SSLv3.0 y explotar el POODLE vulnerabi | AE27: 44012 | AF27: Fue dado de baja el Lunes 13 de Julio del 2020 | AH27: =IFERROR(VLOOKUP(H27,hoja1!A:A,1,),"N/A") -> N/A
A28: 27 | B28: BSNC | C28: Qualys | D28: Wep App | G28: Confirming & Factoring\Bot | H28: QA-94188246370 | J28: SSL Certificate - Subject Common Name Does Not Match Server FQDN | L28: Dismissed | M28: Medium | N28: Vendor | P28: 94188208248 | Q28: confirming-factoring.santander.com.co | R28: 443 | S28: TCP | T28: 43816 | U28: =TODAY()-T28 -> 2393 | V28: =IF(M28="Critical",T28+10,IF(M28="High",T28+30,IF(M28="Bad",T28+30,IF(M28="Medium",T28+90,IF(M28="Warm",T28+90,IF(M28="Low",T28+120,IF(M28="Fair",T28+120,IF(M28="Neutral",T28+120,"")))))))) -> 43906 | W28: =IF(M28="Critical",IF(U28>10,"SLA Vencido","En SLA"),IF(M28="High",IF(U28>30,"SLA Vencido","En SLA"),IF(M28="Bad",IF(U28>30,"SLA Vencido","En SLA"),IF(M28="Medium",IF(U28>90,"SLA Vencido","En SLA"),IF(M28="Warm",IF(U28>90,"SLA Vencido","En SLA"),IF(M28="Low",IF(U28>120,"SLA Vencido","En SLA"),IF(M28="Fair",IF(U28>120,"SLA Vencido","En SLA"),IF(M28="Neutral",IF(U28>120,"SLA Vencido","En SLA"),"Error")))))))) -> SLA Vencido | AB28: Vulnerabilidad presente, debido a que el certificado presente por IP no coincide con el del FQDN (confirming-factoring.santander.com.co), por este motivo se confirma la vulnerabilidad, que conllevaría a la posible situación de cifrado sin autenticación | AC28: Instale un certificado de servidor cuyo Asunto commonName o subjectAltName coincida con el FQDN del servidor. | AD28: Un atacante man-in-the-middle puede explotar esta vulnerabilidad junto con un ataque de envenenamiento de caché DNS para atraer al cliente a otro servidor y luego robar toda la comunicación de cifrado. | AF28: Corresponde a un Falso Positivo | AG28: Jaime Orlando Vargas Martinez | AH28: =IFERROR(VLOOKUP(H28,hoja1!A:A,1,),"N/A") -> N/A
A29: 28 | B29: BSNC | C29: Qualys | D29: Wep App | G29: Confirming & Factoring\Bot | H29: QA-94188219979 | J29: HTTP Security Header Not Detected | L29: Solved | M29: Medium | N29: Vendor | P29: 94188208248 | Q29: confirming-factoring.santander.com.co | R29: 443 | S29: TCP | T29: 43816 | U29: =TODAY()-T29 -> 2393 | V29: =IF(M29="Critical",T29+10,IF(M29="High",T29+30,IF(M29="Bad",T29+30,IF(M29="Medium",T29+90,IF(M29="Warm",T29+90,IF(M29="Low",T29+120,IF(M29="Fair",T29+120,IF(M29="Neutral",T29+120,"")))))))) -> 43906 | W29: =IF(M29="Critical",IF(U29>10,"SLA Vencido","En SLA"),IF(M29="High",IF(U29>30,"SLA Vencido","En SLA"),IF(M29="Bad",IF(U29>30,"SLA Vencido","En SLA"),IF(M29="Medium",IF(U29>90,"SLA Vencido","En SLA"),IF(M29="Warm",IF(U29>90,"SLA Vencido","En SLA"),IF(M29="Low",IF(U29>120,"SLA Vencido","En SLA"),IF(M29="Fair",IF(U29>120,"SLA Vencido","En SLA"),IF(M29="Neutral",IF(U29>120,"SLA Vencido","En SLA"),"Error")))))))) -> SLA Vencido | AA29: 43934 | AC29: <B> Nota: </B> Para depurar mejor los resultados de este QID, se solicita que los clientes ejecuten comandos para simular la siguiente funcionalidad: curl -lkL --verbose. <P> CWE-693: Falla del mecanismo de protección menciona lo siguiente: el producto no | AD29: Dependiendo de la vulnerabilidad que se explota, un atacante remoto no autenticado podría realizar scripts de sitios, clickjacking o ataques de detección de tipo MIME. | AF29: Certificada | AG29: Jaime Orlando Vargas Martinez | AH29: =IFERROR(VLOOKUP(H29,hoja1!A:A,1,),"N/A") -> N/A
A30: 29 | B30: BSNC | C30: Task Force | D30: Telecomunicaciones | G30: Internet invitados Backup Santander (Wifi Backup) | J30: SSL Certificate Not Signed By A Trusted Authority | K30: CWE-296: Improper Following of Chain of Trust for Certificate Validation | L30: Solved | M30: Medium | P30: 181.48.20.105 | R30: 443 | S30: TCP | T30: 43812 | U30: =TODAY()-T30 -> 2397 | V30: =IF(M30="Critical",T30+10,IF(M30="High",T30+30,IF(M30="Bad",T30+30,IF(M30="Medium",T30+90,IF(M30="Warm",T30+90,IF(M30="Low",T30+120,IF(M30="Fair",T30+120,IF(M30="Neutral",T30+120,"")))))))) -> 43902 | W30: =IF(M30="Critical",IF(U30>10,"SLA Vencido","En SLA"),IF(M30="High",IF(U30>30,"SLA Vencido","En SLA"),IF(M30="Bad",IF(U30>30,"SLA Vencido","En SLA"),IF(M30="Medium",IF(U30>90,"SLA Vencido","En SLA"),IF(M30="Warm",IF(U30>90,"SLA Vencido","En SLA"),IF(M30="Low",IF(U30>120,"SLA Vencido","En SLA"),IF(M30="Fair",IF(U30>120,"SLA Vencido","En SLA"),IF(M30="Neutral",IF(U30>120,"SLA Vencido","En SLA"),"Error")))))))) -> SLA Vencido | AA30: 43969 | AB30: The following certificate was part of the certificate chain sent by the remote host, but it has expired : Subject : 2.5.4.41=AR161-Self-Signed-Certificate-21500102122SHB600935 Not After : Apr 02 00:00:00 2010 GMT The following certificate was at the top of the certificate chain sent by the remote host, but it is signed by an unknown certificate authority : Subject : 2.5.4.41=AR161-Self-Signed-Certificate-21500102122SHB600935 Issuer : 2.5.4.41=AR161-Self-Signed-Certificate-21500102122SHB600935 | AC30: Cisco recommends that SSL services always use certificates signed by an authority that clients belonging to normal system users will trust. The vendor for each supported client will be able to provide an up-to-date list of certificate authorities who are trusted by default. One of these will be required to sign the certificate for each affected service. | AF30: Certificada | AH30: =IFERROR(VLOOKUP(H30,hoja1!A:A,1,),"N/A") -> N/A
A31: 30 | B31: BSNC | C31: Task Force | D31: Telecomunicaciones | G31: Internet invitados Backup Santander (Wifi Backup) | J31: SSL Certificate Not Signed By A Trusted Authority | K31: CWE-296: Improper Following of Chain of Trust for Certificate Validation | L31: Solved | M31: Medium | P31: 181.48.20.104 | R31: 443 | S31: TCP | T31: 43812 | U31: =TODAY()-T31 -> 2397 | V31: =IF(M31="Critical",T31+10,IF(M31="High",T31+30,IF(M31="Bad",T31+30,IF(M31="Medium",T31+90,IF(M31="Warm",T31+90,IF(M31="Low",T31+120,IF(M31="Fair",T31+120,IF(M31="Neutral",T31+120,"")))))))) -> 43902 | W31: =IF(M31="Critical",IF(U31>10,"SLA Vencido","En SLA"),IF(M31="High",IF(U31>30,"SLA Vencido","En SLA"),IF(M31="Bad",IF(U31>30,"SLA Vencido","En SLA"),IF(M31="Medium",IF(U31>90,"SLA Vencido","En SLA"),IF(M31="Warm",IF(U31>90,"SLA Vencido","En SLA"),IF(M31="Low",IF(U31>120,"SLA Vencido","En SLA"),IF(M31="Fair",IF(U31>120,"SLA Vencido","En SLA"),IF(M31="Neutral",IF(U31>120,"SLA Vencido","En SLA"),"Error")))))))) -> SLA Vencido | AA31: 43969 | AB31: The following certificate was part of the certificate chain sent by the remote host, but it has expired : Subject : 2.5.4.41=AR161-Self-Signed-Certificate- 186021MISC : Banco Santander (PID 894366) IR Complementary Pen Test 25 CISCO RESTRICTED 21500102122SHB600935 Not After : Apr 02 00:00:00 2010 GMT The following certificate was at the top of the certificate chain sent by the remote host, but it is signed by an unknown certificate authority : Subject : 2.5.4.41=AR161-Self-Signed-Certificate-21500102122SHB600935 Issuer : 2.5.4.41=AR161-Self-Signed-Certificate-21500102122SHB600935 | AC31: Cisco recommends that SSL services always use certificates signed by an authority that clients belonging to normal system users will trust. The vendor for each supported client will be able to provide an up-to-date list of certificate authorities who are trusted by default. One of these will be required to sign the certificate for each affected service. | AF31: Certificada | AH31: =IFERROR(VLOOKUP(H31,hoja1!A:A,1,),"N/A") -> N/A
A32: 31 | B32: BSNC | C32: Task Force | D32: Telecomunicaciones | G32: fw.santander.com.co/Peer del Firewall | J32: SSL Certificate Not Signed By A Trusted Authority | K32: CWE-296: Improper Following of Chain of Trust for Certificate Validation | L32: Solved | M32: Medium | P32: 170.169.127.22 | R32: 443 | S32: TCP | T32: 43812 | U32: =TODAY()-T32 -> 2397 | V32: =IF(M32="Critical",T32+10,IF(M32="High",T32+30,IF(M32="Bad",T32+30,IF(M32="Medium",T32+90,IF(M32="Warm",T32+90,IF(M32="Low",T32+120,IF(M32="Fair",T32+120,IF(M32="Neutral",T32+120,"")))))))) -> 43902 | W32: =IF(M32="Critical",IF(U32>10,"SLA Vencido","En SLA"),IF(M32="High",IF(U32>30,"SLA Vencido","En SLA"),IF(M32="Bad",IF(U32>30,"SLA Vencido","En SLA"),IF(M32="Medium",IF(U32>90,"SLA Vencido","En SLA"),IF(M32="Warm",IF(U32>90,"SLA Vencido","En SLA"),IF(M32="Low",IF(U32>120,"SLA Vencido","En SLA"),IF(M32="Fair",IF(U32>120,"SLA Vencido","En SLA"),IF(M32="Neutral",IF(U32>120,"SLA Vencido","En SLA"),"Error")))))))) -> SLA Vencido | AA32: 43969 | AB32: The following certificate was at the top of the certificate chain sent by the remote host, but it is signed by an unknown certificate authority : Subject : O=InternetNala..fgvprc Issuer : O=InternetNala..fgvprc | AC32: Cisco recommends that SSL services always use certificates signed by an authority that clients belonging to normal system users will trust. The vendor for each supported client will be able to provide an up-to-date list of certificate authorities who are trusted by default. One of these will be required to sign the certificate for each affected service. | AF32: Certificada | AH32: =IFERROR(VLOOKUP(H32,hoja1!A:A,1,),"N/A") -> N/A
A33: 32 | B33: BSNC | C33: Task Force | D33: Telecomunicaciones | G33: Internet Backup Santander (Cableada | J33: Network Time Protocol (NTP) Allows Mode 6 Queries | K33: CWE-406: Insufficient Control of Network Message Volume (Network Amplification) | L33: Dismissed | M33: Medium | P33: 190216136242 | R33: 123 | S33: UDP | T33: 43812 | U33: =TODAY()-T33 -> 2397 | V33: =IF(M33="Critical",T33+10,IF(M33="High",T33+30,IF(M33="Bad",T33+30,IF(M33="Medium",T33+90,IF(M33="Warm",T33+90,IF(M33="Low",T33+120,IF(M33="Fair",T33+120,IF(M33="Neutral",T33+120,"")))))))) -> 43902 | W33: =IF(M33="Critical",IF(U33>10,"SLA Vencido","En SLA"),IF(M33="High",IF(U33>30,"SLA Vencido","En SLA"),IF(M33="Bad",IF(U33>30,"SLA Vencido","En SLA"),IF(M33="Medium",IF(U33>90,"SLA Vencido","En SLA"),IF(M33="Warm",IF(U33>90,"SLA Vencido","En SLA"),IF(M33="Low",IF(U33>120,"SLA Vencido","En SLA"),IF(M33="Fair",IF(U33>120,"SLA Vencido","En SLA"),IF(M33="Neutral",IF(U33>120,"SLA Vencido","En SLA"),"Error")))))))) -> SLA Vencido | AB33: Cisco elicited the following response from the remote host by sending an NTP mode 6 query : 'version="4", processor="unknown", system="UNIX", leap=3, stratum=16, precision=-21, rootdelay=, rootdisp=, refid=INIT, reftime=0x00000000.00000000, clock=0xE0C57C60.745BE732, peer=0, tc=3, mintc=3, offset=, frequency=, sys_jitter=, clk_jitter=, clk_wander=' | AC33: Cisco recommends disabling the NTP server, or if the NTP server is required, Cisco recommends that ACLs are set in order to only allow the access to this service to the IP addresses that use this service. In case of Cisco IOS devices, it is not allowed to disable Mode 6 queries. | AF33: En proceso de certificacion. No fue certificada Susana Tovar: La red ya no existen Javier Leon: dado que el servicio se canceló y que son segmentos públicos el proveedor de servicio reasigno el direccionamiento a otro cliente. | AH33: =IFERROR(VLOOKUP(H33,hoja1!A:A,1,),"N/A") -> N/A
A34: 33 | B34: BSNC | C34: Task Force | D34: Telecomunicaciones | G34: Internet Backup Santander (Cableada | J34: Network Time Protocol (NTP) Allows Mode 6 Queries | K34: CWE-406: Insufficient Control of Network Message Volume (Network Amplification) | L34: Dismissed | M34: Medium | P34: 190216136241 | R34: 123 | S34: UDP | T34: 43812 | U34: =TODAY()-T34 -> 2397 | V34: =IF(M34="Critical",T34+10,IF(M34="High",T34+30,IF(M34="Bad",T34+30,IF(M34="Medium",T34+90,IF(M34="Warm",T34+90,IF(M34="Low",T34+120,IF(M34="Fair",T34+120,IF(M34="Neutral",T34+120,"")))))))) -> 43902 | W34: =IF(M34="Critical",IF(U34>10,"SLA Vencido","En SLA"),IF(M34="High",IF(U34>30,"SLA Vencido","En SLA"),IF(M34="Bad",IF(U34>30,"SLA Vencido","En SLA"),IF(M34="Medium",IF(U34>90,"SLA Vencido","En SLA"),IF(M34="Warm",IF(U34>90,"SLA Vencido","En SLA"),IF(M34="Low",IF(U34>120,"SLA Vencido","En SLA"),IF(M34="Fair",IF(U34>120,"SLA Vencido","En SLA"),IF(M34="Neutral",IF(U34>120,"SLA Vencido","En SLA"),"Error")))))))) -> SLA Vencido | AB34: Cisco elicited the following response from the remote host by sending an NTP mode 6 query : 'version="4", processor="unknown", system="UNIX", leap=3, stratum=16, precision=-21, rootdelay=, rootdisp=, refid=INIT, reftime=0x00000000.00000000, clock=0xE0C5B1FC.6E124E27, peer=0, tc=3, mintc=3, offset=, frequency=, sys_jitter=, clk_jitter=,clk_wander=' | AC34: Cisco recommends disabling the NTP server, or if the NTP server is required, Cisco recommends that ACLs are set in order to only allow the access to this service to the IP addresses that use this service. In case of Cisco IOS devices, it is not allowed to disable Mode 6 queries. | AF34: En proceso de certificacion. No fue certificada Susana Tovar: La red ya no existen Javier Leon: dado que el servicio se canceló y que son segmentos públicos el proveedor de servicio reasigno el direccionamiento a otro cliente. | AH34: =IFERROR(VLOOKUP(H34,hoja1!A:A,1,),"N/A") -> N/A
A35: 34 | B35: BSNC | C35: Task Force | D35: Telecomunicaciones | G35: Internet principal Santander (Cableada) | J35: Network Time Protocol (NTP) Allows Mode 6 Queries | K35: CWE-406: Insufficient Control of Network Message Volume (Network Amplification) | L35: Solved | M35: Medium | P35: 181.48.106.210 | R35: 123 | S35: UDP | T35: 43812 | U35: =TODAY()-T35 -> 2397 | V35: =IF(M35="Critical",T35+10,IF(M35="High",T35+30,IF(M35="Bad",T35+30,IF(M35="Medium",T35+90,IF(M35="Warm",T35+90,IF(M35="Low",T35+120,IF(M35="Fair",T35+120,IF(M35="Neutral",T35+120,"")))))))) -> 43902 | W35: =IF(M35="Critical",IF(U35>10,"SLA Vencido","En SLA"),IF(M35="High",IF(U35>30,"SLA Vencido","En SLA"),IF(M35="Bad",IF(U35>30,"SLA Vencido","En SLA"),IF(M35="Medium",IF(U35>90,"SLA Vencido","En SLA"),IF(M35="Warm",IF(U35>90,"SLA Vencido","En SLA"),IF(M35="Low",IF(U35>120,"SLA Vencido","En SLA"),IF(M35="Fair",IF(U35>120,"SLA Vencido","En SLA"),IF(M35="Neutral",IF(U35>120,"SLA Vencido","En SLA"),"Error")))))))) -> SLA Vencido | AA35: 44069 | AB35: Cisco elicited the following response from the remote host by sending an NTP mode 6 query : 'version="4", processor="unknown", system="UNIX", leap=3, stratum=16, precision=-21, rootdelay=, rootdisp=, refid=INIT, reftime=0x00000000.00000000, clock=0xE0C5B209.4748434E, peer=0, tc=3, mintc=3, offset=, frequency=, sys_jitter=, clk_jitter=, clk_wander=' | AC35: Cisco recommends disabling the NTP server, or if the NTP server is required, Cisco recommends that ACLs are set in order to only allow the access to this service to the IP addresses that use this service. In case of Cisco IOS devices, it is not allowed to disable Mode 6 queries. | AF35: Certificada | AH35: =IFERROR(VLOOKUP(H35,hoja1!A:A,1,),"N/A") -> N/A
A36: 35 | B36: BSNC | C36: Task Force | D36: Telecomunicaciones | G36: Internet principal Santander (Cableada) | J36: Potentially Unnecessary Services | K36: CWE-0: Insecure Configuration | L36: Solved | M36: Medium | P36: 181.48.106.209 | R36: 161 | S36: UDP | T36: 43812 | U36: =TODAY()-T36 -> 2397 | V36: =IF(M36="Critical",T36+10,IF(M36="High",T36+30,IF(M36="Bad",T36+30,IF(M36="Medium",T36+90,IF(M36="Warm",T36+90,IF(M36="Low",T36+120,IF(M36="Fair",T36+120,IF(M36="Neutral",T36+120,"")))))))) -> 43902 | W36: =IF(M36="Critical",IF(U36>10,"SLA Vencido","En SLA"),IF(M36="High",IF(U36>30,"SLA Vencido","En SLA"),IF(M36="Bad",IF(U36>30,"SLA Vencido","En SLA"),IF(M36="Medium",IF(U36>90,"SLA Vencido","En SLA"),IF(M36="Warm",IF(U36>90,"SLA Vencido","En SLA"),IF(M36="Low",IF(U36>120,"SLA Vencido","En SLA"),IF(M36="Fair",IF(U36>120,"SLA Vencido","En SLA"),IF(M36="Neutral",IF(U36>120,"SLA Vencido","En SLA"),"Error")))))))) -> SLA Vencido | AA36: 43969 | AB36: The Team identified the presence of services not usually required for normal operations. For instance, NTP and SNMP services were observed exposed to the Internet. The Team also identified SSH and Telnet services exposed; however, the connection to these services is terminated from the server before reaching the login prompt. | AC36: Cisco recommends that any services not strictly necessary for normal operations are either disabled or removed completely. | AF36: Certificada | AH36: =IFERROR(VLOOKUP(H36,hoja1!A:A,1,),"N/A") -> N/A
A37: 36 | B37: BSNC | C37: Task Force | D37: Telecomunicaciones | G37: Internet principal Santander (Cableada) | J37: Potentially Unnecessary Services | K37: CWE-0: Insecure Configuration | L37: Solved | M37: Medium | P37: 181.48.106.210 | R37: 123 | S37: UDP | T37: 43812 | U37: =TODAY()-T37 -> 2397 | V37: =IF(M37="Critical",T37+10,IF(M37="High",T37+30,IF(M37="Bad",T37+30,IF(M37="Medium",T37+90,IF(M37="Warm",T37+90,IF(M37="Low",T37+120,IF(M37="Fair",T37+120,IF(M37="Neutral",T37+120,"")))))))) -> 43902 | W37: =IF(M37="Critical",IF(U37>10,"SLA Vencido","En SLA"),IF(M37="High",IF(U37>30,"SLA Vencido","En SLA"),IF(M37="Bad",IF(U37>30,"SLA Vencido","En SLA"),IF(M37="Medium",IF(U37>90,"SLA Vencido","En SLA"),IF(M37="Warm",IF(U37>90,"SLA Vencido","En SLA"),IF(M37="Low",IF(U37>120,"SLA Vencido","En SLA"),IF(M37="Fair",IF(U37>120,"SLA Vencido","En SLA"),IF(M37="Neutral",IF(U37>120,"SLA Vencido","En SLA"),"Error")))))))) -> SLA Vencido | AA37: 44069 | AB37: The Team identified the presence of services not usually required for normal operations. For instance, NTP and SNMP services were observed exposed to the Internet. The Team also identified SSH and Telnet services exposed; however, the connection to these services is terminated from the server before reaching the login prompt. | AC37: Cisco recommends that any services not strictly necessary for normal operations are either disabled or removed completely. | AF37: Certificada | AH37: =IFERROR(VLOOKUP(H37,hoja1!A:A,1,),"N/A") -> N/A
A38: 37 | B38: BSNC | C38: Task Force | D38: Telecomunicaciones | G38: Internet invitados Backup Santander (Wifi Backup) | J38: Potentially Unnecessary Services | K38: CWE-0: Insecure Configuration | L38: Solved | M38: Medium | P38: 181.48.20.111 | R38: 123 | S38: UDP | T38: 43812 | U38: =TODAY()-T38 -> 2397 | V38: =IF(M38="Critical",T38+10,IF(M38="High",T38+30,IF(M38="Bad",T38+30,IF(M38="Medium",T38+90,IF(M38="Warm",T38+90,IF(M38="Low",T38+120,IF(M38="Fair",T38+120,IF(M38="Neutral",T38+120,"")))))))) -> 43902 | W38: =IF(M38="Critical",IF(U38>10,"SLA Vencido","En SLA"),IF(M38="High",IF(U38>30,"SLA Vencido","En SLA"),IF(M38="Bad",IF(U38>30,"SLA Vencido","En SLA"),IF(M38="Medium",IF(U38>90,"SLA Vencido","En SLA"),IF(M38="Warm",IF(U38>90,"SLA Vencido","En SLA"),IF(M38="Low",IF(U38>120,"SLA Vencido","En SLA"),IF(M38="Fair",IF(U38>120,"SLA Vencido","En SLA"),IF(M38="Neutral",IF(U38>120,"SLA Vencido","En SLA"),"Error")))))))) -> SLA Vencido | AA38: 43969 | AB38: The Team identified the presence of services not usually required for normal operations. For instance, NTP and SNMP services were observed exposed to the Internet. The Team also identified SSH and Telnet services exposed; however, the connection to these services is terminated from the server before reaching the login prompt. | AC38: Cisco recommends that any services not strictly necessary for normal operations are either disabled or removed completely. | AF38: Certificada | AH38: =IFERROR(VLOOKUP(H38,hoja1!A:A,1,),"N/A") -> N/A
A39: 38 | B39: BSNC | C39: Task Force | D39: Telecomunicaciones | G39: Internet invitados principal Santander (Wifi Ppal) | J39: Potentially Unnecessary Services | K39: CWE-0: Insecure Configuration | L39: Solved | M39: Medium | P39: 181.49.176.1 | R39: 123 | S39: UDP | T39: 43812 | U39: =TODAY()-T39 -> 2397 | V39: =IF(M39="Critical",T39+10,IF(M39="High",T39+30,IF(M39="Bad",T39+30,IF(M39="Medium",T39+90,IF(M39="Warm",T39+90,IF(M39="Low",T39+120,IF(M39="Fair",T39+120,IF(M39="Neutral",T39+120,"")))))))) -> 43902 | W39: =IF(M39="Critical",IF(U39>10,"SLA Vencido","En SLA"),IF(M39="High",IF(U39>30,"SLA Vencido","En SLA"),IF(M39="Bad",IF(U39>30,"SLA Vencido","En SLA"),IF(M39="Medium",IF(U39>90,"SLA Vencido","En SLA"),IF(M39="Warm",IF(U39>90,"SLA Vencido","En SLA"),IF(M39="Low",IF(U39>120,"SLA Vencido","En SLA"),IF(M39="Fair",IF(U39>120,"SLA Vencido","En SLA"),IF(M39="Neutral",IF(U39>120,"SLA Vencido","En SLA"),"Error")))))))) -> SLA Vencido | AA39: 43969 | AB39: The Team identified the presence of services not usually required for normal operations. For instance, NTP and SNMP services were observed exposed to the Internet. The Team also identified SSH and Telnet services exposed; however, the connection to these services is terminated from the server before reaching the login prompt. | AC39: Cisco recommends that any services not strictly necessary for normal operations are either disabled or removed completely. | AF39: Certificada | AH39: =IFERROR(VLOOKUP(H39,hoja1!A:A,1,),"N/A") -> N/A
A40: 39 | B40: BSNC | C40: Task Force | D40: Telecomunicaciones | G40: Internet invitados Backup Santander (Wifi Backup) | J40: Potentially Unnecessary Services | K40: CWE-0: Insecure Configuration | L40: Solved | M40: Medium | P40: 181.48.20.104 | R40: 23 | S40: TCP | T40: 43812 | U40: =TODAY()-T40 -> 2397 | V40: =IF(M40="Critical",T40+10,IF(M40="High",T40+30,IF(M40="Bad",T40+30,IF(M40="Medium",T40+90,IF(M40="Warm",T40+90,IF(M40="Low",T40+120,IF(M40="Fair",T40+120,IF(M40="Neutral",T40+120,"")))))))) -> 43902 | W40: =IF(M40="Critical",IF(U40>10,"SLA Vencido","En SLA"),IF(M40="High",IF(U40>30,"SLA Vencido","En SLA"),IF(M40="Bad",IF(U40>30,"SLA Vencido","En SLA"),IF(M40="Medium",IF(U40>90,"SLA Vencido","En SLA"),IF(M40="Warm",IF(U40>90,"SLA Vencido","En SLA"),IF(M40="Low",IF(U40>120,"SLA Vencido","En SLA"),IF(M40="Fair",IF(U40>120,"SLA Vencido","En SLA"),IF(M40="Neutral",IF(U40>120,"SLA Vencido","En SLA"),"Error")))))))) -> SLA Vencido | AA40: 43969 | AB40: The Team identified the presence of services not usually required for normal operations. For instance, NTP and SNMP services were observed exposed to the Internet. The Team also identified SSH and Telnet services exposed; however, the connection to these services is terminated from the server before reaching the login prompt. | AC40: Cisco recommends that any services not strictly necessary for normal operations are either disabled or removed completely. | AF40: Certificada | AH40: =IFERROR(VLOOKUP(H40,hoja1!A:A,1,),"N/A") -> N/A
A41: 40 | B41: BSNC | C41: Task Force | D41: Telecomunicaciones | G41: Internet invitados principal Santander (Wifi Ppal) | J41: Potentially Unnecessary Services | K41: CWE-0: Insecure Configuration | L41: Solved | M41: Medium | P41: 181.49.176.1 | R41: 161 | S41: UDP | T41: 43812 | U41: =TODAY()-T41 -> 2397 | V41: =IF(M41="Critical",T41+10,IF(M41="High",T41+30,IF(M41="Bad",T41+30,IF(M41="Medium",T41+90,IF(M41="Warm",T41+90,IF(M41="Low",T41+120,IF(M41="Fair",T41+120,IF(M41="Neutral",T41+120,"")))))))) -> 43902 | W41: =IF(M41="Critical",IF(U41>10,"SLA Vencido","En SLA"),IF(M41="High",IF(U41>30,"SLA Vencido","En SLA"),IF(M41="Bad",IF(U41>30,"SLA Vencido","En SLA"),IF(M41="Medium",IF(U41>90,"SLA Vencido","En SLA"),IF(M41="Warm",IF(U41>90,"SLA Vencido","En SLA"),IF(M41="Low",IF(U41>120,"SLA Vencido","En SLA"),IF(M41="Fair",IF(U41>120,"SLA Vencido","En SLA"),IF(M41="Neutral",IF(U41>120,"SLA Vencido","En SLA"),"Error")))))))) -> SLA Vencido | AA41: 43969 | AB41: The Team identified the presence of services not usually required for normal operations. For instance, NTP and SNMP services were observed exposed to the Internet. The Team also identified SSH and Telnet services exposed; however, the connection to these services is terminated from the server before reaching the login prompt. | AC41: Cisco recommends that any services not strictly necessary for normal operations are either disabled or removed completely. | AF41: Certificada | AH41: =IFERROR(VLOOKUP(H41,hoja1!A:A,1,),"N/A") -> N/A
A42: 41 | B42: BSNC | C42: Task Force | D42: Telecomunicaciones | G42: Internet invitados Backup Santander (Wifi Backup) | J42: Potentially Unnecessary Services | K42: CWE-0: Insecure Configuration | L42: Solved | M42: Medium | P42: 181.48.20.104 | R42: 22 | S42: TCP | T42: 43812 | U42: =TODAY()-T42 -> 2397 | V42: =IF(M42="Critical",T42+10,IF(M42="High",T42+30,IF(M42="Bad",T42+30,IF(M42="Medium",T42+90,IF(M42="Warm",T42+90,IF(M42="Low",T42+120,IF(M42="Fair",T42+120,IF(M42="Neutral",T42+120,"")))))))) -> 43902 | W42: =IF(M42="Critical",IF(U42>10,"SLA Vencido","En SLA"),IF(M42="High",IF(U42>30,"SLA Vencido","En SLA"),IF(M42="Bad",IF(U42>30,"SLA Vencido","En SLA"),IF(M42="Medium",IF(U42>90,"SLA Vencido","En SLA"),IF(M42="Warm",IF(U42>90,"SLA Vencido","En SLA"),IF(M42="Low",IF(U42>120,"SLA Vencido","En SLA"),IF(M42="Fair",IF(U42>120,"SLA Vencido","En SLA"),IF(M42="Neutral",IF(U42>120,"SLA Vencido","En SLA"),"Error")))))))) -> SLA Vencido | AA42: 43969 | AB42: The Team identified the presence of services not usually required for normal operations. For instance, NTP and SNMP services were observed exposed to the Internet. The Team also identified SSH and Telnet services exposed; however, the connection to these services is terminated from the server before reaching the login prompt. | AC42: Cisco recommends that any services not strictly necessary for normal operations are either disabled or removed completely. | AF42: Certificada | AH42: =IFERROR(VLOOKUP(H42,hoja1!A:A,1,),"N/A") -> N/A
A43: 42 | B43: BSNC | C43: Task Force | D43: Telecomunicaciones | G43: Internet principal Santander (Cableada) | J43: Potentially Unnecessary Services | K43: CWE-0: Insecure Configuration | L43: Solved | M43: Medium | P43: 181.48.106.209 | R43: 123 | S43: UDP | T43: 43812 | U43: =TODAY()-T43 -> 2397 | V43: =IF(M43="Critical",T43+10,IF(M43="High",T43+30,IF(M43="Bad",T43+30,IF(M43="Medium",T43+90,IF(M43="Warm",T43+90,IF(M43="Low",T43+120,IF(M43="Fair",T43+120,IF(M43="Neutral",T43+120,"")))))))) -> 43902 | W43: =IF(M43="Critical",IF(U43>10,"SLA Vencido","En SLA"),IF(M43="High",IF(U43>30,"SLA Vencido","En SLA"),IF(M43="Bad",IF(U43>30,"SLA Vencido","En SLA"),IF(M43="Medium",IF(U43>90,"SLA Vencido","En SLA"),IF(M43="Warm",IF(U43>90,"SLA Vencido","En SLA"),IF(M43="Low",IF(U43>120,"SLA Vencido","En SLA"),IF(M43="Fair",IF(U43>120,"SLA Vencido","En SLA"),IF(M43="Neutral",IF(U43>120,"SLA Vencido","En SLA"),"Error")))))))) -> SLA Vencido | AA43: 43969 | AB43: The Team identified the presence of services not usually required for normal operations. For instance, NTP and SNMP services were observed exposed to the Internet. The Team also identified SSH and Telnet services exposed; however, the connection to these services is terminated from the server before reaching the login prompt. | AC43: Cisco recommends that any services not strictly necessary for normal operations are either disabled or removed completely. | AF43: Certificada | AH43: =IFERROR(VLOOKUP(H43,hoja1!A:A,1,),"N/A") -> N/A
A44: 43 | B44: BSNC | C44: Task Force | D44: Telecomunicaciones | G44: Internet principal Santander (Cableada) | J44: Potentially Unnecessary Services | K44: CWE-0: Insecure Configuration | L44: Solved | M44: Medium | P44: 181.48.106.210 | R44: 161 | S44: UDP | T44: 43812 | U44: =TODAY()-T44 -> 2397 | V44: =IF(M44="Critical",T44+10,IF(M44="High",T44+30,IF(M44="Bad",T44+30,IF(M44="Medium",T44+90,IF(M44="Warm",T44+90,IF(M44="Low",T44+120,IF(M44="Fair",T44+120,IF(M44="Neutral",T44+120,"")))))))) -> 43902 | W44: =IF(M44="Critical",IF(U44>10,"SLA Vencido","En SLA"),IF(M44="High",IF(U44>30,"SLA Vencido","En SLA"),IF(M44="Bad",IF(U44>30,"SLA Vencido","En SLA"),IF(M44="Medium",IF(U44>90,"SLA Vencido","En SLA"),IF(M44="Warm",IF(U44>90,"SLA Vencido","En SLA"),IF(M44="Low",IF(U44>120,"SLA Vencido","En SLA"),IF(M44="Fair",IF(U44>120,"SLA Vencido","En SLA"),IF(M44="Neutral",IF(U44>120,"SLA Vencido","En SLA"),"Error")))))))) -> SLA Vencido | AA44: 44069 | AB44: The Team identified the presence of services not usually required for normal operations. For instance, NTP and SNMP services were observed exposed to the Internet. The Team also identified SSH and Telnet services exposed; however, the connection to these services is terminated from the server before reaching the login prompt. | AC44: Cisco recommends that any services not strictly necessary for normal operations are either disabled or removed completely. | AF44: Certificada | AH44: =IFERROR(VLOOKUP(H44,hoja1!A:A,1,),"N/A") -> N/A
A45: 44 | B45: BSNC | C45: Task Force | D45: Telecomunicaciones | G45: Internet invitados Backup Santander (Wifi Backup) | J45: Potentially Unnecessary Services | K45: CWE-0: Insecure Configuration | L45: Solved | M45: Medium | P45: 181.48.20.105 | R45: 22 | S45: TCP | T45: 43812 | U45: =TODAY()-T45 -> 2397 | V45: =IF(M45="Critical",T45+10,IF(M45="High",T45+30,IF(M45="Bad",T45+30,IF(M45="Medium",T45+90,IF(M45="Warm",T45+90,IF(M45="Low",T45+120,IF(M45="Fair",T45+120,IF(M45="Neutral",T45+120,"")))))))) -> 43902 | W45: =IF(M45="Critical",IF(U45>10,"SLA Vencido","En SLA"),IF(M45="High",IF(U45>30,"SLA Vencido","En SLA"),IF(M45="Bad",IF(U45>30,"SLA Vencido","En SLA"),IF(M45="Medium",IF(U45>90,"SLA Vencido","En SLA"),IF(M45="Warm",IF(U45>90,"SLA Vencido","En SLA"),IF(M45="Low",IF(U45>120,"SLA Vencido","En SLA"),IF(M45="Fair",IF(U45>120,"SLA Vencido","En SLA"),IF(M45="Neutral",IF(U45>120,"SLA Vencido","En SLA"),"Error")))))))) -> SLA Vencido | AA45: 43969 | AB45: The Team identified the presence of services not usually required for normal operations. For instance, NTP and SNMP services were observed exposed to the Internet. The Team also identified SSH and Telnet services exposed; however, the connection to these services is terminated from the server before reaching the login prompt. | AC45: Cisco recommends that any services not strictly necessary for normal operations are either disabled or removed completely. | AF45: Certificada | AH45: =IFERROR(VLOOKUP(H45,hoja1!A:A,1,),"N/A") -> N/A
A46: 45 | B46: BSNC | C46: Task Force | D46: Telecomunicaciones | G46: Internet Backup Santander (Cableada | J46: Potentially Unnecessary Services | K46: CWE-0: Insecure Configuration | L46: Dismissed | M46: Medium | P46: 190216136241 | R46: 123 | S46: UDP | T46: 43812 | U46: =TODAY()-T46 -> 2397 | V46: =IF(M46="Critical",T46+10,IF(M46="High",T46+30,IF(M46="Bad",T46+30,IF(M46="Medium",T46+90,IF(M46="Warm",T46+90,IF(M46="Low",T46+120,IF(M46="Fair",T46+120,IF(M46="Neutral",T46+120,"")))))))) -> 43902 | W46: =IF(M46="Critical",IF(U46>10,"SLA Vencido","En SLA"),IF(M46="High",IF(U46>30,"SLA Vencido","En SLA"),IF(M46="Bad",IF(U46>30,"SLA Vencido","En SLA"),IF(M46="Medium",IF(U46>90,"SLA Vencido","En SLA"),IF(M46="Warm",IF(U46>90,"SLA Vencido","En SLA"),IF(M46="Low",IF(U46>120,"SLA Vencido","En SLA"),IF(M46="Fair",IF(U46>120,"SLA Vencido","En SLA"),IF(M46="Neutral",IF(U46>120,"SLA Vencido","En SLA"),"Error")))))))) -> SLA Vencido | AB46: The Team identified the presence of services not usually required for normal operations. For instance, NTP and SNMP services were observed exposed to the Internet. The Team also identified SSH and Telnet services exposed; however, the connection to these services is terminated from the server before reaching the login prompt. | AC46: Cisco recommends that any services not strictly necessary for normal operations are either disabled or removed completely. | AF46: En proceso de certificacion. No fue certificada Susana Tovar: La red ya no existen Javier Leon: dado que el servicio se canceló y que son segmentos públicos el proveedor de servicio reasigno el direccionamiento a otro cliente. | AH46: =IFERROR(VLOOKUP(H46,hoja1!A:A,1,),"N/A") -> N/A
A47: 46 | B47: BSNC | C47: Task Force | D47: Telecomunicaciones | G47: Internet invitados Backup Santander (Wifi Backup) | J47: Potentially Unnecessary Services | K47: CWE-0: Insecure Configuration | L47: Solved | M47: Medium | P47: 181.48.20.105 | R47: 123 | S47: UDP | T47: 43812 | U47: =TODAY()-T47 -> 2397 | V47: =IF(M47="Critical",T47+10,IF(M47="High",T47+30,IF(M47="Bad",T47+30,IF(M47="Medium",T47+90,IF(M47="Warm",T47+90,IF(M47="Low",T47+120,IF(M47="Fair",T47+120,IF(M47="Neutral",T47+120,"")))))))) -> 43902 | W47: =IF(M47="Critical",IF(U47>10,"SLA Vencido","En SLA"),IF(M47="High",IF(U47>30,"SLA Vencido","En SLA"),IF(M47="Bad",IF(U47>30,"SLA Vencido","En SLA"),IF(M47="Medium",IF(U47>90,"SLA Vencido","En SLA"),IF(M47="Warm",IF(U47>90,"SLA Vencido","En SLA"),IF(M47="Low",IF(U47>120,"SLA Vencido","En SLA"),IF(M47="Fair",IF(U47>120,"SLA Vencido","En SLA"),IF(M47="Neutral",IF(U47>120,"SLA Vencido","En SLA"),"Error")))))))) -> SLA Vencido | AA47: 43969 | AB47: The Team identified the presence of services not usually required for normal operations. For instance, NTP and SNMP services were observed exposed to the Internet. The Team also identified SSH and Telnet services exposed; however, the connection to these services is terminated from the server before reaching the login prompt. | AC47: Cisco recommends that any services not strictly necessary for normal operations are either disabled or removed completely. | AF47: Certificada | AH47: =IFERROR(VLOOKUP(H47,hoja1!A:A,1,),"N/A") -> N/A
A48: 47 | B48: BSNC | C48: Task Force | D48: Telecomunicaciones | G48: Internet Backup Santander (Cableada | J48: Potentially Unnecessary Services | K48: CWE-0: Insecure Configuration | L48: Dismissed | M48: Medium | P48: 190216136242 | R48: 161 | S48: UDP | T48: 43812 | U48: =TODAY()-T48 -> 2397 | V48: =IF(M48="Critical",T48+10,IF(M48="High",T48+30,IF(M48="Bad",T48+30,IF(M48="Medium",T48+90,IF(M48="Warm",T48+90,IF(M48="Low",T48+120,IF(M48="Fair",T48+120,IF(M48="Neutral",T48+120,"")))))))) -> 43902 | W48: =IF(M48="Critical",IF(U48>10,"SLA Vencido","En SLA"),IF(M48="High",IF(U48>30,"SLA Vencido","En SLA"),IF(M48="Bad",IF(U48>30,"SLA Vencido","En SLA"),IF(M48="Medium",IF(U48>90,"SLA Vencido","En SLA"),IF(M48="Warm",IF(U48>90,"SLA Vencido","En SLA"),IF(M48="Low",IF(U48>120,"SLA Vencido","En SLA"),IF(M48="Fair",IF(U48>120,"SLA Vencido","En SLA"),IF(M48="Neutral",IF(U48>120,"SLA Vencido","En SLA"),"Error")))))))) -> SLA Vencido | AB48: The Team identified the presence of services not usually required for normal operations. For instance, NTP and SNMP services were observed exposed to the Internet. The Team also identified SSH and Telnet services exposed; however, the connection to these services is terminated from the server before reaching the login prompt. | AC48: Cisco recommends that any services not strictly necessary for normal operations are either disabled or removed completely. | AF48: En proceso de certificacion. No fue certificada Susana Tovar: La red ya no existen Javier Leon: dado que el servicio se canceló y que son segmentos públicos el proveedor de servicio reasigno el direccionamiento a otro cliente. | AH48: =IFERROR(VLOOKUP(H48,hoja1!A:A,1,),"N/A") -> N/A
A49: 48 | B49: BSNC | C49: Task Force | D49: Telecomunicaciones | G49: Internet invitados principal Santander (Wifi Ppal) | J49: Potentially Unnecessary Services | K49: CWE-0: Insecure Configuration | L49: Solved | M49: Medium | P49: 181.49.176.0 | R49: 161 | S49: UDP | T49: 43812 | U49: =TODAY()-T49 -> 2397 | V49: =IF(M49="Critical",T49+10,IF(M49="High",T49+30,IF(M49="Bad",T49+30,IF(M49="Medium",T49+90,IF(M49="Warm",T49+90,IF(M49="Low",T49+120,IF(M49="Fair",T49+120,IF(M49="Neutral",T49+120,"")))))))) -> 43902 | W49: =IF(M49="Critical",IF(U49>10,"SLA Vencido","En SLA"),IF(M49="High",IF(U49>30,"SLA Vencido","En SLA"),IF(M49="Bad",IF(U49>30,"SLA Vencido","En SLA"),IF(M49="Medium",IF(U49>90,"SLA Vencido","En SLA"),IF(M49="Warm",IF(U49>90,"SLA Vencido","En SLA"),IF(M49="Low",IF(U49>120,"SLA Vencido","En SLA"),IF(M49="Fair",IF(U49>120,"SLA Vencido","En SLA"),IF(M49="Neutral",IF(U49>120,"SLA Vencido","En SLA"),"Error")))))))) -> SLA Vencido | AA49: 43969 | AB49: The Team identified the presence of services not usually required for normal operations. For instance, NTP and SNMP services were observed exposed to the Internet. The Team also identified SSH and Telnet services exposed; however, the connection to these services is terminated from the server before reaching the login prompt. | AC49: Cisco recommends that any services not strictly necessary for normal operations are either disabled or removed completely. | AF49: Certificada | AH49: =IFERROR(VLOOKUP(H49,hoja1!A:A,1,),"N/A") -> N/A
A50: 49 | B50: BSNC | C50: Task Force | D50: Telecomunicaciones | G50: Internet invitados Backup Santander (Wifi Backup) | J50: Potentially Unnecessary Services | K50: CWE-0: Insecure Configuration | L50: Solved | M50: Medium | P50: 181.48.20.105 | R50: 23 | S50: TCP | T50: 43812 | U50: =TODAY()-T50 -> 2397 | V50: =IF(M50="Critical",T50+10,IF(M50="High",T50+30,IF(M50="Bad",T50+30,IF(M50="Medium",T50+90,IF(M50="Warm",T50+90,IF(M50="Low",T50+120,IF(M50="Fair",T50+120,IF(M50="Neutral",T50+120,"")))))))) -> 43902 | W50: =IF(M50="Critical",IF(U50>10,"SLA Vencido","En SLA"),IF(M50="High",IF(U50>30,"SLA Vencido","En SLA"),IF(M50="Bad",IF(U50>30,"SLA Vencido","En SLA"),IF(M50="Medium",IF(U50>90,"SLA Vencido","En SLA"),IF(M50="Warm",IF(U50>90,"SLA Vencido","En SLA"),IF(M50="Low",IF(U50>120,"SLA Vencido","En SLA"),IF(M50="Fair",IF(U50>120,"SLA Vencido","En SLA"),IF(M50="Neutral",IF(U50>120,"SLA Vencido","En SLA"),"Error")))))))) -> SLA Vencido | AA50: 43969 | AB50: The Team identified the presence of services not usually required for normal operations. For instance, NTP and SNMP services were observed exposed to the Internet. The Team also identified SSH and Telnet services exposed; however, the connection to these services is terminated from the server before reaching the login prompt. | AC50: Cisco recommends that any services not strictly necessary for normal operations are either disabled or removed completely. | AF50: Certificada | AH50: =IFERROR(VLOOKUP(H50,hoja1!A:A,1,),"N/A") -> N/A
A51: 50 | B51: BSNC | C51: Task Force | D51: Telecomunicaciones | G51: Internet Backup Santander (Cableada | J51: Potentially Unnecessary Services | K51: CWE-0: Insecure Configuration | L51: Dismissed | M51: Medium | P51: 190216136242 | R51: 123 | S51: UDP | T51: 43812 | U51: =TODAY()-T51 -> 2397 | V51: =IF(M51="Critical",T51+10,IF(M51="High",T51+30,IF(M51="Bad",T51+30,IF(M51="Medium",T51+90,IF(M51="Warm",T51+90,IF(M51="Low",T51+120,IF(M51="Fair",T51+120,IF(M51="Neutral",T51+120,"")))))))) -> 43902 | W51: =IF(M51="Critical",IF(U51>10,"SLA Vencido","En SLA"),IF(M51="High",IF(U51>30,"SLA Vencido","En SLA"),IF(M51="Bad",IF(U51>30,"SLA Vencido","En SLA"),IF(M51="Medium",IF(U51>90,"SLA Vencido","En SLA"),IF(M51="Warm",IF(U51>90,"SLA Vencido","En SLA"),IF(M51="Low",IF(U51>120,"SLA Vencido","En SLA"),IF(M51="Fair",IF(U51>120,"SLA Vencido","En SLA"),IF(M51="Neutral",IF(U51>120,"SLA Vencido","En SLA"),"Error")))))))) -> SLA Vencido | AB51: The Team identified the presence of services not usually required for normal operations. For instance, NTP and SNMP services were observed exposed to the Internet. The Team also identified SSH and Telnet services exposed; however, the connection to these services is terminated from the server before reaching the login prompt. | AC51: Cisco recommends that any services not strictly necessary for normal operations are either disabled or removed completely. | AF51: En proceso de certificacion. No fue certificada Susana Tovar: La red ya no existen Javier Leon: dado que el servicio se canceló y que son segmentos públicos el proveedor de servicio reasigno el direccionamiento a otro cliente. | AH51: =IFERROR(VLOOKUP(H51,hoja1!A:A,1,),"N/A") -> N/A
A52: 51 | B52: BSNC | C52: Task Force | D52: Telecomunicaciones | G52: Internet Backup Santander (Cableada | J52: Potentially Unnecessary Services | K52: CWE-0: Insecure Configuration | L52: Dismissed | M52: Medium | P52: 190216136241 | R52: 161 | S52: UDP | T52: 43812 | U52: =TODAY()-T52 -> 2397 | V52: =IF(M52="Critical",T52+10,IF(M52="High",T52+30,IF(M52="Bad",T52+30,IF(M52="Medium",T52+90,IF(M52="Warm",T52+90,IF(M52="Low",T52+120,IF(M52="Fair",T52+120,IF(M52="Neutral",T52+120,"")))))))) -> 43902 | W52: =IF(M52="Critical",IF(U52>10,"SLA Vencido","En SLA"),IF(M52="High",IF(U52>30,"SLA Vencido","En SLA"),IF(M52="Bad",IF(U52>30,"SLA Vencido","En SLA"),IF(M52="Medium",IF(U52>90,"SLA Vencido","En SLA"),IF(M52="Warm",IF(U52>90,"SLA Vencido","En SLA"),IF(M52="Low",IF(U52>120,"SLA Vencido","En SLA"),IF(M52="Fair",IF(U52>120,"SLA Vencido","En SLA"),IF(M52="Neutral",IF(U52>120,"SLA Vencido","En SLA"),"Error")))))))) -> SLA Vencido | AB52: The Team identified the presence of services not usually required for normal operations. For instance, NTP and SNMP services were observed exposed to the Internet. The Team also identified SSH and Telnet services exposed; however, the connection to these services is terminated from the server before reaching the login prompt. | AC52: Cisco recommends that any services not strictly necessary for normal operations are either disabled or removed completely. | AF52: En proceso de certificacion. No fue certificada Susana Tovar: La red ya no existen Javier Leon: dado que el servicio se canceló y que son segmentos públicos el proveedor de servicio reasigno el direccionamiento a otro cliente. | AH52: =IFERROR(VLOOKUP(H52,hoja1!A:A,1,),"N/A") -> N/A
A53: 52 | B53: BSNC | C53: Task Force | D53: Telecomunicaciones | G53: Internet invitados principal Santander (Wifi Ppal) | J53: Potentially Unnecessary Services | K53: CWE-0: Insecure Configuration | L53: Solved | M53: Medium | P53: 181.49.176.7 | R53: 161 | S53: UDP | T53: 43812 | U53: =TODAY()-T53 -> 2397 | V53: =IF(M53="Critical",T53+10,IF(M53="High",T53+30,IF(M53="Bad",T53+30,IF(M53="Medium",T53+90,IF(M53="Warm",T53+90,IF(M53="Low",T53+120,IF(M53="Fair",T53+120,IF(M53="Neutral",T53+120,"")))))))) -> 43902 | W53: =IF(M53="Critical",IF(U53>10,"SLA Vencido","En SLA"),IF(M53="High",IF(U53>30,"SLA Vencido","En SLA"),IF(M53="Bad",IF(U53>30,"SLA Vencido","En SLA"),IF(M53="Medium",IF(U53>90,"SLA Vencido","En SLA"),IF(M53="Warm",IF(U53>90,"SLA Vencido","En SLA"),IF(M53="Low",IF(U53>120,"SLA Vencido","En SLA"),IF(M53="Fair",IF(U53>120,"SLA Vencido","En SLA"),IF(M53="Neutral",IF(U53>120,"SLA Vencido","En SLA"),"Error")))))))) -> SLA Vencido | AA53: 43969 | AB53: The Team identified the presence of services not usually required for normal operations. For instance, NTP and SNMP services were observed exposed to the Internet. The Team also identified SSH and Telnet services exposed; however, the connection to these services is terminated from the server before reaching the login prompt. | AC53: Cisco recommends that any services not strictly necessary for normal operations are either disabled or removed completely. | AF53: Certificada | AH53: =IFERROR(VLOOKUP(H53,hoja1!A:A,1,),"N/A") -> N/A
A54: 53 | B54: BSNC | C54: Task Force | D54: Telecomunicaciones | G54: Internet invitados Backup Santander (Wifi Backup) | J54: SSL Service Uses Expired Certificates | K54: CWE-298: Improper Validation of Certificate - Expiration | L54: Solved | M54: Medium | P54: 181.48.20.104 | R54: 443 | S54: TCP | T54: 43812 | U54: =TODAY()-T54 -> 2397 | V54: =IF(M54="Critical",T54+10,IF(M54="High",T54+30,IF(M54="Bad",T54+30,IF(M54="Medium",T54+90,IF(M54="Warm",T54+90,IF(M54="Low",T54+120,IF(M54="Fair",T54+120,IF(M54="Neutral",T54+120,"")))))))) -> 43902 | W54: =IF(M54="Critical",IF(U54>10,"SLA Vencido","En SLA"),IF(M54="High",IF(U54>30,"SLA Vencido","En SLA"),IF(M54="Bad",IF(U54>30,"SLA Vencido","En SLA"),IF(M54="Medium",IF(U54>90,"SLA Vencido","En SLA"),IF(M54="Warm",IF(U54>90,"SLA Vencido","En SLA"),IF(M54="Low",IF(U54>120,"SLA Vencido","En SLA"),IF(M54="Fair",IF(U54>120,"SLA Vencido","En SLA"),IF(M54="Neutral",IF(U54>120,"SLA Vencido","En SLA"),"Error")))))))) -> SLA Vencido | AA54: 43969 | AB54: The SSL certificate has already expired : Subject : n/a Issuer : n/a Not valid before : Apr 2 00:00:00 2000 GMT Not valid after : Apr 2 00:00:00 2010 GMT | AC54: Cisco recommends that any expired SSL Certificate is renewed as soon as possible if SSL continues to be required. | AF54: Certificada | AH54: =IFERROR(VLOOKUP(H54,hoja1!A:A,1,),"N/A") -> N/A
A55: 54 | B55: BSNC | C55: Task Force | D55: Telecomunicaciones | G55: Internet invitados principal Santander (Wifi Ppal) | J55: Check Point ‘SecuRemote’ Hostname Information Disclosure | K55: CWE-201: Information Exposure Through Sent Data | L55: Solved | M55: Medium | P55: 181.49.176.4 | R55: 264 | S55: TCP | T55: 43812 | U55: =TODAY()-T55 -> 2397 | V55: =IF(M55="Critical",T55+10,IF(M55="High",T55+30,IF(M55="Bad",T55+30,IF(M55="Medium",T55+90,IF(M55="Warm",T55+90,IF(M55="Low",T55+120,IF(M55="Fair",T55+120,IF(M55="Neutral",T55+120,"")))))))) -> 43902 | W55: =IF(M55="Critical",IF(U55>10,"SLA Vencido","En SLA"),IF(M55="High",IF(U55>30,"SLA Vencido","En SLA"),IF(M55="Bad",IF(U55>30,"SLA Vencido","En SLA"),IF(M55="Medium",IF(U55>90,"SLA Vencido","En SLA"),IF(M55="Warm",IF(U55>90,"SLA Vencido","En SLA"),IF(M55="Low",IF(U55>120,"SLA Vencido","En SLA"),IF(M55="Fair",IF(U55>120,"SLA Vencido","En SLA"),IF(M55="Neutral",IF(U55>120,"SLA Vencido","En SLA"),"Error")))))))) -> SLA Vencido | AA55: 43969 | AB55: Firewall host : FWCOLBSNC1 SmartCenter host : InternetNala | AC55: Cisco recommends that access to this service is limited to only those IP addresses specifically requiring it. | AF55: Certificada | AH55: =IFERROR(VLOOKUP(H55,hoja1!A:A,1,),"N/A") -> N/A
A56: 55 | B56: BSNC | C56: Task Force | D56: Telecomunicaciones | G56: fw.santander.com.co/Peer del Firewall | J56: Check Point ‘SecuRemote’ Hostname Information Disclosure | K56: CWE-201: Information Exposure Through Sent Data | L56: Solved | M56: Medium | P56: 170.169.127.22 | R56: 264 | S56: TCP | T56: 43812 | U56: =TODAY()-T56 -> 2397 | V56: =IF(M56="Critical",T56+10,IF(M56="High",T56+30,IF(M56="Bad",T56+30,IF(M56="Medium",T56+90,IF(M56="Warm",T56+90,IF(M56="Low",T56+120,IF(M56="Fair",T56+120,IF(M56="Neutral",T56+120,"")))))))) -> 43902 | W56: =IF(M56="Critical",IF(U56>10,"SLA Vencido","En SLA"),IF(M56="High",IF(U56>30,"SLA Vencido","En SLA"),IF(M56="Bad",IF(U56>30,"SLA Vencido","En SLA"),IF(M56="Medium",IF(U56>90,"SLA Vencido","En SLA"),IF(M56="Warm",IF(U56>90,"SLA Vencido","En SLA"),IF(M56="Low",IF(U56>120,"SLA Vencido","En SLA"),IF(M56="Fair",IF(U56>120,"SLA Vencido","En SLA"),IF(M56="Neutral",IF(U56>120,"SLA Vencido","En SLA"),"Error")))))))) -> SLA Vencido | AA56: 44069 | AB56: Firewall host : FWCORE02_VPN_Nala SmartCenter host : InternetNala | AC56: Cisco recommends that access to this service is limited to only those IP addresses specifically requiring it. | AF56: Certificada | AH56: =IFERROR(VLOOKUP(H56,hoja1!A:A,1,),"N/A") -> N/A
A57: 56 | B57: BSNC | C57: Task Force | D57: Telecomunicaciones | G57: Internet invitados principal Santander (Wifi Ppal) | J57: Check Point ‘SecuRemote’ Hostname Information Disclosure | K57: CWE-201: Information Exposure Through Sent Data | L57: Solved | M57: Medium | P57: 181.49.176.5 | R57: 264 | S57: TCP | T57: 43812 | U57: =TODAY()-T57 -> 2397 | V57: =IF(M57="Critical",T57+10,IF(M57="High",T57+30,IF(M57="Bad",T57+30,IF(M57="Medium",T57+90,IF(M57="Warm",T57+90,IF(M57="Low",T57+120,IF(M57="Fair",T57+120,IF(M57="Neutral",T57+120,"")))))))) -> 43902 | W57: =IF(M57="Critical",IF(U57>10,"SLA Vencido","En SLA"),IF(M57="High",IF(U57>30,"SLA Vencido","En SLA"),IF(M57="Bad",IF(U57>30,"SLA Vencido","En SLA"),IF(M57="Medium",IF(U57>90,"SLA Vencido","En SLA"),IF(M57="Warm",IF(U57>90,"SLA Vencido","En SLA"),IF(M57="Low",IF(U57>120,"SLA Vencido","En SLA"),IF(M57="Fair",IF(U57>120,"SLA Vencido","En SLA"),IF(M57="Neutral",IF(U57>120,"SLA Vencido","En SLA"),"Error")))))))) -> SLA Vencido | AA57: 43969 | AB57: Firewall host : FWCOLBSNC2 SmartCenter host : InternetNala | AC57: Cisco recommends that access to this service is limited to only those IP addresses specifically requiring it. | AF57: Certificada | AH57: =IFERROR(VLOOKUP(H57,hoja1!A:A,1,),"N/A") -> N/A
A58: 57 | B58: BSNC | C58: Task Force | D58: Telecomunicaciones | G58: Internet Backup Santander (Cableada | J58: Cisco IOS IKEv1 Packet Handling Remote Information Disclosure | K58: CWE-0: Missing Security Patches | L58: Dismissed | M58: Medium | P58: 190216136241 | R58: 500 | S58: UDP | T58: 43812 | U58: =TODAY()-T58 -> 2397 | V58: =IF(M58="Critical",T58+10,IF(M58="High",T58+30,IF(M58="Bad",T58+30,IF(M58="Medium",T58+90,IF(M58="Warm",T58+90,IF(M58="Low",T58+120,IF(M58="Fair",T58+120,IF(M58="Neutral",T58+120,"")))))))) -> 43902 | W58: =IF(M58="Critical",IF(U58>10,"SLA Vencido","En SLA"),IF(M58="High",IF(U58>30,"SLA Vencido","En SLA"),IF(M58="Bad",IF(U58>30,"SLA Vencido","En SLA"),IF(M58="Medium",IF(U58>90,"SLA Vencido","En SLA"),IF(M58="Warm",IF(U58>90,"SLA Vencido","En SLA"),IF(M58="Low",IF(U58>120,"SLA Vencido","En SLA"),IF(M58="Fair",IF(U58>120,"SLA Vencido","En SLA"),IF(M58="Neutral",IF(U58>120,"SLA Vencido","En SLA"),"Error")))))))) -> SLA Vencido | AB58: Cisco was able to get the following IKE vendor ID(s) : CISCO-DELETE-REASON FLEXVPN-SUPPORTED | AC58: Cisco recommends upgrading to the relevant fixed version referenced in Cisco bug ID CSCvb29204. | AF58: En proceso de certificacion. No fue certificada Susana Tovar: La red ya no existen Javier Leon: dado que el servicio se canceló y que son segmentos públicos el proveedor de servicio reasigno el direccionamiento a otro cliente. | AH58: =IFERROR(VLOOKUP(H58,hoja1!A:A,1,),"N/A") -> N/A
A59: 58 | B59: BSNC | C59: Task Force | D59: Telecomunicaciones | G59: Internet principal Santander (Cableada) | J59: Cisco IOS IKEv1 Packet Handling Remote Information Disclosure | K59: CWE-0: Missing Security Patches | L59: Solved | M59: Medium | P59: 181.48.106.210 | R59: 500 | S59: UDP | T59: 43812 | U59: =TODAY()-T59 -> 2397 | V59: =IF(M59="Critical",T59+10,IF(M59="High",T59+30,IF(M59="Bad",T59+30,IF(M59="Medium",T59+90,IF(M59="Warm",T59+90,IF(M59="Low",T59+120,IF(M59="Fair",T59+120,IF(M59="Neutral",T59+120,"")))))))) -> 43902 | W59: =IF(M59="Critical",IF(U59>10,"SLA Vencido","En SLA"),IF(M59="High",IF(U59>30,"SLA Vencido","En SLA"),IF(M59="Bad",IF(U59>30,"SLA Vencido","En SLA"),IF(M59="Medium",IF(U59>90,"SLA Vencido","En SLA"),IF(M59="Warm",IF(U59>90,"SLA Vencido","En SLA"),IF(M59="Low",IF(U59>120,"SLA Vencido","En SLA"),IF(M59="Fair",IF(U59>120,"SLA Vencido","En SLA"),IF(M59="Neutral",IF(U59>120,"SLA Vencido","En SLA"),"Error")))))))) -> SLA Vencido | AA59: 43969 | AB59: Cisco was able to get the following IKE vendor ID(s) : CISCO-DELETE-REASON FLEXVPN-SUPPORTED | AC59: Cisco recommends upgrading to the relevant fixed version referenced in Cisco bug ID CSCvb29204. | AF59: Certificada | AH59: =IFERROR(VLOOKUP(H59,hoja1!A:A,1,),"N/A") -> N/A
A60: 59 | B60: BSNC | C60: Task Force | D60: Telecomunicaciones | G60: Internet principal Santander (Cableada) | J60: Cisco IOS IKEv1 Packet Handling Remote Information Disclosure | K60: CWE-0: Missing Security Patches | L60: Solved | M60: Medium | P60: 181.48.106.209 | R60: 500 | S60: UDP | T60: 43812 | U60: =TODAY()-T60 -> 2397 | V60: =IF(M60="Critical",T60+10,IF(M60="High",T60+30,IF(M60="Bad",T60+30,IF(M60="Medium",T60+90,IF(M60="Warm",T60+90,IF(M60="Low",T60+120,IF(M60="Fair",T60+120,IF(M60="Neutral",T60+120,"")))))))) -> 43902 | W60: =IF(M60="Critical",IF(U60>10,"SLA Vencido","En SLA"),IF(M60="High",IF(U60>30,"SLA Vencido","En SLA"),IF(M60="Bad",IF(U60>30,"SLA Vencido","En SLA"),IF(M60="Medium",IF(U60>90,"SLA Vencido","En SLA"),IF(M60="Warm",IF(U60>90,"SLA Vencido","En SLA"),IF(M60="Low",IF(U60>120,"SLA Vencido","En SLA"),IF(M60="Fair",IF(U60>120,"SLA Vencido","En SLA"),IF(M60="Neutral",IF(U60>120,"SLA Vencido","En SLA"),"Error")))))))) -> SLA Vencido | AA60: 43969 | AB60: Cisco was able to get the following IKE vendor ID(s) : CISCO-DELETE-REASON FLEXVPN-SUPPORTED | AC60: Cisco recommends upgrading to the relevant fixed version referenced in Cisco bug ID CSCvb29204. | AF60: Certificada | AH60: =IFERROR(VLOOKUP(H60,hoja1!A:A,1,),"N/A") -> N/A
A61: 60 | B61: BSNC | C61: Task Force | D61: Telecomunicaciones | G61: Internet Backup Santander (Cableada | J61: Cisco IOS IKEv1 Packet Handling Remote Information Disclosure | K61: CWE-0: Missing Security Patches | L61: Dismissed | M61: Medium | P61: 190216136242 | R61: 500 | S61: UDP | T61: 43812 | U61: =TODAY()-T61 -> 2397 | V61: =IF(M61="Critical",T61+10,IF(M61="High",T61+30,IF(M61="Bad",T61+30,IF(M61="Medium",T61+90,IF(M61="Warm",T61+90,IF(M61="Low",T61+120,IF(M61="Fair",T61+120,IF(M61="Neutral",T61+120,"")))))))) -> 43902 | W61: =IF(M61="Critical",IF(U61>10,"SLA Vencido","En SLA"),IF(M61="High",IF(U61>30,"SLA Vencido","En SLA"),IF(M61="Bad",IF(U61>30,"SLA Vencido","En SLA"),IF(M61="Medium",IF(U61>90,"SLA Vencido","En SLA"),IF(M61="Warm",IF(U61>90,"SLA Vencido","En SLA"),IF(M61="Low",IF(U61>120,"SLA Vencido","En SLA"),IF(M61="Fair",IF(U61>120,"SLA Vencido","En SLA"),IF(M61="Neutral",IF(U61>120,"SLA Vencido","En SLA"),"Error")))))))) -> SLA Vencido | AB61: Cisco was able to get the following IKE vendor ID(s) : CISCO-DELETE-REASON FLEXVPN-SUPPORTED | AC61: Cisco recommends upgrading to the relevant fixed version referenced in Cisco bug ID CSCvb29204. | AF61: En proceso de certificacion. No fue certificada Susana Tovar: La red ya no existen Javier Leon: dado que el servicio se canceló y que son segmentos públicos el proveedor de servicio reasigno el direccionamiento a otro cliente. | AH61: =IFERROR(VLOOKUP(H61,hoja1!A:A,1,),"N/A") -> N/A
A62: 61 | B62: BSNC | C62: Task Force | D62: Telecomunicaciones | G62: fw.santander.com.co/Peer del Firewall | J62: SSL Certificate Signed Using A Weak Hashing Algorithm | K62: CWE-327: Use of a Broken or Unreliable Cryptographic Algorithm | L62: Solved | M62: Medium | P62: 170.169.127.22 | R62: 443 | S62: TCP | T62: 43812 | U62: =TODAY()-T62 -> 2397 | V62: =IF(M62="Critical",T62+10,IF(M62="High",T62+30,IF(M62="Bad",T62+30,IF(M62="Medium",T62+90,IF(M62="Warm",T62+90,IF(M62="Low",T62+120,IF(M62="Fair",T62+120,IF(M62="Neutral",T62+120,"")))))))) -> 43902 | W62: =IF(M62="Critical",IF(U62>10,"SLA Vencido","En SLA"),IF(M62="High",IF(U62>30,"SLA Vencido","En SLA"),IF(M62="Bad",IF(U62>30,"SLA Vencido","En SLA"),IF(M62="Medium",IF(U62>90,"SLA Vencido","En SLA"),IF(M62="Warm",IF(U62>90,"SLA Vencido","En SLA"),IF(M62="Low",IF(U62>120,"SLA Vencido","En SLA"),IF(M62="Fair",IF(U62>120,"SLA Vencido","En SLA"),IF(M62="Neutral",IF(U62>120,"SLA Vencido","En SLA"),"Error")))))))) -> SLA Vencido | AA62: 43969 | AB62: The following certificates were part of the certificate chain sent by the remote host, but contain hashes that are considered to be weak. Subject : O=InternetNala..fgvprc Signature Algorithm : SHA-1 With RSA Encryption Valid From : Sep 12 14:32:37 2013 GMT Valid To : Sep 07 14:32:37 2033 GMT Subject : O=InternetNala..fgvprc/CN=VPN_Nala VPN Certificate Signature Algorithm : SHA-1 With RSA Encryption Valid From : Oct 16 03:24:58 2016 GMT Valid To : Oct 16 03:24:58 2021 GMT | AC62: Cisco recommends that only SSL certificates with a strong hashing algorithm, such as SHA256, are used. | AF62: Certificada | AH62: =IFERROR(VLOOKUP(H62,hoja1!A:A,1,),"N/A") -> N/A
A63: 62 | B63: BSNC | C63: Task Force | D63: Telecomunicaciones | G63: Internet Backup Santander (Cableada | J63: Internet Key Exchange (IKE) Aggressive Mode With Pre-Shared Key | K63: CWE-327: Use of a Broken or Unreliable Cryptographic Algorithm | L63: Dismissed | M63: Medium | P63: 190216136242 | R63: 500 | S63: UDP | T63: 43812 | U63: =TODAY()-T63 -> 2397 | V63: =IF(M63="Critical",T63+10,IF(M63="High",T63+30,IF(M63="Bad",T63+30,IF(M63="Medium",T63+90,IF(M63="Warm",T63+90,IF(M63="Low",T63+120,IF(M63="Fair",T63+120,IF(M63="Neutral",T63+120,"")))))))) -> 43902 | W63: =IF(M63="Critical",IF(U63>10,"SLA Vencido","En SLA"),IF(M63="High",IF(U63>30,"SLA Vencido","En SLA"),IF(M63="Bad",IF(U63>30,"SLA Vencido","En SLA"),IF(M63="Medium",IF(U63>90,"SLA Vencido","En SLA"),IF(M63="Warm",IF(U63>90,"SLA Vencido","En SLA"),IF(M63="Low",IF(U63>120,"SLA Vencido","En SLA"),IF(M63="Fair",IF(U63>120,"SLA Vencido","En SLA"),IF(M63="Neutral",IF(U63>120,"SLA Vencido","En SLA"),"Error")))))))) -> SLA Vencido | AB63: 190.216.136.242 Notify message 14 (NO-PROPOSAL-CHOSEN) HDR=(CKY-R=c9abf8bedbdd981a) | AC63: Cisco recommends disabling Aggressive Mode and discontinuing the use of PSK for authentication, where possible. If, however, the use of PSK cannot be avoided, then only very strong keys should be used. In addition, where possible, VPN connections should not be permitted from arbitrary IP addresses, although Cisco recognises that this may be impractical for roaming users. | AF63: En proceso de certificacion. No fue certificada Susana Tovar: La red ya no existen Javier Leon: dado que el servicio se canceló y que son segmentos públicos el proveedor de servicio reasigno el direccionamiento a otro cliente. | AH63: =IFERROR(VLOOKUP(H63,hoja1!A:A,1,),"N/A") -> N/A
A64: 63 | B64: BSNC | C64: Task Force | D64: Telecomunicaciones | G64: Internet Backup Santander (Cableada | J64: Internet Key Exchange (IKE) Aggressive Mode With Pre-Shared Key | K64: CWE-327: Use of a Broken or Unreliable Cryptographic Algorithm | L64: Dismissed | M64: Medium | P64: 190216136241 | R64: 500 | S64: UDP | T64: 43812 | U64: =TODAY()-T64 -> 2397 | V64: =IF(M64="Critical",T64+10,IF(M64="High",T64+30,IF(M64="Bad",T64+30,IF(M64="Medium",T64+90,IF(M64="Warm",T64+90,IF(M64="Low",T64+120,IF(M64="Fair",T64+120,IF(M64="Neutral",T64+120,"")))))))) -> 43902 | W64: =IF(M64="Critical",IF(U64>10,"SLA Vencido","En SLA"),IF(M64="High",IF(U64>30,"SLA Vencido","En SLA"),IF(M64="Bad",IF(U64>30,"SLA Vencido","En SLA"),IF(M64="Medium",IF(U64>90,"SLA Vencido","En SLA"),IF(M64="Warm",IF(U64>90,"SLA Vencido","En SLA"),IF(M64="Low",IF(U64>120,"SLA Vencido","En SLA"),IF(M64="Fair",IF(U64>120,"SLA Vencido","En SLA"),IF(M64="Neutral",IF(U64>120,"SLA Vencido","En SLA"),"Error")))))))) -> SLA Vencido | AB64: 190.216.136.241 Notify message 14 (NO-PROPOSAL-CHOSEN) HDR=(CKY-R=9edf4bb7af18e785) | AC64: Cisco recommends disabling Aggressive Mode and discontinuing the use of PSK for authentication, where possible. If, however, the use of PSK cannot be avoided, then only very strong keys should be used. In addition, where possible, VPN connections should not be permitted from arbitrary IP addresses, although Cisco recognises that this may be impractical for roaming users. | AF64: En proceso de certificacion. No fue certificada Susana Tovar: La red ya no existen Javier Leon: dado que el servicio se canceló y que son segmentos públicos el proveedor de servicio reasigno el direccionamiento a otro cliente. | AH64: =IFERROR(VLOOKUP(H64,hoja1!A:A,1,),"N/A") -> N/A
A65: 64 | B65: BSNC | C65: Task Force | D65: Telecomunicaciones | G65: Internet principal Santander (Cableada) | J65: Internet Key Exchange (IKE) Aggressive Mode With Pre-Shared Key | K65: CWE-327: Use of a Broken or Unreliable Cryptographic Algorithm | L65: Solved | M65: Medium | P65: 181.48.106.209 | R65: 500 | S65: UDP | T65: 43812 | U65: =TODAY()-T65 -> 2397 | V65: =IF(M65="Critical",T65+10,IF(M65="High",T65+30,IF(M65="Bad",T65+30,IF(M65="Medium",T65+90,IF(M65="Warm",T65+90,IF(M65="Low",T65+120,IF(M65="Fair",T65+120,IF(M65="Neutral",T65+120,"")))))))) -> 43902 | W65: =IF(M65="Critical",IF(U65>10,"SLA Vencido","En SLA"),IF(M65="High",IF(U65>30,"SLA Vencido","En SLA"),IF(M65="Bad",IF(U65>30,"SLA Vencido","En SLA"),IF(M65="Medium",IF(U65>90,"SLA Vencido","En SLA"),IF(M65="Warm",IF(U65>90,"SLA Vencido","En SLA"),IF(M65="Low",IF(U65>120,"SLA Vencido","En SLA"),IF(M65="Fair",IF(U65>120,"SLA Vencido","En SLA"),IF(M65="Neutral",IF(U65>120,"SLA Vencido","En SLA"),"Error")))))))) -> SLA Vencido | AA65: 43969 | AB65: 181.48.106.209 Notify message 14 (NO-PROPOSAL-CHOSEN) HDR=(CKY-R=da7f53d3bac5babb) | AC65: Cisco recommends disabling Aggressive Mode and discontinuing the use of PSK for authentication, where possible. If, however, the use of PSK cannot be avoided, then only very strong keys should be used. In addition, where possible, VPN connections should not be permitted from arbitrary IP addresses, although Cisco recognises that this may be impractical for roaming users. | AF65: Certificada | AH65: =IFERROR(VLOOKUP(H65,hoja1!A:A,1,),"N/A") -> N/A
A66: 65 | B66: BSNC | C66: Task Force | D66: Telecomunicaciones | G66: Internet principal Santander (Cableada) | J66: Internet Key Exchange (IKE) Aggressive Mode With Pre-Shared Key | K66: CWE-327: Use of a Broken or Unreliable Cryptographic Algorithm | L66: Solved | M66: Medium | P66: 181.48.106.210 | R66: 500 | S66: UDP | T66: 43812 | U66: =TODAY()-T66 -> 2397 | V66: =IF(M66="Critical",T66+10,IF(M66="High",T66+30,IF(M66="Bad",T66+30,IF(M66="Medium",T66+90,IF(M66="Warm",T66+90,IF(M66="Low",T66+120,IF(M66="Fair",T66+120,IF(M66="Neutral",T66+120,"")))))))) -> 43902 | W66: =IF(M66="Critical",IF(U66>10,"SLA Vencido","En SLA"),IF(M66="High",IF(U66>30,"SLA Vencido","En SLA"),IF(M66="Bad",IF(U66>30,"SLA Vencido","En SLA"),IF(M66="Medium",IF(U66>90,"SLA Vencido","En SLA"),IF(M66="Warm",IF(U66>90,"SLA Vencido","En SLA"),IF(M66="Low",IF(U66>120,"SLA Vencido","En SLA"),IF(M66="Fair",IF(U66>120,"SLA Vencido","En SLA"),IF(M66="Neutral",IF(U66>120,"SLA Vencido","En SLA"),"Error")))))))) -> SLA Vencido | AA66: 43969 | AB66: 181.48.106.210 Notify message 14 (NO-PROPOSAL-CHOSEN) HDR=(CKY-R=8361bdd290f487fd) | AC66: Cisco recommends disabling Aggressive Mode and discontinuing the use of PSK for authentication, where possible. If, however, the use of PSK cannot be avoided, then only very strong keys should be used. In addition, where possible, VPN connections should not be permitted from arbitrary IP addresses, although Cisco recognises that this may be impractical for roaming users. | AF66: Certificada | AH66: =IFERROR(VLOOKUP(H66,hoja1!A:A,1,),"N/A") -> N/A
A67: 66 | B67: BSNC | C67: Task Force | D67: Telecomunicaciones | G67: Internet invitados principal Santander (Wifi Ppal) | J67: IPSec IKE Detection | K67: CWE-200: Information Exposure | L67: Solved | M67: Low | P67: 181.49.176.3 | R67: 500 | S67: UDP | T67: 43812 | U67: =TODAY()-T67 -> 2397 | V67: =IF(M67="Critical",T67+10,IF(M67="High",T67+30,IF(M67="Bad",T67+30,IF(M67="Medium",T67+90,IF(M67="Warm",T67+90,IF(M67="Low",T67+120,IF(M67="Fair",T67+120,IF(M67="Neutral",T67+120,"")))))))) -> 43932 | W67: =IF(M67="Critical",IF(U67>10,"SLA Vencido","En SLA"),IF(M67="High",IF(U67>30,"SLA Vencido","En SLA"),IF(M67="Bad",IF(U67>30,"SLA Vencido","En SLA"),IF(M67="Medium",IF(U67>90,"SLA Vencido","En SLA"),IF(M67="Warm",IF(U67>90,"SLA Vencido","En SLA"),IF(M67="Low",IF(U67>120,"SLA Vencido","En SLA"),IF(M67="Fair",IF(U67>120,"SLA Vencido","En SLA"),IF(M67="Neutral",IF(U67>120,"SLA Vencido","En SLA"),"Error")))))))) -> SLA Vencido | AA67: 43969 | AC67: Cisco recommends that this service is disabled if it is not required, or alternatively that incoming traffic to the affected port is filtered. | AF67: Certificada | AH67: =IFERROR(VLOOKUP(H67,hoja1!A:A,1,),"N/A") -> N/A
A68: 67 | B68: BSNC | C68: Task Force | D68: Telecomunicaciones | G68: Internet Backup Santander (Cableada | J68: IPSec IKE Detection | K68: CWE-200: Information Exposure | L68: Dismissed | M68: Low | P68: 190216136242 | R68: 500 | S68: UDP | T68: 43812 | U68: =TODAY()-T68 -> 2397 | V68: =IF(M68="Critical",T68+10,IF(M68="High",T68+30,IF(M68="Bad",T68+30,IF(M68="Medium",T68+90,IF(M68="Warm",T68+90,IF(M68="Low",T68+120,IF(M68="Fair",T68+120,IF(M68="Neutral",T68+120,"")))))))) -> 43932 | W68: =IF(M68="Critical",IF(U68>10,"SLA Vencido","En SLA"),IF(M68="High",IF(U68>30,"SLA Vencido","En SLA"),IF(M68="Bad",IF(U68>30,"SLA Vencido","En SLA"),IF(M68="Medium",IF(U68>90,"SLA Vencido","En SLA"),IF(M68="Warm",IF(U68>90,"SLA Vencido","En SLA"),IF(M68="Low",IF(U68>120,"SLA Vencido","En SLA"),IF(M68="Fair",IF(U68>120,"SLA Vencido","En SLA"),IF(M68="Neutral",IF(U68>120,"SLA Vencido","En SLA"),"Error")))))))) -> SLA Vencido | AB68: Cisco was able to get the following IKE vendor ID(s) : CISCO-DELETE-REASON FLEXVPN-SUPPORTED | AC68: Cisco recommends that this service is disabled if it is not required, or alternatively that incoming traffic to the affected port is filtered. | AF68: En proceso de certificacion. No fue certificada Susana Tovar: La red ya no existen Javier Leon: dado que el servicio se canceló y que son segmentos públicos el proveedor de servicio reasigno el direccionamiento a otro cliente. | AH68: =IFERROR(VLOOKUP(H68,hoja1!A:A,1,),"N/A") -> N/A
A69: 68 | B69: BSNC | C69: Task Force | D69: Telecomunicaciones | G69: Internet invitados principal Santander (Wifi Ppal) | J69: IPSec IKE Detection | K69: CWE-200: Information Exposure | L69: Solved | M69: Low | P69: 181.49.176.5 | R69: 500 | S69: UDP | T69: 43812 | U69: =TODAY()-T69 -> 2397 | V69: =IF(M69="Critical",T69+10,IF(M69="High",T69+30,IF(M69="Bad",T69+30,IF(M69="Medium",T69+90,IF(M69="Warm",T69+90,IF(M69="Low",T69+120,IF(M69="Fair",T69+120,IF(M69="Neutral",T69+120,"")))))))) -> 43932 | W69: =IF(M69="Critical",IF(U69>10,"SLA Vencido","En SLA"),IF(M69="High",IF(U69>30,"SLA Vencido","En SLA"),IF(M69="Bad",IF(U69>30,"SLA Vencido","En SLA"),IF(M69="Medium",IF(U69>90,"SLA Vencido","En SLA"),IF(M69="Warm",IF(U69>90,"SLA Vencido","En SLA"),IF(M69="Low",IF(U69>120,"SLA Vencido","En SLA"),IF(M69="Fair",IF(U69>120,"SLA Vencido","En SLA"),IF(M69="Neutral",IF(U69>120,"SLA Vencido","En SLA"),"Error")))))))) -> SLA Vencido | AA69: 43969 | AC69: Cisco recommends that this service is disabled if it is not required, or alternatively that incoming traffic to the affected port is filtered. | AF69: Certificada | AH69: =IFERROR(VLOOKUP(H69,hoja1!A:A,1,),"N/A") -> N/A
A70: 69 | B70: BSNC | C70: Task Force | D70: Telecomunicaciones | G70: Internet Backup Santander (Cableada | J70: IPSec IKE Detection | K70: CWE-200: Information Exposure | L70: Dismissed | M70: Low | P70: 190216136241 | R70: 500 | S70: UDP | T70: 43812 | U70: =TODAY()-T70 -> 2397 | V70: =IF(M70="Critical",T70+10,IF(M70="High",T70+30,IF(M70="Bad",T70+30,IF(M70="Medium",T70+90,IF(M70="Warm",T70+90,IF(M70="Low",T70+120,IF(M70="Fair",T70+120,IF(M70="Neutral",T70+120,"")))))))) -> 43932 | W70: =IF(M70="Critical",IF(U70>10,"SLA Vencido","En SLA"),IF(M70="High",IF(U70>30,"SLA Vencido","En SLA"),IF(M70="Bad",IF(U70>30,"SLA Vencido","En SLA"),IF(M70="Medium",IF(U70>90,"SLA Vencido","En SLA"),IF(M70="Warm",IF(U70>90,"SLA Vencido","En SLA"),IF(M70="Low",IF(U70>120,"SLA Vencido","En SLA"),IF(M70="Fair",IF(U70>120,"SLA Vencido","En SLA"),IF(M70="Neutral",IF(U70>120,"SLA Vencido","En SLA"),"Error")))))))) -> SLA Vencido | AB70: Cisco was able to get the following IKE vendor ID(s) : CISCO-DELETE-REASON FLEXVPN-SUPPORTED | AC70: Cisco recommends that this service is disabled if it is not required, or alternatively that incoming traffic to the affected port is filtered. | AF70: En proceso de certificacion. No fue certificada Susana Tovar: La red ya no existen Javier Leon: dado que el servicio se canceló y que son segmentos públicos el proveedor de servicio reasigno el direccionamiento a otro cliente. | AH70: =IFERROR(VLOOKUP(H70,hoja1!A:A,1,),"N/A") -> N/A
A71: 70 | B71: BSNC | C71: Task Force | D71: Telecomunicaciones | G71: Internet principal Santander (Cableada) | J71: IPSec IKE Detection | K71: CWE-200: Information Exposure | L71: Solved | M71: Low | P71: 181.48.106.209 | R71: 500 | S71: UDP | T71: 43812 | U71: =TODAY()-T71 -> 2397 | V71: =IF(M71="Critical",T71+10,IF(M71="High",T71+30,IF(M71="Bad",T71+30,IF(M71="Medium",T71+90,IF(M71="Warm",T71+90,IF(M71="Low",T71+120,IF(M71="Fair",T71+120,IF(M71="Neutral",T71+120,"")))))))) -> 43932 | W71: =IF(M71="Critical",IF(U71>10,"SLA Vencido","En SLA"),IF(M71="High",IF(U71>30,"SLA Vencido","En SLA"),IF(M71="Bad",IF(U71>30,"SLA Vencido","En SLA"),IF(M71="Medium",IF(U71>90,"SLA Vencido","En SLA"),IF(M71="Warm",IF(U71>90,"SLA Vencido","En SLA"),IF(M71="Low",IF(U71>120,"SLA Vencido","En SLA"),IF(M71="Fair",IF(U71>120,"SLA Vencido","En SLA"),IF(M71="Neutral",IF(U71>120,"SLA Vencido","En SLA"),"Error")))))))) -> SLA Vencido | AA71: 43969 | AB71: Cisco was able to get the following IKE vendor ID(s) : CISCO-DELETE-REASON FLEXVPN-SUPPORTED | AC71: Cisco recommends that this service is disabled if it is not required, or alternatively that incoming traffic to the affected port is filtered. | AF71: Certificada | AH71: =IFERROR(VLOOKUP(H71,hoja1!A:A,1,),"N/A") -> N/A
A72: 71 | B72: BSNC | C72: Task Force | D72: Telecomunicaciones | G72: Internet invitados principal Santander (Wifi Ppal) | J72: IPSec IKE Detection | K72: CWE-200: Information Exposure | L72: Solved | M72: Low | P72: 181.49.176.4 | R72: 500 | S72: UDP | T72: 43812 | U72: =TODAY()-T72 -> 2397 | V72: =IF(M72="Critical",T72+10,IF(M72="High",T72+30,IF(M72="Bad",T72+30,IF(M72="Medium",T72+90,IF(M72="Warm",T72+90,IF(M72="Low",T72+120,IF(M72="Fair",T72+120,IF(M72="Neutral",T72+120,"")))))))) -> 43932 | W72: =IF(M72="Critical",IF(U72>10,"SLA Vencido","En SLA"),IF(M72="High",IF(U72>30,"SLA Vencido","En SLA"),IF(M72="Bad",IF(U72>30,"SLA Vencido","En SLA"),IF(M72="Medium",IF(U72>90,"SLA Vencido","En SLA"),IF(M72="Warm",IF(U72>90,"SLA Vencido","En SLA"),IF(M72="Low",IF(U72>120,"SLA Vencido","En SLA"),IF(M72="Fair",IF(U72>120,"SLA Vencido","En SLA"),IF(M72="Neutral",IF(U72>120,"SLA Vencido","En SLA"),"Error")))))))) -> SLA Vencido | AA72: 43969 | AC72: Cisco recommends that this service is disabled if it is not required, or alternatively that incoming traffic to the affected port is filtered. | AF72: Certificada | AH72: =IFERROR(VLOOKUP(H72,hoja1!A:A,1,),"N/A") -> N/A
A73: 72 | B73: BSNC | C73: Task Force | D73: Telecomunicaciones | G73: fw.santander.com.co/Peer del Firewall | J73: IPSec IKE Detection | K73: CWE-200: Information Exposure | L73: Dismissed | M73: Low | P73: 170.169.127.22 | R73: 500 | S73: UDP | T73: 43812 | U73: =TODAY()-T73 -> 2397 | V73: =IF(M73="Critical",T73+10,IF(M73="High",T73+30,IF(M73="Bad",T73+30,IF(M73="Medium",T73+90,IF(M73="Warm",T73+90,IF(M73="Low",T73+120,IF(M73="Fair",T73+120,IF(M73="Neutral",T73+120,"")))))))) -> 43932 | W73: =IF(M73="Critical",IF(U73>10,"SLA Vencido","En SLA"),IF(M73="High",IF(U73>30,"SLA Vencido","En SLA"),IF(M73="Bad",IF(U73>30,"SLA Vencido","En SLA"),IF(M73="Medium",IF(U73>90,"SLA Vencido","En SLA"),IF(M73="Warm",IF(U73>90,"SLA Vencido","En SLA"),IF(M73="Low",IF(U73>120,"SLA Vencido","En SLA"),IF(M73="Fair",IF(U73>120,"SLA Vencido","En SLA"),IF(M73="Neutral",IF(U73>120,"SLA Vencido","En SLA"),"Error")))))))) -> SLA Vencido | AB73: Cisco was able to get the following IKE vendor ID(s): IKE Fragmentation Firewall-1 Unknown Vsn | AC73: Cisco recommends that this service is disabled if it is not required, or alternatively that incoming traffic to the affected port is filtered. | AF73: En proceso de Certificacion. Se envió la evidencia para aceptar la vulnerabilidad, dado a que por el puerto 500 esta establacida la VPN | AH73: =IFERROR(VLOOKUP(H73,hoja1!A:A,1,),"N/A") -> N/A
A74: 73 | B74: BSNC | C74: Task Force | D74: Telecomunicaciones | G74: Internet principal Santander (Cableada) | J74: IPSec IKE Detection | K74: CWE-200: Information Exposure | L74: Solved | M74: Low | P74: 181.48.106.210 | R74: 500 | S74: UDP | T74: 43812 | U74: =TODAY()-T74 -> 2397 | V74: =IF(M74="Critical",T74+10,IF(M74="High",T74+30,IF(M74="Bad",T74+30,IF(M74="Medium",T74+90,IF(M74="Warm",T74+90,IF(M74="Low",T74+120,IF(M74="Fair",T74+120,IF(M74="Neutral",T74+120,"")))))))) -> 43932 | W74: =IF(M74="Critical",IF(U74>10,"SLA Vencido","En SLA"),IF(M74="High",IF(U74>30,"SLA Vencido","En SLA"),IF(M74="Bad",IF(U74>30,"SLA Vencido","En SLA"),IF(M74="Medium",IF(U74>90,"SLA Vencido","En SLA"),IF(M74="Warm",IF(U74>90,"SLA Vencido","En SLA"),IF(M74="Low",IF(U74>120,"SLA Vencido","En SLA"),IF(M74="Fair",IF(U74>120,"SLA Vencido","En SLA"),IF(M74="Neutral",IF(U74>120,"SLA Vencido","En SLA"),"Error")))))))) -> SLA Vencido | AA74: 43969 | AB74: Cisco was able to get the following IKE vendor ID(s) : CISCO-DELETE-REASON FLEXVPN-SUPPORTED | AC74: Cisco recommends that this service is disabled if it is not required, or alternatively that incoming traffic to the affected port is filtered. | AF74: Certificada | AH74: =IFERROR(VLOOKUP(H74,hoja1!A:A,1,),"N/A") -> N/A
A75: 74 | B75: BSNC | C75: Task Force | D75: Telecomunicaciones | G75: Internet invitados Backup Santander (Wifi Backup) | J75: System Responds To ICMP ‘Timestamp’ Requests | K75: CWE-200: Information Exposure | L75: Solved | M75: Low | P75: 181.48.20.104 | T75: 43812 | U75: =TODAY()-T75 -> 2397 | V75: =IF(M75="Critical",T75+10,IF(M75="High",T75+30,IF(M75="Bad",T75+30,IF(M75="Medium",T75+90,IF(M75="Warm",T75+90,IF(M75="Low",T75+120,IF(M75="Fair",T75+120,IF(M75="Neutral",T75+120,"")))))))) -> 43932 | W75: =IF(M75="Critical",IF(U75>10,"SLA Vencido","En SLA"),IF(M75="High",IF(U75>30,"SLA Vencido","En SLA"),IF(M75="Bad",IF(U75>30,"SLA Vencido","En SLA"),IF(M75="Medium",IF(U75>90,"SLA Vencido","En SLA"),IF(M75="Warm",IF(U75>90,"SLA Vencido","En SLA"),IF(M75="Low",IF(U75>120,"SLA Vencido","En SLA"),IF(M75="Fair",IF(U75>120,"SLA Vencido","En SLA"),IF(M75="Neutral",IF(U75>120,"SLA Vencido","En SLA"),"Error")))))))) -> SLA Vencido | AA75: 43969 | AB75: This host returns non-standard timestamps (high bit is set) | AC75: Cisco recommends that, wherever possible, systems should be configured not to respond to any ICMP requests. In addition, each firewall should be configured to drop all ICMP traffic. Where a case can be made for ICMP traffic to be allowed, it should be restricted by type and only to known, trusted hosts. | AF75: Certificada | AH75: =IFERROR(VLOOKUP(H75,hoja1!A:A,1,),"N/A") -> N/A
A76: 75 | B76: BSNC | C76: Task Force | D76: Telecomunicaciones | G76: Internet Backup Santander (Cableada | J76: System Responds To ICMP ‘Timestamp’ Requests | K76: CWE-200: Information Exposure | L76: Dismissed | M76: Low | P76: 190216136241 | T76: 43812 | U76: =TODAY()-T76 -> 2397 | V76: =IF(M76="Critical",T76+10,IF(M76="High",T76+30,IF(M76="Bad",T76+30,IF(M76="Medium",T76+90,IF(M76="Warm",T76+90,IF(M76="Low",T76+120,IF(M76="Fair",T76+120,IF(M76="Neutral",T76+120,"")))))))) -> 43932 | W76: =IF(M76="Critical",IF(U76>10,"SLA Vencido","En SLA"),IF(M76="High",IF(U76>30,"SLA Vencido","En SLA"),IF(M76="Bad",IF(U76>30,"SLA Vencido","En SLA"),IF(M76="Medium",IF(U76>90,"SLA Vencido","En SLA"),IF(M76="Warm",IF(U76>90,"SLA Vencido","En SLA"),IF(M76="Low",IF(U76>120,"SLA Vencido","En SLA"),IF(M76="Fair",IF(U76>120,"SLA Vencido","En SLA"),IF(M76="Neutral",IF(U76>120,"SLA Vencido","En SLA"),"Error")))))))) -> SLA Vencido | AA76: 43969 | AB76: The difference between the local and remote clocks is 3041 seconds. | AC76: Cisco recommends that, wherever possible, systems should be configured not to respond to any ICMP requests. In addition, each firewall should be configured to drop all ICMP traffic. Where a case can be made for ICMP traffic to be allowed, it should be restricted by type and only to known, trusted hosts. | AF76: En proceso de certificacion. No fue certificada Susana Tovar: La red ya no existen Javier Leon: dado que el servicio se canceló y que son segmentos públicos el proveedor de servicio reasigno el direccionamiento a otro cliente. | AH76: =IFERROR(VLOOKUP(H76,hoja1!A:A,1,),"N/A") -> N/A
A77: 76 | B77: BSNC | C77: Task Force | D77: Telecomunicaciones | G77: Internet Backup Santander (Cableada | J77: System Responds To ICMP ‘Timestamp’ Requests | K77: CWE-200: Information Exposure | L77: Dismissed | M77: Low | P77: 190216136242 | T77: 43812 | U77: =TODAY()-T77 -> 2397 | V77: =IF(M77="Critical",T77+10,IF(M77="High",T77+30,IF(M77="Bad",T77+30,IF(M77="Medium",T77+90,IF(M77="Warm",T77+90,IF(M77="Low",T77+120,IF(M77="Fair",T77+120,IF(M77="Neutral",T77+120,"")))))))) -> 43932 | W77: =IF(M77="Critical",IF(U77>10,"SLA Vencido","En SLA"),IF(M77="High",IF(U77>30,"SLA Vencido","En SLA"),IF(M77="Bad",IF(U77>30,"SLA Vencido","En SLA"),IF(M77="Medium",IF(U77>90,"SLA Vencido","En SLA"),IF(M77="Warm",IF(U77>90,"SLA Vencido","En SLA"),IF(M77="Low",IF(U77>120,"SLA Vencido","En SLA"),IF(M77="Fair",IF(U77>120,"SLA Vencido","En SLA"),IF(M77="Neutral",IF(U77>120,"SLA Vencido","En SLA"),"Error")))))))) -> SLA Vencido | AA77: 43969 | AB77: The difference between the local and remote clocks is 3041 seconds. | AC77: Cisco recommends that, wherever possible, systems should be configured not to respond to any ICMP requests. In addition, each firewall should be configured to drop all ICMP traffic. Where a case can be made for ICMP traffic to be allowed, it should be restricted by type and only to known, trusted hosts. | AF77: En proceso de certificacion. No fue certificada Susana Tovar: La red ya no existen Javier Leon: dado que el servicio se canceló y que son segmentos públicos el proveedor de servicio reasigno el direccionamiento a otro cliente. | AH77: =IFERROR(VLOOKUP(H77,hoja1!A:A,1,),"N/A") -> N/A
A78: 77 | B78: BSNC | C78: Task Force | D78: Telecomunicaciones | G78: Internet invitados principal Santander (Wifi Ppal) | J78: System Responds To ICMP ‘Timestamp’ Requests | K78: CWE-200: Information Exposure | L78: Solved | M78: Low | P78: 181.49.176.1 | T78: 43812 | U78: =TODAY()-T78 -> 2397 | V78: =IF(M78="Critical",T78+10,IF(M78="High",T78+30,IF(M78="Bad",T78+30,IF(M78="Medium",T78+90,IF(M78="Warm",T78+90,IF(M78="Low",T78+120,IF(M78="Fair",T78+120,IF(M78="Neutral",T78+120,"")))))))) -> 43932 | W78: =IF(M78="Critical",IF(U78>10,"SLA Vencido","En SLA"),IF(M78="High",IF(U78>30,"SLA Vencido","En SLA"),IF(M78="Bad",IF(U78>30,"SLA Vencido","En SLA"),IF(M78="Medium",IF(U78>90,"SLA Vencido","En SLA"),IF(M78="Warm",IF(U78>90,"SLA Vencido","En SLA"),IF(M78="Low",IF(U78>120,"SLA Vencido","En SLA"),IF(M78="Fair",IF(U78>120,"SLA Vencido","En SLA"),IF(M78="Neutral",IF(U78>120,"SLA Vencido","En SLA"),"Error")))))))) -> SLA Vencido | AA78: 43969 | AB78: This host returns non-standard timestamps (high bit is set) | AC78: Cisco recommends that, wherever possible, systems should be configured not to respond to any ICMP requests. In addition, each firewall should be configured to drop all ICMP traffic. Where a case can be made for ICMP traffic to be allowed, it should be restricted by type and only to known, trusted hosts. | AF78: Certificada | AH78: =IFERROR(VLOOKUP(H78,hoja1!A:A,1,),"N/A") -> N/A
A79: 78 | B79: BSNC | C79: Task Force | D79: Telecomunicaciones | G79: Internet invitados Backup Santander (Wifi Backup) | J79: System Responds To ICMP ‘Timestamp’ Requests | K79: CWE-200: Information Exposure | L79: Solved | M79: Low | P79: 181.48.20.111 | T79: 43812 | U79: =TODAY()-T79 -> 2397 | V79: =IF(M79="Critical",T79+10,IF(M79="High",T79+30,IF(M79="Bad",T79+30,IF(M79="Medium",T79+90,IF(M79="Warm",T79+90,IF(M79="Low",T79+120,IF(M79="Fair",T79+120,IF(M79="Neutral",T79+120,"")))))))) -> 43932 | W79: =IF(M79="Critical",IF(U79>10,"SLA Vencido","En SLA"),IF(M79="High",IF(U79>30,"SLA Vencido","En SLA"),IF(M79="Bad",IF(U79>30,"SLA Vencido","En SLA"),IF(M79="Medium",IF(U79>90,"SLA Vencido","En SLA"),IF(M79="Warm",IF(U79>90,"SLA Vencido","En SLA"),IF(M79="Low",IF(U79>120,"SLA Vencido","En SLA"),IF(M79="Fair",IF(U79>120,"SLA Vencido","En SLA"),IF(M79="Neutral",IF(U79>120,"SLA Vencido","En SLA"),"Error")))))))) -> SLA Vencido | AA79: 43969 | AB79: This host returns non-standard timestamps (high bit is set) | AC79: Cisco recommends that, wherever possible, systems should be configured not to respond to any ICMP requests. In addition, each firewall should be configured to drop all ICMP traffic. Where a case can be made for ICMP traffic to be allowed, it should be restricted by type and only to known, trusted hosts. | AF79: Certificada | AH79: =IFERROR(VLOOKUP(H79,hoja1!A:A,1,),"N/A") -> N/A
A80: 79 | B80: BSNC | C80: Task Force | D80: Telecomunicaciones | G80: Internet principal Santander (Cableada) | J80: System Responds To ICMP ‘Timestamp’ Requests | K80: CWE-200: Information Exposure | L80: Solved | M80: Low | P80: 181.48.106.209 | T80: 43812 | U80: =TODAY()-T80 -> 2397 | V80: =IF(M80="Critical",T80+10,IF(M80="High",T80+30,IF(M80="Bad",T80+30,IF(M80="Medium",T80+90,IF(M80="Warm",T80+90,IF(M80="Low",T80+120,IF(M80="Fair",T80+120,IF(M80="Neutral",T80+120,"")))))))) -> 43932 | W80: =IF(M80="Critical",IF(U80>10,"SLA Vencido","En SLA"),IF(M80="High",IF(U80>30,"SLA Vencido","En SLA"),IF(M80="Bad",IF(U80>30,"SLA Vencido","En SLA"),IF(M80="Medium",IF(U80>90,"SLA Vencido","En SLA"),IF(M80="Warm",IF(U80>90,"SLA Vencido","En SLA"),IF(M80="Low",IF(U80>120,"SLA Vencido","En SLA"),IF(M80="Fair",IF(U80>120,"SLA Vencido","En SLA"),IF(M80="Neutral",IF(U80>120,"SLA Vencido","En SLA"),"Error")))))))) -> SLA Vencido | AA80: 43969 | AB80: The difference between the local and remote clocks is 2862 seconds. | AC80: Cisco recommends that, wherever possible, systems should be configured not to respond to any ICMP requests. In addition, each firewall should be configured to drop all ICMP traffic. Where a case can be made for ICMP traffic to be allowed, it should be restricted by type and only to known, trusted hosts. | AF80: Certificada | AH80: =IFERROR(VLOOKUP(H80,hoja1!A:A,1,),"N/A") -> N/A
A81: 80 | B81: BSNC | C81: Task Force | D81: Telecomunicaciones | G81: Internet principal Santander (Cableada) | J81: System Responds To ICMP ‘Timestamp’ Requests | K81: CWE-200: Information Exposure | L81: Solved | M81: Low | P81: 181.48.106.210 | T81: 43812 | U81: =TODAY()-T81 -> 2397 | V81: =IF(M81="Critical",T81+10,IF(M81="High",T81+30,IF(M81="Bad",T81+30,IF(M81="Medium",T81+90,IF(M81="Warm",T81+90,IF(M81="Low",T81+120,IF(M81="Fair",T81+120,IF(M81="Neutral",T81+120,"")))))))) -> 43932 | W81: =IF(M81="Critical",IF(U81>10,"SLA Vencido","En SLA"),IF(M81="High",IF(U81>30,"SLA Vencido","En SLA"),IF(M81="Bad",IF(U81>30,"SLA Vencido","En SLA"),IF(M81="Medium",IF(U81>90,"SLA Vencido","En SLA"),IF(M81="Warm",IF(U81>90,"SLA Vencido","En SLA"),IF(M81="Low",IF(U81>120,"SLA Vencido","En SLA"),IF(M81="Fair",IF(U81>120,"SLA Vencido","En SLA"),IF(M81="Neutral",IF(U81>120,"SLA Vencido","En SLA"),"Error")))))))) -> SLA Vencido | AA81: 43969 | AB81: The difference between the local and remote clocks is 2863 seconds. | AC81: Cisco recommends that, wherever possible, systems should be configured not to respond to any ICMP requests. In addition, each firewall should be configured to drop all ICMP traffic. Where a case can be made for ICMP traffic to be allowed, it should be restricted by type and only to known, trusted hosts. | AF81: Certificada | AH81: =IFERROR(VLOOKUP(H81,hoja1!A:A,1,),"N/A") -> N/A
A82: 81 | B82: BSNC | C82: Task Force | D82: Telecomunicaciones | G82: Internet invitados Backup Santander (Wifi Backup) | J82: System Responds To ICMP ‘Timestamp’ Requests | K82: CWE-200: Information Exposure | L82: Solved | M82: Low | P82: 181.48.20.105 | T82: 43812 | U82: =TODAY()-T82 -> 2397 | V82: =IF(M82="Critical",T82+10,IF(M82="High",T82+30,IF(M82="Bad",T82+30,IF(M82="Medium",T82+90,IF(M82="Warm",T82+90,IF(M82="Low",T82+120,IF(M82="Fair",T82+120,IF(M82="Neutral",T82+120,"")))))))) -> 43932 | W82: =IF(M82="Critical",IF(U82>10,"SLA Vencido","En SLA"),IF(M82="High",IF(U82>30,"SLA Vencido","En SLA"),IF(M82="Bad",IF(U82>30,"SLA Vencido","En SLA"),IF(M82="Medium",IF(U82>90,"SLA Vencido","En SLA"),IF(M82="Warm",IF(U82>90,"SLA Vencido","En SLA"),IF(M82="Low",IF(U82>120,"SLA Vencido","En SLA"),IF(M82="Fair",IF(U82>120,"SLA Vencido","En SLA"),IF(M82="Neutral",IF(U82>120,"SLA Vencido","En SLA"),"Error")))))))) -> SLA Vencido | AA82: 43969 | AB82: This host returns non-standard timestamps (high bit is set) | AC82: Cisco recommends that, wherever possible, systems should be configured not to respond to any ICMP requests. In addition, each firewall should be configured to drop all ICMP traffic. Where a case can be made for ICMP traffic to be allowed, it should be restricted by type and only to known, trusted hosts. | AF82: Certificada | AH82: =IFERROR(VLOOKUP(H82,hoja1!A:A,1,),"N/A") -> N/A
A83: 82 | B83: BSNC | C83: Task Force | D83: Wep App | E83: A2 20190509_2.3.1.c_CO_20200612_N_10 | G83: Portal Web | J83: Web Application Includes Files From A Third-Party | K83: CWE-830: Inclusion of Web Functionality from an Untrusted Source | L83: Solved | M83: Medium | P83: 170.169.33.93 | Q83: www.santander.com.co | R83: 443 | S83: TCP | T83: 43816 | U83: =TODAY()-T83 -> 2393 | V83: =IF(M83="Critical",T83+10,IF(M83="High",T83+30,IF(M83="Bad",T83+30,IF(M83="Medium",T83+90,IF(M83="Warm",T83+90,IF(M83="Low",T83+120,IF(M83="Fair",T83+120,IF(M83="Neutral",T83+120,"")))))))) -> 43906 | W83: =IF(M83="Critical",IF(U83>10,"SLA Vencido","En SLA"),IF(M83="High",IF(U83>30,"SLA Vencido","En SLA"),IF(M83="Bad",IF(U83>30,"SLA Vencido","En SLA"),IF(M83="Medium",IF(U83>90,"SLA Vencido","En SLA"),IF(M83="Warm",IF(U83>90,"SLA Vencido","En SLA"),IF(M83="Low",IF(U83>120,"SLA Vencido","En SLA"),IF(M83="Fair",IF(U83>120,"SLA Vencido","En SLA"),IF(M83="Neutral",IF(U83>120,"SLA Vencido","En SLA"),"Error")))))))) -> SLA Vencido | X83: Waiver | Y83: 1ª Fecha: 12/06/2020 | Z83: 1ª Fecha: 09/09/2020 | AA83: 44260 | AB83: La respuesta incluye dinámicamente el siguiente guión de otro dominio: - https://ajax.googleapis.com/ajax/libs/jquery/3.1.1/jquery.min.js - https://platform.twitter.com/oct.js - https://sb.scorecardresearch.com/c2/16058935/cs.js - https://www.youtube.com/iframe_api - https://www.youtube.com/player_api - https://www.images-home.com/image.js | AC83: Cisco recomienda que no se utilicen dominios cruzados, particularmente de sistemas controlados por terceros. Siempre que sea posible, la aplicación web debe ser autónoma y cualquier copia incluida de los hosts remotos y colocada en el servidor web que aloja la aplicación. | AE83: 44119 | AF83: Certificada | AG83: Jaime Orlando Vargas Martinez | AH83: =IFERROR(VLOOKUP(H83,hoja1!A:A,1,),"N/A") -> N/A
A84: 83 | B84: BSNC | C84: Task Force | D84: Wep App | E84: BSNC-2020-005 | G84: Web de Proveedores | J84: Web Application Includes Files From A Third-Party | K84: CWE-830: Inclusion of Web Functionality from an Untrusted Source | L84: Dismissed | M84: Medium | P84: 170.169.33.48 | Q84: confirming.santander.com.co | R84: 443 | S84: TCP | T84: 43816 | U84: =TODAY()-T84 -> 2393 | V84: =IF(M84="Critical",T84+10,IF(M84="High",T84+30,IF(M84="Bad",T84+30,IF(M84="Medium",T84+90,IF(M84="Warm",T84+90,IF(M84="Low",T84+120,IF(M84="Fair",T84+120,IF(M84="Neutral",T84+120,"")))))))) -> 43906 | W84: =IF(M84="Critical",IF(U84>10,"SLA Vencido","En SLA"),IF(M84="High",IF(U84>30,"SLA Vencido","En SLA"),IF(M84="Bad",IF(U84>30,"SLA Vencido","En SLA"),IF(M84="Medium",IF(U84>90,"SLA Vencido","En SLA"),IF(M84="Warm",IF(U84>90,"SLA Vencido","En SLA"),IF(M84="Low",IF(U84>120,"SLA Vencido","En SLA"),IF(M84="Fair",IF(U84>120,"SLA Vencido","En SLA"),IF(M84="Neutral",IF(U84>120,"SLA Vencido","En SLA"),"Error")))))))) -> SLA Vencido | X84: Waiver | Y84: 1ª Fecha: 2ª Fecha: | Z84: 1ª Fecha: 2ª Fecha: | AA84: 44025 | AB84: La respuesta incluye dinámicamente el siguiente guión de otro dominio: - https://www.images-home.com/image.js | AC84: Cisco recomienda que no se utilicen dominios cruzados, particularmente de sistemas controlados por terceros. Siempre que sea posible, la aplicación web debe ser autónoma y cualquier copia incluida de los hosts remotos y colocada en el servidor web que aloja la aplicación. | AD84: El script puede hacer cualquier cosa que los propios scripts de la aplicación puedan hacer, como acceder a los datos de la aplicación y realizar acciones dentro del contexto del usuario actual. | AE84: 44012 | AF84: Fue dado de baja el Lunes 13 de Julio del 2020 | AH84: =IFERROR(VLOOKUP(H84,hoja1!A:A,1,),"N/A") -> N/A
A85: 84 | B85: BSNC | C85: Task Force | D85: Wep App | G85: N/A | J85: Web Application Does Not Use ‘HTTPOnly’ Cookies | K85: CWE-830: Inclusion of Web Functionality from an Untrusted Source | L85: N/A | M85: Medium | U85: =TODAY()-T85 -> 46209 | V85: =IF(M85="Critical",T85+10,IF(M85="High",T85+30,IF(M85="Bad",T85+30,IF(M85="Medium",T85+90,IF(M85="Warm",T85+90,IF(M85="Low",T85+120,IF(M85="Fair",T85+120,IF(M85="Neutral",T85+120,"")))))))) -> 90 | W85: =IF(M85="Critical",IF(U85>10,"SLA Vencido","En SLA"),IF(M85="High",IF(U85>30,"SLA Vencido","En SLA"),IF(M85="Bad",IF(U85>30,"SLA Vencido","En SLA"),IF(M85="Medium",IF(U85>90,"SLA Vencido","En SLA"),IF(M85="Warm",IF(U85>90,"SLA Vencido","En SLA"),IF(M85="Low",IF(U85>120,"SLA Vencido","En SLA"),IF(M85="Fair",IF(U85>120,"SLA Vencido","En SLA"),IF(M85="Neutral",IF(U85>120,"SLA Vencido","En SLA"),"Error")))))))) -> SLA Vencido | AA85: N/A | AB85: The Team observed that the ‘HTTPOnly’ attribute was not set. | AC85: Cisco recommends that the web application is reconfigured to use ‘HTTPOnly’ cookies. PHP can be configured to set the ‘HTTPOnly’ attribute on all cookies by setting ‘session.cookie_httponly’ to ‘true’ in ‘php.ini’. The ‘HTTPOnly’ attribute can be set on a page-by-page basis as follows: session_set_cookie_params(null, null, null, null, true); session_start(); Sun Java EE has supported the ‘HTTPOnly’ flag in the Cookie interface since version 6 (Servlet class version 3), as well as for session cookies (‘JSESSIONID’). Methods ‘setHttpOnly’ and ‘isHttpOnly’ can be used to set and check for ‘HTTPOnly’ value in the cookies. For older versions the workaround is to rewrite the ‘JSESSIONID’ value using and setting it as a custom header: String sessionid = request.getSession().getId(); response.setHeader("SET-COOKIE", "JSESSIONID=" + sessionid + "; HttpOnly"); | AF85: Esta vulnerabilidad no se encuentra presente en ningun activo que pertenezca a BSNC | AH85: =IFERROR(VLOOKUP(H85,hoja1!A:A,1,),"N/A") -> N/A
A86: 85 | B86: BSNC | C86: Task Force | D86: Wep App | G86: Confirming & Factoring\Bot | J86: Web Application Can Be Embedded In Third-Party Websites | K86: CWE-668: Exposure of Resource to Wrong Sphere | L86: Solved | M86: Medium | P86: 94188208248 | Q86: confirming-factoring.santander.com.co | R86: 443 | T86: 43816 | U86: =TODAY()-T86 -> 2393 | V86: =IF(M86="Critical",T86+10,IF(M86="High",T86+30,IF(M86="Bad",T86+30,IF(M86="Medium",T86+90,IF(M86="Warm",T86+90,IF(M86="Low",T86+120,IF(M86="Fair",T86+120,IF(M86="Neutral",T86+120,"")))))))) -> 43906 | W86: =IF(M86="Critical",IF(U86>10,"SLA Vencido","En SLA"),IF(M86="High",IF(U86>30,"SLA Vencido","En SLA"),IF(M86="Bad",IF(U86>30,"SLA Vencido","En SLA"),IF(M86="Medium",IF(U86>90,"SLA Vencido","En SLA"),IF(M86="Warm",IF(U86>90,"SLA Vencido","En SLA"),IF(M86="Low",IF(U86>120,"SLA Vencido","En SLA"),IF(M86="Fair",IF(U86>120,"SLA Vencido","En SLA"),IF(M86="Neutral",IF(U86>120,"SLA Vencido","En SLA"),"Error")))))))) -> SLA Vencido | AA86: 44069 | AB86: El Equipo estableció que la aplicación web podía incorporarse a sitios web de terceros utilizando iFrames. | AC86: Cisco recomienda que, en los casos en que la aplicación necesite ser incorporada en una aplicación de terceros, el servidor web se reconfigure de manera que las respuestas incluyan el siguiente encabezado personalizado, que indique a los navegadores modernos que la representación de la página dentro de un iFrame está prohibida, o que sólo se acepta de los dominios especificados: X-Frame-Options: Deny X-Frame-Options: Allow-From https://some.othersite.com Alternativamente, Cisco recomienda utilizar el JavaScript para evitar que la aplicación se incruste en otra página web. Nota: Aunque el encabezado 'X-Frame-Options' es soportado por los principales navegadores, nunca fue estandarizado y ha sido desaprobado en favor de la directiva 'frame-ancestors' de la especificación CSP Nivel 2. Sin embargo, se recomienda que el encabezado 'X-Frame-Options' actualmente soportado y la recién introducida directiva 'frame-ancestor' se utilicen para garantizar la protección contra todas las amenazas conocidas en todos los escenarios. | AF86: Certificada | AG86: Jaime Orlando Vargas Martinez | AH86: =IFERROR(VLOOKUP(H86,hoja1!A:A,1,),"N/A") -> N/A
A87: 86 | B87: BSNC | C87: Task Force | D87: Wep App | E87: A2 20190509_2.3.1.c_CO_20200612_N_09 | G87: Portal Web | J87: Web Application Discloses Information To Third-Party | K87: CWE-201: Information Exposure Through Sent Data | L87: Solved | M87: Medium | P87: 170.169.33.93 | Q87: www.santander.com.co | T87: 43816 | U87: =TODAY()-T87 -> 2393 | V87: =IF(M87="Critical",T87+10,IF(M87="High",T87+30,IF(M87="Bad",T87+30,IF(M87="Medium",T87+90,IF(M87="Warm",T87+90,IF(M87="Low",T87+120,IF(M87="Fair",T87+120,IF(M87="Neutral",T87+120,"")))))))) -> 43906 | W87: =IF(M87="Critical",IF(U87>10,"SLA Vencido","En SLA"),IF(M87="High",IF(U87>30,"SLA Vencido","En SLA"),IF(M87="Bad",IF(U87>30,"SLA Vencido","En SLA"),IF(M87="Medium",IF(U87>90,"SLA Vencido","En SLA"),IF(M87="Warm",IF(U87>90,"SLA Vencido","En SLA"),IF(M87="Low",IF(U87>120,"SLA Vencido","En SLA"),IF(M87="Fair",IF(U87>120,"SLA Vencido","En SLA"),IF(M87="Neutral",IF(U87>120,"SLA Vencido","En SLA"),"Error")))))))) -> SLA Vencido | X87: Waiver | Y87: 1ª Fecha: 12/06/2020 | Z87: 1ª Fecha: 13/11/2020 | AA87: 44260 | AB87: La aplicación contiene el siguiente enlace a otro dominio desde URL que contienen una línea de consulta: - https://ajax.googleapis.com/ajax/libs/jquery/3.1.1/jquery.min.js - https://analytics.twitter.com/i/adsct?txn_id=nuum1&p_id=Twitter&tw_sale_amount=0&tw_order_qua ntity=0 - https://fonts.googleapis.com/css?family=Open+Sans:400,300,600,700,800 - https://platform.twitter.com/oct.js - https://sb.scorecardresearch.com/c2/16058935/cs.js - https://sb.scorecardresearch.com/p?c1=2&c2=16058935&ns_site=santanderadvance&name=&ns_categor y=banco - https://t.co/i/adsct?txn_id=nuum1&p_id=Twitter&tw_sale_amount=0&tw_order_quantity=0 - https://www.facebook.com/tr?id=1685728391672672&ev=PageView&noscript=1 - https://www.fogafin.gov.co/ - https://www.googletagmanager.com/ns.html?id=GTM-WNBLPF - https://www.youtube.com/iframe_api - https://www.youtube.com/player_api - https://www.images-home.com/image.js | AC87: Cisco recomienda verificar la información revelada a todos los terceros y evitar compartir esa información a menos que sea un requisito comercial. | AE87: 44148 | AF87: Certificada | AG87: Jaime Orlando Vargas Martinez | AH87: =IFERROR(VLOOKUP(H87,hoja1!A:A,1,),"N/A") -> N/A
A88: 87 | B88: BSNC | C88: Task Force | D88: Wep App | E88: A2 20190509_2.3.1.c_CO_20200717_N | G88: Portal Web | J88: Web Application Uses Unsafe Content Disposition For PDF Files | K88: CWE-138: Improper Neutralization of Special Elements | L88: Solved | M88: Medium | P88: 170.169.33.93 | Q88: www.santander.com.co | R88: 443 | S88: TCP | T88: 43816 | U88: =TODAY()-T88 -> 2393 | V88: =IF(M88="Critical",T88+10,IF(M88="High",T88+30,IF(M88="Bad",T88+30,IF(M88="Medium",T88+90,IF(M88="Warm",T88+90,IF(M88="Low",T88+120,IF(M88="Fair",T88+120,IF(M88="Neutral",T88+120,"")))))))) -> 43906 | W88: =IF(M88="Critical",IF(U88>10,"SLA Vencido","En SLA"),IF(M88="High",IF(U88>30,"SLA Vencido","En SLA"),IF(M88="Bad",IF(U88>30,"SLA Vencido","En SLA"),IF(M88="Medium",IF(U88>90,"SLA Vencido","En SLA"),IF(M88="Warm",IF(U88>90,"SLA Vencido","En SLA"),IF(M88="Low",IF(U88>120,"SLA Vencido","En SLA"),IF(M88="Fair",IF(U88>120,"SLA Vencido","En SLA"),IF(M88="Neutral",IF(U88>120,"SLA Vencido","En SLA"),"Error")))))))) -> SLA Vencido | X88: Waiver | Y88: 1ª Fecha 17/07/2020 | Z88: 1ª Fecha: 09/09/2020 | AA88: 44113 | AB88: El Equipo descubrió que los archivos PDF se mostraban en el navegador, lo que exponía potencialmente a los usuarios a múltiples vulnerabilidades relacionadas de forma innecesaria. Algunos archivos de ejemplo: https://www.santander.com.co/recursos/archivos/aceptacion-condiciones.pdf https://www.santander.com.co/recursos/archivos/aviso-de-privacidad.pdf https://www.santander.com.co/recursos/archivos/bsnc-certificaciones-eeff-2018.pdf https://www.santander.com.co/recursos/archivos/bsnc-eeff-auditados-2018-2017.pdf https://www.santander.com.co/recursos/archivos/bsnc-eeff-y-notas-marzo-19.pdf https://www.santander.com.co/recursos/archivos/bsnc-informe-de-gestion-2018.pdf https://www.santander.com.co/recursos/archivos/bsnc-sfc-2013.pdf https://www.santander.com.co/recursos/archivos/canales-atencion-amv.pdf [TRUCATED] | AC88: Cisco recomienda que se modifique la forma en que se accede a los documentos PDF para que los usuarios se vean obligados a descargar los documentos PDF en lugar de abrirlos en su navegador. Esto puede lograrse añadiendo un encabezado de Disposición de Contenido a una solicitud de un documento PDF con el tipo establecido en "adjunto" disposición de contenido: adjunto; Nota: En el sitio web de Adobe se pueden encontrar más consejos sobre cómo añadir un encabezado de Disposición de contenido, así como información sobre la propia vulnerabilidad. | AE88: 44119 | AF88: Certificada | AG88: Jaime Orlando Vargas Martinez | AH88: =IFERROR(VLOOKUP(H88,hoja1!A:A,1,),"N/A") -> N/A
A89: 88 | B89: BSNC | C89: Task Force | D89: Wep App | G89: N/A | J89: Web Application Uses Insecure Transmission For Login Forms | K89: CWE-319: Transmission of Sensitive Information In Plain Text | L89: N/A | M89: Low | U89: =TODAY()-T89 -> 46209 | V89: =IF(M89="Critical",T89+10,IF(M89="High",T89+30,IF(M89="Bad",T89+30,IF(M89="Medium",T89+90,IF(M89="Warm",T89+90,IF(M89="Low",T89+120,IF(M89="Fair",T89+120,IF(M89="Neutral",T89+120,"")))))))) -> 120 | W89: =IF(M89="Critical",IF(U89>10,"SLA Vencido","En SLA"),IF(M89="High",IF(U89>30,"SLA Vencido","En SLA"),IF(M89="Bad",IF(U89>30,"SLA Vencido","En SLA"),IF(M89="Medium",IF(U89>90,"SLA Vencido","En SLA"),IF(M89="Warm",IF(U89>90,"SLA Vencido","En SLA"),IF(M89="Low",IF(U89>120,"SLA Vencido","En SLA"),IF(M89="Fair",IF(U89>120,"SLA Vencido","En SLA"),IF(M89="Neutral",IF(U89>120,"SLA Vencido","En SLA"),"Error")))))))) -> SLA Vencido | AA89: N/A | AB89: The Team discovered that sensitive content was transmitted over the plain text protocol HTTP. | AC89: Cisco recommends that the web application is reconfigured to run over an encrypted protocol such as HTTPS, which should be configured to use trusted certificates and the strongest cipher suites supported by the intended client base. It is important to ensure that no content within the application is accessed via HTTP, as an attacker could exploit this to inject code that would disclose any sensitive content on the affected pages. | AF89: Esta vulnerabilidad no se encuentra presente en ningun activo que pertenezca a BSNC | AH89: =IFERROR(VLOOKUP(H89,hoja1!A:A,1,),"N/A") -> N/A
A90: 89 | B90: BSNC | C90: Task Force | D90: Wep App | E90: BSNC-2020-006 | G90: Web de Proveedores | J90: Web Application Does Not Specify Content Security Policy (CSP) | K90: CWE-673: External Influence of Sphere Definition | L90: Dismissed | M90: Low | P90: 170.169.33.48 | Q90: confirming.santander.com.co | R90: 443 | S90: TCP | T90: 43816 | U90: =TODAY()-T90 -> 2393 | V90: =IF(M90="Critical",T90+10,IF(M90="High",T90+30,IF(M90="Bad",T90+30,IF(M90="Medium",T90+90,IF(M90="Warm",T90+90,IF(M90="Low",T90+120,IF(M90="Fair",T90+120,IF(M90="Neutral",T90+120,"")))))))) -> 43936 | W90: =IF(M90="Critical",IF(U90>10,"SLA Vencido","En SLA"),IF(M90="High",IF(U90>30,"SLA Vencido","En SLA"),IF(M90="Bad",IF(U90>30,"SLA Vencido","En SLA"),IF(M90="Medium",IF(U90>90,"SLA Vencido","En SLA"),IF(M90="Warm",IF(U90>90,"SLA Vencido","En SLA"),IF(M90="Low",IF(U90>120,"SLA Vencido","En SLA"),IF(M90="Fair",IF(U90>120,"SLA Vencido","En SLA"),IF(M90="Neutral",IF(U90>120,"SLA Vencido","En SLA"),"Error")))))))) -> SLA Vencido | X90: Waiver | Y90: 1ª Fecha: 2ª Fecha: | Z90: 1ª Fecha: 2ª Fecha: | AA90: 44025 | AB90: El Equipo observó que el servidor web no daba instrucciones al navegador del usuario para que restringiera las fuentes desde las que se permitía cargar los activos (por ejemplo, scripts, estilos, imágenes o marcos). No se devolvió un encabezamiento HTTP similar al siguiente en respuesta a las solicitudes. Content-Security-Policy: script-src 'self' https://cdn.example.com; img-src 'self'; style-src ' self'; frame-src 'self' | AC90: Cisco recomienda que se utilice la función de Política de Seguridad de Contenidos (CSP) para mejorar la resistencia a los ataques de Cross-site Scripting, prohibiendo el uso de scripts y estilos en línea y limitando las fuentes de activos permitidos a las ubicaciones de confianza. Cuando se implementa correctamente, CSP puede mitigar todos los ataques de Cross-site Scripting, excepto los más sofisticados. Nota: Para una protección efectiva, no se deben utilizar scripts o estilos en línea en las páginas, y en su lugar se deben mover a sus propios archivos. | AD90: Plantean riesgos de seguridad para los usuarios de Internet y los gestores de páginas web y pueden manipularse, por ejemplo, mediante el Cross Site Scripting. | AE90: 44012 | AF90: Fue dado de baja el Lunes 13 de Julio del 2020 | AH90: =IFERROR(VLOOKUP(H90,hoja1!A:A,1,),"N/A") -> N/A
A91: 90 | B91: BSNC | C91: Task Force | D91: Wep App | G91: Internet invitados Backup Santander (Wifi Backup) | J91: Web Application Does Not Specify Content Security Policy (CSP) | K91: CWE-673: External Influence of Sphere Definition | L91: Solved | M91: Low | P91: 181.48.20.105 | R91: 443 | S91: TCP | T91: 43812 | U91: =TODAY()-T91 -> 2397 | V91: =IF(M91="Critical",T91+10,IF(M91="High",T91+30,IF(M91="Bad",T91+30,IF(M91="Medium",T91+90,IF(M91="Warm",T91+90,IF(M91="Low",T91+120,IF(M91="Fair",T91+120,IF(M91="Neutral",T91+120,"")))))))) -> 43932 | W91: =IF(M91="Critical",IF(U91>10,"SLA Vencido","En SLA"),IF(M91="High",IF(U91>30,"SLA Vencido","En SLA"),IF(M91="Bad",IF(U91>30,"SLA Vencido","En SLA"),IF(M91="Medium",IF(U91>90,"SLA Vencido","En SLA"),IF(M91="Warm",IF(U91>90,"SLA Vencido","En SLA"),IF(M91="Low",IF(U91>120,"SLA Vencido","En SLA"),IF(M91="Fair",IF(U91>120,"SLA Vencido","En SLA"),IF(M91="Neutral",IF(U91>120,"SLA Vencido","En SLA"),"Error")))))))) -> SLA Vencido | AA91: 43969 | AB91: The Team observed that the web server did not instruct the user's browser to restrict the sources from which assets (for example, scripts, styles, images or frames) were allowed to be loaded. An HTTP header similar to the following was not returned in response to requests: Content-Security-Policy: script-src 'self' https://cdn.example.com; img-src 'self'; style-src ' self'; frame-src 'self' | AC91: Cisco recommends that the Content Security Policy (CSP) feature be used to improve resistance to Cross-site Scripting attacks by banning the use of inline scripts and styles, and limiting allowed asset sources to trusted locations. When implemented correctly, CSP can mitigate all but the most sophisticated Cross-site Scripting attacks. Note: For effective protection, no inline scripts or styles should be used in pages, and should instead be moved to their own files. | AF91: Certificada | AH91: =IFERROR(VLOOKUP(H91,hoja1!A:A,1,),"N/A") -> N/A
A92: 91 | B92: BSNC | C92: Task Force | D92: Wep App | G92: Confirming & Factoring\Bot | J92: Web Application Does Not Specify Content Security Policy (CSP) | K92: CWE-673: External Influence of Sphere Definition | L92: Solved | M92: Low | P92: 94188208248 | Q92: confirming-factoring.santander.com.co | R92: 443 | S92: TCP | T92: 43816 | U92: =TODAY()-T92 -> 2393 | V92: =IF(M92="Critical",T92+10,IF(M92="High",T92+30,IF(M92="Bad",T92+30,IF(M92="Medium",T92+90,IF(M92="Warm",T92+90,IF(M92="Low",T92+120,IF(M92="Fair",T92+120,IF(M92="Neutral",T92+120,"")))))))) -> 43936 | W92: =IF(M92="Critical",IF(U92>10,"SLA Vencido","En SLA"),IF(M92="High",IF(U92>30,"SLA Vencido","En SLA"),IF(M92="Bad",IF(U92>30,"SLA Vencido","En SLA"),IF(M92="Medium",IF(U92>90,"SLA Vencido","En SLA"),IF(M92="Warm",IF(U92>90,"SLA Vencido","En SLA"),IF(M92="Low",IF(U92>120,"SLA Vencido","En SLA"),IF(M92="Fair",IF(U92>120,"SLA Vencido","En SLA"),IF(M92="Neutral",IF(U92>120,"SLA Vencido","En SLA"),"Error")))))))) -> SLA Vencido | AA92: 43969 | AB92: The Team observed that the web server did not instruct the user's browser to restrict the sources from which assets (for example, scripts, styles, images or frames) were allowed to be loaded. An HTTP header similar to the following was not returned in response to requests: Content-Security-Policy: script-src 'self' https://cdn.example.com; img-src 'self'; style-src ' self'; frame-src 'self' | AC92: Cisco recommends that the Content Security Policy (CSP) feature be used to improve resistance to Cross-site Scripting attacks by banning the use of inline scripts and styles, and limiting allowed asset sources to trusted locations. When implemented correctly, CSP can mitigate all but the most sophisticated Cross-site Scripting attacks. Note: For effective protection, no inline scripts or styles should be used in pages, and should instead be moved to their own files. | AF92: Certificada | AG92: Jaime Orlando Vargas Martinez | AH92: =IFERROR(VLOOKUP(H92,hoja1!A:A,1,),"N/A") -> N/A
A93: 92 | B93: BSNC | C93: Task Force | D93: Wep App | G93: Internet invitados Backup Santander (Wifi Backup) | J93: Web Application Does Not Specify Content Security Policy (CSP) | K93: CWE-673: External Influence of Sphere Definition | L93: Solved | M93: Low | P93: 181.48.20.104 | R93: 443 | S93: TCP | T93: 43812 | U93: =TODAY()-T93 -> 2397 | V93: =IF(M93="Critical",T93+10,IF(M93="High",T93+30,IF(M93="Bad",T93+30,IF(M93="Medium",T93+90,IF(M93="Warm",T93+90,IF(M93="Low",T93+120,IF(M93="Fair",T93+120,IF(M93="Neutral",T93+120,"")))))))) -> 43932 | W93: =IF(M93="Critical",IF(U93>10,"SLA Vencido","En SLA"),IF(M93="High",IF(U93>30,"SLA Vencido","En SLA"),IF(M93="Bad",IF(U93>30,"SLA Vencido","En SLA"),IF(M93="Medium",IF(U93>90,"SLA Vencido","En SLA"),IF(M93="Warm",IF(U93>90,"SLA Vencido","En SLA"),IF(M93="Low",IF(U93>120,"SLA Vencido","En SLA"),IF(M93="Fair",IF(U93>120,"SLA Vencido","En SLA"),IF(M93="Neutral",IF(U93>120,"SLA Vencido","En SLA"),"Error")))))))) -> SLA Vencido | AA93: 43969 | AB93: The Team observed that the web server did not instruct the user's browser to restrict the sources from which assets (for example, scripts, styles, images or frames) were allowed to be loaded. An HTTP header similar to the following was not returned in response to requests: Content-Security-Policy: script-src 'self' https://cdn.example.com; img-src 'self'; style-src ' self'; frame-src 'self' | AC93: Cisco recommends that the Content Security Policy (CSP) feature be used to improve resistance to Cross-site Scripting attacks by banning the use of inline scripts and styles, and limiting allowed asset sources to trusted locations. When implemented correctly, CSP can mitigate all but the most sophisticated Cross-site Scripting attacks. Note: For effective protection, no inline scripts or styles should be used in pages, and should instead be moved to their own files. | AF93: Certificada | AH93: =IFERROR(VLOOKUP(H93,hoja1!A:A,1,),"N/A") -> N/A
A94: 93 | B94: BSNC | C94: Task Force | D94: Wep App | G94: Portal Web | J94: ‘Robots.txt’ File Discloses Information | K94: CWE-200: Information Exposure | L94: Solved | M94: Low | P94: 170.169.33.93 | Q94: www.santander.com.co | R94: 443 | S94: TCP | T94: 43816 | U94: =TODAY()-T94 -> 2393 | V94: =IF(M94="Critical",T94+10,IF(M94="High",T94+30,IF(M94="Bad",T94+30,IF(M94="Medium",T94+90,IF(M94="Warm",T94+90,IF(M94="Low",T94+120,IF(M94="Fair",T94+120,IF(M94="Neutral",T94+120,"")))))))) -> 43936 | W94: =IF(M94="Critical",IF(U94>10,"SLA Vencido","En SLA"),IF(M94="High",IF(U94>30,"SLA Vencido","En SLA"),IF(M94="Bad",IF(U94>30,"SLA Vencido","En SLA"),IF(M94="Medium",IF(U94>90,"SLA Vencido","En SLA"),IF(M94="Warm",IF(U94>90,"SLA Vencido","En SLA"),IF(M94="Low",IF(U94>120,"SLA Vencido","En SLA"),IF(M94="Fair",IF(U94>120,"SLA Vencido","En SLA"),IF(M94="Neutral",IF(U94>120,"SLA Vencido","En SLA"),"Error")))))))) -> SLA Vencido | AA94: 44069 | AB94: El Equipo descubrió que el archivo '/robots.txt' contenía directorios utilizados para controlar los robots de los motores de búsqueda que rastrean los sitios web en busca de información. El contenido de robots.txt : : User-agent: * Disallow: /*?* Sitemap: https://es.santanderadvance.com/sitemaps/sitemap.xml https://www.santander.com.co/robots.txt | AC94: Cisco recomienda que '/robots.txt' sea eliminado a menos que sea absolutamente necesario. Cabe señalar que los motores de búsqueda sólo seguirán los enlaces accesibles, por lo que un método válido para evitar que se indexen las zonas sensibles del sitio es simplemente no incluir los URL sensibles en ninguna de las páginas con enlaces públicos. Si la información presentada por la aplicación no está destinada al consumo público, también es posible sustituir el contenido de '/robots.txt' por el texto que figura a continuación, lo que impedirá que los robots de los motores de búsqueda indexen cualquier contenido de la página: User-agent: * Disallow: * Alternativamente, el archivo '/robots.txt' puede ser reemplazado usando el encabezado X-Robots-Tag Header. En el directorio que no debe ser indexado por los motores de búsqueda, cree un archivo .htaccess e introduzca lo siguiente en él: Header set X-Robots-Tag "noindex, nofollow" | AF94: Certificada | AG94: Jaime Orlando Vargas Martinez | AH94: =IFERROR(VLOOKUP(H94,hoja1!A:A,1,),"N/A") -> N/A
A95: 94 | B95: BSNC | C95: Task Force | D95: Wep App | E95: BSNC-2020-007 | G95: Web de Proveedores | J95: ‘X-Content-Type-Options’ HTTP Header Not Specified | K95: CWE-0: Insecure Configuration | L95: Dismissed | M95: Low | P95: 170.169.33.48 | Q95: confirming.santander.com.co | R95: 443 | S95: TCP | T95: 43816 | U95: =TODAY()-T95 -> 2393 | V95: =IF(M95="Critical",T95+10,IF(M95="High",T95+30,IF(M95="Bad",T95+30,IF(M95="Medium",T95+90,IF(M95="Warm",T95+90,IF(M95="Low",T95+120,IF(M95="Fair",T95+120,IF(M95="Neutral",T95+120,"")))))))) -> 43936 | W95: =IF(M95="Critical",IF(U95>10,"SLA Vencido","En SLA"),IF(M95="High",IF(U95>30,"SLA Vencido","En SLA"),IF(M95="Bad",IF(U95>30,"SLA Vencido","En SLA"),IF(M95="Medium",IF(U95>90,"SLA Vencido","En SLA"),IF(M95="Warm",IF(U95>90,"SLA Vencido","En SLA"),IF(M95="Low",IF(U95>120,"SLA Vencido","En SLA"),IF(M95="Fair",IF(U95>120,"SLA Vencido","En SLA"),IF(M95="Neutral",IF(U95>120,"SLA Vencido","En SLA"),"Error")))))))) -> SLA Vencido | X95: Waiver | Y95: 1ª Fecha: 2ª Fecha: | Z95: 1ª Fecha: 2ª Fecha: | AA95: 44025 | AB95: El Equipo observó que el servidor web no daba instrucciones al navegador del usuario para que no adivinara el tipo de MIME de un archivo por medio del "content sniffing". Una cabecera HTTP similar a la siguiente no se devolvía en respuesta a las solicitudes:: X-Content-Type-Options: nosniff | AC95: Cisco recomienda que el servidor web esté configurado para añadir el siguiente encabezado HTTP "X-Content-Type-Options": X-Content-Type-Options: nosniff | AD95: se produzca un ataque basado en confusión de tipos mime. | AE95: 44012 | AF95: Fue dado de baja el Lunes 13 de Julio del 2020 | AH95: =IFERROR(VLOOKUP(H95,hoja1!A:A,1,),"N/A") -> N/A
A96: 95 | B96: BSNC | C96: Task Force | D96: Wep App | G96: Portal Web | J96: ‘X-Content-Type-Options’ HTTP Header Not Specified | K96: CWE-0: Insecure Configuration | L96: Solved | M96: Low | P96: 170.169.33.93 | Q96: www.santander.com.co | R96: 80 | S96: TCP | T96: 43816 | U96: =TODAY()-T96 -> 2393 | V96: =IF(M96="Critical",T96+10,IF(M96="High",T96+30,IF(M96="Bad",T96+30,IF(M96="Medium",T96+90,IF(M96="Warm",T96+90,IF(M96="Low",T96+120,IF(M96="Fair",T96+120,IF(M96="Neutral",T96+120,"")))))))) -> 43936 | W96: =IF(M96="Critical",IF(U96>10,"SLA Vencido","En SLA"),IF(M96="High",IF(U96>30,"SLA Vencido","En SLA"),IF(M96="Bad",IF(U96>30,"SLA Vencido","En SLA"),IF(M96="Medium",IF(U96>90,"SLA Vencido","En SLA"),IF(M96="Warm",IF(U96>90,"SLA Vencido","En SLA"),IF(M96="Low",IF(U96>120,"SLA Vencido","En SLA"),IF(M96="Fair",IF(U96>120,"SLA Vencido","En SLA"),IF(M96="Neutral",IF(U96>120,"SLA Vencido","En SLA"),"Error")))))))) -> SLA Vencido | AA96: 43969 | AB96: The Team observed that the web server did not instruct the user's browser not to guess the MIME type of a file via content sniffing. An HTTP header similar to the following was not returned in response to requests: X-Content-Type-Options: nosniff | AC96: Cisco recommends that the web server is configured to add the following ‘X-Content-Type-Options’ HTTP header: X-Content-Type-Options: nosniff | AF96: Certificada | AG96: Jaime Orlando Vargas Martinez | AH96: =IFERROR(VLOOKUP(H96,hoja1!A:A,1,),"N/A") -> N/A
A97: 96 | B97: BSNC | C97: Task Force | D97: Wep App | G97: Confirming & Factoring\Bot | J97: ‘X-Content-Type-Options’ HTTP Header Not Specified | K97: CWE-0: Insecure Configuration | L97: Solved | M97: Low | Q97: confirming-factoring.santander.com.co | R97: 443 | S97: TCP | T97: 43816 | U97: =TODAY()-T97 -> 2393 | V97: =IF(M97="Critical",T97+10,IF(M97="High",T97+30,IF(M97="Bad",T97+30,IF(M97="Medium",T97+90,IF(M97="Warm",T97+90,IF(M97="Low",T97+120,IF(M97="Fair",T97+120,IF(M97="Neutral",T97+120,"")))))))) -> 43936 | W97: =IF(M97="Critical",IF(U97>10,"SLA Vencido","En SLA"),IF(M97="High",IF(U97>30,"SLA Vencido","En SLA"),IF(M97="Bad",IF(U97>30,"SLA Vencido","En SLA"),IF(M97="Medium",IF(U97>90,"SLA Vencido","En SLA"),IF(M97="Warm",IF(U97>90,"SLA Vencido","En SLA"),IF(M97="Low",IF(U97>120,"SLA Vencido","En SLA"),IF(M97="Fair",IF(U97>120,"SLA Vencido","En SLA"),IF(M97="Neutral",IF(U97>120,"SLA Vencido","En SLA"),"Error")))))))) -> SLA Vencido | AA97: 43969 | AB97: The Team observed that the web server did not instruct the user's browser not to guess the MIME type of a file via content sniffing. An HTTP header similar to the following was not returned in response to requests: X-Content-Type-Options: nosniff | AC97: Cisco recommends that the web server is configured to add the following ‘X-Content-Type-Options’ HTTP header: X-Content-Type-Options: nosniff | AF97: Certificada | AG97: Jaime Orlando Vargas Martinez | AH97: =IFERROR(VLOOKUP(H97,hoja1!A:A,1,),"N/A") -> N/A
A98: 97 | B98: BSNC | C98: Task Force | D98: Wep App | G98: Confirming & Factoring\Bot | J98: ‘X-XSS-Protection’ HTTP Header Not Specified | K98: CWE-693: Protection Mechanism Failure | L98: Solved | M98: Low | Q98: confirming-factoring.santander.com.co | R98: 443 | S98: TCP | T98: 43816 | U98: =TODAY()-T98 -> 2393 | V98: =IF(M98="Critical",T98+10,IF(M98="High",T98+30,IF(M98="Bad",T98+30,IF(M98="Medium",T98+90,IF(M98="Warm",T98+90,IF(M98="Low",T98+120,IF(M98="Fair",T98+120,IF(M98="Neutral",T98+120,"")))))))) -> 43936 | W98: =IF(M98="Critical",IF(U98>10,"SLA Vencido","En SLA"),IF(M98="High",IF(U98>30,"SLA Vencido","En SLA"),IF(M98="Bad",IF(U98>30,"SLA Vencido","En SLA"),IF(M98="Medium",IF(U98>90,"SLA Vencido","En SLA"),IF(M98="Warm",IF(U98>90,"SLA Vencido","En SLA"),IF(M98="Low",IF(U98>120,"SLA Vencido","En SLA"),IF(M98="Fair",IF(U98>120,"SLA Vencido","En SLA"),IF(M98="Neutral",IF(U98>120,"SLA Vencido","En SLA"),"Error")))))))) -> SLA Vencido | AA98: 43969 | AB98: No X-XSS-Protection header was set in the response. | AC98: Cisco recommends that the web server is configured to add the ‘X-XSS-Protection’ HTTP header as follows: X-XSS-Protection: 1; mode=block | AF98: Certificada | AG98: Jaime Orlando Vargas Martinez | AH98: =IFERROR(VLOOKUP(H98,hoja1!A:A,1,),"N/A") -> N/A
A99: 98 | B99: BSNC | C99: Qualys | D99: Infraestructura | G99: bsncp201bck.cosan.corp | H99: QA-18026094337 | J99: Apache Tomcat Remote Code Execution Vulnerability | L99: Solved | M99: Critical | N99: Vendor | O99: CVE-2019-0232 | P99: 180.26.138.201 | Q99: bsncp201bck.cosan.corp | T99: 43866 | U99: =TODAY()-T99 -> 2343 | V99: =IF(M99="Critical",T99+10,IF(M99="High",T99+30,IF(M99="Bad",T99+30,IF(M99="Medium",T99+90,IF(M99="Warm",T99+90,IF(M99="Low",T99+120,IF(M99="Fair",T99+120,IF(M99="Neutral",T99+120,"")))))))) -> 43876 | W99: =IF(M99="Critical",IF(U99>10,"SLA Vencido","En SLA"),IF(M99="High",IF(U99>30,"SLA Vencido","En SLA"),IF(M99="Bad",IF(U99>30,"SLA Vencido","En SLA"),IF(M99="Medium",IF(U99>90,"SLA Vencido","En SLA"),IF(M99="Warm",IF(U99>90,"SLA Vencido","En SLA"),IF(M99="Low",IF(U99>120,"SLA Vencido","En SLA"),IF(M99="Fair",IF(U99>120,"SLA Vencido","En SLA"),IF(M99="Neutral",IF(U99>120,"SLA Vencido","En SLA"),"Error")))))))) -> SLA Vencido | AA99: 43952 | AC99: El proveedor ha publicado las siguientes correcciones de seguridad relacionadas con esta vulnerabilidad: - Apache Tomcat 9.0.18 o posterior - Apache Tomcat 8.5.40 o posterior - Apache Tomcat 7.0.93 o posterior Se puede encontrar más información en Tomcat | AD99: Cuando se ejecuta en Windows con enableCmdLineArguments habilitado, el Servlet CGI en Apache Tomcat 9.0.0.M1 a 9.0.17, 8.5.0 a 8.5.39 y 7.0.0 a 7.0.93 es vulnerable a la ejecución remota de código debido a un error en la forma en que el JRE pasa los argumentos de la línea de comandos a W | AF99: Certificada | AH99: =IFERROR(VLOOKUP(H99,hoja1!A:A,1,),"N/A") -> N/A
A100: 99 | B100: BSNC | C100: Synack | D100: Wep App | G100: Confirming & Factoring\Bot | H100: helicopterblizzard-4 | J100: XXE in https://141.226.106.45/factoringWSOccidente-factoringWSOccidente/ConsultarProductoOcciclienteServiceAction | L100: Solved | M100: Medium | N100: Vendor | P100: 141.226.106.45 | Q100: confirming-factoring.santander.com.co | T100: 43896 | U100: =TODAY()-T100 -> 2313 | V100: =IF(M100="Critical",T100+10,IF(M100="High",T100+30,IF(M100="Bad",T100+30,IF(M100="Medium",T100+90,IF(M100="Warm",T100+90,IF(M100="Low",T100+120,IF(M100="Fair",T100+120,IF(M100="Neutral",T100+120,"")))))))) -> 43986 | W100: =IF(M100="Critical",IF(U100>10,"SLA Vencido","En SLA"),IF(M100="High",IF(U100>30,"SLA Vencido","En SLA"),IF(M100="Bad",IF(U100>30,"SLA Vencido","En SLA"),IF(M100="Medium",IF(U100>90,"SLA Vencido","En SLA"),IF(M100="Warm",IF(U100>90,"SLA Vencido","En SLA"),IF(M100="Low",IF(U100>120,"SLA Vencido","En SLA"),IF(M100="Fair",IF(U100>120,"SLA Vencido","En SLA"),IF(M100="Neutral",IF(U100>120,"SLA Vencido","En SLA"),"Error")))))))) -> SLA Vencido | AA100: 43891 | AB100: XXE en https://141.226.106.45/factoringWSOccidente-factoringWSOccidente/ConsultarProductoOcciclienteServiceAction: # Descripción del problema: - XXE en la aplicación https://141.226.106.45/f usando la API de SOAP, que se confirmó usando un requerimiento de DNS ciego | AC100: Análisis correcto del XML en la API SOAP. | AD100: Enumeración de archivos verificando si la aplicación tiene errores o no Posible exfiltración (sin el firewall) | AF100: Certificada | AG100: Jaime Orlando Vargas Martinez | AH100: =IFERROR(VLOOKUP(H100,hoja1!A:A,1,),"N/A") -> N/A
...

Sheet BSNC -DT
A1: SLA State | B1: SLA Vencido
A2: Criticity | B2: Critical
A4: Etiquetas de fila | B4: Cuenta de Vulnerability description
A5: Referencias Inseguras a Objetos de manera Directa (IDOR) | B5: 5
A6: Vulnerabilidad de directorio transversal | B6: 1
A7: Versión vulnerable de iText | B7: 1
A8: Librerias de Bootstrap vulnerables | B8: 1
A9: Fallo en identificada en la validación del PIN | B9: 1
A10: Cross Site Request Forgery | B10: 1
A11: Apache Tomcat Remote Code Execution Vulnerability | B11: 1
A12: Referencia Directa a Objeto Insegura (IDOR) | B12: 1
A13: Librerias de Javascript vulnerables | B13: 1
A14: Total general | B14: 13

Sheet BSNC
A1: # | B1: Company | C1: Source | D1: Type | E1: Waiver Code | F1: Previous Waiver code | G1: Name of vulnerable asset | H1: Internal Identification Code | I1: Identification Code External | J1: Vulnerability description | K1: CWE Category | L1: State | M1: Criticity | N1: CVSS / Vendor Severity | O1: Code CVE (Common Vulnerabilities and Exposures) | P1: IP | Q1: Hostname | R1: Port | S1: Port Type | T1: Reported Date | U1: Days that reported | V1: Expiration day according to SLA | W1: SLA State | X1: Waiver | Y1: Date of application for Waiver | Z1: End date of Waiver | AA1: Remediation Date | AB1: Details | AC1: Recommendation | AD1: Risks Derived | AE1: Date of attention | AF1: Commentary | AG1: Owner
A2: 1 | B2: BSNC | C2: Deloitte | D2: Wep App | E2: BSNC-2019-021 | F2: BSNC-2019-005 BSNC-2019-007 | G2: Web de Proveedores | H2: MAN-b00ec668 | I2: CO-001-003 | J2: Vulnerabilidad de directorio transversal | L2: Dismissed | M2: Critical | N2: 7.6999998 | P2: 170.169.33.48 | Q2: confirming.santander.com.co | R2: 443 | T2: 42941 | U2: =TODAY()-T2 -> 3268 | V2: =IF(M2="Critical",T2+10,IF(M2="High",T2+30,IF(M2="Bad",T2+30,IF(M2="Medium",T2+90,IF(M2="Warm",T2+90,IF(M2="Low",T2+120,IF(M2="Fair",T2+120,IF(M2="Neutral",T2+120,"")))))))) -> 42951 | W2: =IF(M2="Critical",IF(U2>10,"SLA Vencido","En SLA"),IF(M2="High",IF(U2>30,"SLA Vencido","En SLA"),IF(M2="Bad",IF(U2>30,"SLA Vencido","En SLA"),IF(M2="Medium",IF(U2>90,"SLA Vencido","En SLA"),IF(M2="Warm",IF(U2>90,"SLA Vencido","En SLA"),IF(M2="Low",IF(U2>120,"SLA Vencido","En SLA"),IF(M2="Fair",IF(U2>120,"SLA Vencido","En SLA"),IF(M2="Neutral",IF(U2>120,"SLA Vencido","En SLA"),"Error")))))))) -> SLA Vencido | X2: Waiver | Y2: 1ª Fecha: 25/07/2017 2ª Fecha: 31/07/2019 3ª Fecha: 21/12/2019 4ª Fecha: 13/04/2020 | Z2: 1ª Fecha: 31/07/2019 2ª Fecha: 29/11/2019 3ª Fecha: 30/04/2020 4ª Fecha: 30/06/2020 | AA2: 44025 | AD2: Un directorio transversal (o path traversal) consiste en explotar una vulnerabilidad informática que ocurre cuando no existe suficiente seguridad en cuanto a la validación de un usuario, permitiéndole acceder a cualquier tipo de directorio superior (padre) sin ningún control. | AE2: 44012 | AF2: Fue dado de baja el Lunes 13 de Julio del 2020
A3: 2 | B3: BSNC | C3: Deloitte | D3: Wep App | E3: BSNC-2019-022 | F3: BSNC-2019-008 | G3: Web de Proveedores | H3: MAN-b00ec669 | I3: CO-005-002 | J3: Cross Site Request Forgery | L3: Dismissed | M3: Critical | N3: 7.5999999 | P3: 170.169.33.48 | Q3: confirming.santander.com.co | R3: 443 | T3: 42941 | U3: =TODAY()-T3 -> 3268 | V3: =IF(M3="Critical",T3+10,IF(M3="High",T3+30,IF(M3="Bad",T3+30,IF(M3="Medium",T3+90,IF(M3="Warm",T3+90,IF(M3="Low",T3+120,IF(M3="Fair",T3+120,IF(M3="Neutral",T3+120,"")))))))) -> 42951 | W3: =IF(M3="Critical",IF(U3>10,"SLA Vencido","En SLA"),IF(M3="High",IF(U3>30,"SLA Vencido","En SLA"),IF(M3="Bad",IF(U3>30,"SLA Vencido","En SLA"),IF(M3="Medium",IF(U3>90,"SLA Vencido","En SLA"),IF(M3="Warm",IF(U3>90,"SLA Vencido","En SLA"),IF(M3="Low",IF(U3>120,"SLA Vencido","En SLA"),IF(M3="Fair",IF(U3>120,"SLA Vencido","En SLA"),IF(M3="Neutral",IF(U3>120,"SLA Vencido","En SLA"),"Error")))))))) -> SLA Vencido | X3: Waiver | Y3: 1ª Fecha: 23/07/2019 2ª Fecha: 21/12/2019 3ª Fecha: 13/04/2020 | Z3: 1ª Fecha: 29/11/2019 2ª Fecha: 30/04/2020 3ª Fecha: 30/06/2020 | AA3: 44025 | AD3: Los ataques de tipo "Cross-site Request Forgery" fuerzan a un usuario a realizar acciones no deseadas en aplicativos web, aprovechando que los usuarios legítimos se encuentran previamente autenticados en la plataforma. De esta manera, un atacante malintencionado podría confeccionar peticiones HTTP que realizasen alguna acción concreta de la aplicación, por ejemplo, cambiar la contraseña del usuario legítimo, hacer una transacción bancaria, etc. Una vez confeccionadas estas peticiones se forzaría al usuario a realizarlas, en este paso interviene un componente de ingeniería social, ya que se ha de hacer llegar al usuario un link con la acción confeccionada por el atacante para que el usuario la ejecute. Por ejemplo, simular una campaña de publicidad de la compañía via e-mail con un enlace a la acción confeccionada por el atacante. Por otro lado, para camuflar el enlace se puede esconder el mismo modificando el texto del hipervínculo, el típico "pulse aquí" o, incluso, utilizar acortadores de URL. De esta manera, cuando el usuario acceda al enlace enviado por correo electrónico se intentará ejecutar la acción deseada dentro de la sesión del usuario en la aplicación, sin que éste se de cuenta. En numerosas ocasiones, si el usuario no se encuentra previamente autenticado, al intentar realizar una acción privilegiada como cambiar la contraseña, el propio aplicativo web presentará al usuario el formulario de inicio de sesión para que éste se autentique y posteriormente realizar la acción diseñada por el atacante. | AE3: 44012 | AF3: Fue dado de baja el Lunes 13 de Julio del 2020
A4: 3 | B4: BSNC | C4: Deloitte | D4: Wep App | E4: BSNC-2019-013 | G4: Web de Proveedores | H4: MAN-28ad454c | I4: CO-017-002 | J4: Debilidad en el mecanismo de CAPTCHA | L4: Dismissed | M4: Medium | N4: 6.5 | P4: 170.169.33.48 | Q4: confirming.santander.com.co | R4: 443 | T4: 42746 | U4: =TODAY()-T4 -> 3463 | V4: =IF(M4="Critical",T4+10,IF(M4="High",T4+30,IF(M4="Bad",T4+30,IF(M4="Medium",T4+90,IF(M4="Warm",T4+90,IF(M4="Low",T4+120,IF(M4="Fair",T4+120,IF(M4="Neutral",T4+120,"")))))))) -> 42836 | W4: =IF(M4="Critical",IF(U4>10,"SLA Vencido","En SLA"),IF(M4="High",IF(U4>30,"SLA Vencido","En SLA"),IF(M4="Bad",IF(U4>30,"SLA Vencido","En SLA"),IF(M4="Medium",IF(U4>90,"SLA Vencido","En SLA"),IF(M4="Warm",IF(U4>90,"SLA Vencido","En SLA"),IF(M4="Low",IF(U4>120,"SLA Vencido","En SLA"),IF(M4="Fair",IF(U4>120,"SLA Vencido","En SLA"),IF(M4="Neutral",IF(U4>120,"SLA Vencido","En SLA"),"Error")))))))) -> SLA Vencido | X4: Waiver | Y4: 1ª Fecha: 21/12/2019 2ª Fecha: 13/04/2020 | Z4: 1ª Fecha: 30/04/2020 2ª Fecha: 30/06/2020 | AA4: 44025 | AD4: Ataque de fuerza bruta | AE4: 44012 | AF4: Fue dado de baja el Lunes 13 de Julio del 2020
A5: 4 | B5: BSNC | C5: Deloitte | D5: Wep App | E5: BSNC-2019-023 | G5: Web de Proveedores | H5: MAN-18af2324 | I5: CO-19-AUTO-02-CO-001 | J5: Uso de librerias desactualizadas | L5: Dismissed | M5: Medium | N5: 5.5999999 | P5: 170.169.33.48 | Q5: confirming.santander.com.co | R5: 443 | T5: 43719 | U5: =TODAY()-T5 -> 2490 | V5: =IF(M5="Critical",T5+10,IF(M5="High",T5+30,IF(M5="Bad",T5+30,IF(M5="Medium",T5+90,IF(M5="Warm",T5+90,IF(M5="Low",T5+120,IF(M5="Fair",T5+120,IF(M5="Neutral",T5+120,"")))))))) -> 43809 | W5: =IF(M5="Critical",IF(U5>10,"SLA Vencido","En SLA"),IF(M5="High",IF(U5>30,"SLA Vencido","En SLA"),IF(M5="Bad",IF(U5>30,"SLA Vencido","En SLA"),IF(M5="Medium",IF(U5>90,"SLA Vencido","En SLA"),IF(M5="Warm",IF(U5>90,"SLA Vencido","En SLA"),IF(M5="Low",IF(U5>120,"SLA Vencido","En SLA"),IF(M5="Fair",IF(U5>120,"SLA Vencido","En SLA"),IF(M5="Neutral",IF(U5>120,"SLA Vencido","En SLA"),"Error")))))))) -> SLA Vencido | X5: Waiver | Y5: 1ª Fecha: 21/12/2019 2ª Fecha: 13/04/2020 | Z5: 1ª Fecha: 30/04/2020 2ª Fecha: 30/06/2020 | AA5: 44025 | AB5: Se encuentra el uso de funciones de Modernizr 2.6.2: /WebProveedoresNala/proveedores/js/vendor/modernizr-2.6.2.min.js | AC5: Se recomienda utilizar versiones actualizadas del software y/o plataformas tecnológicas utilizadas, en caso de no ser posible aplicar todas las actualizaciones de seguridad publicadas para la versión utilizada. | AD5: El software o plataforma utilizada no se encuentra actualizado a la última versión disponible. Esto implica que podría ser susceptible de poder ser comprometido mediante vulnerabilidades conocidas que pudieran poner en riesgo el activo afectado. | AE5: 44012 | AF5: Fue dado de baja el Lunes 13 de Julio del 2020
A6: 5 | B6: BSNC | C6: Deloitte | D6: Wep App | E6: BSNC-2019-014 | G6: Web de Proveedores | H6: MAN-28ad454d | I6: CO-037-001 | J6: Revelación de información a través de SSL/TLS (BEAST) | L6: Dismissed | M6: Medium | N6: 5.3000002 | P6: 170.169.33.48 | Q6: confirming.santander.com.co | R6: 443 | T6: 42879 | U6: =TODAY()-T6 -> 3330 | V6: =IF(M6="Critical",T6+10,IF(M6="High",T6+30,IF(M6="Bad",T6+30,IF(M6="Medium",T6+90,IF(M6="Warm",T6+90,IF(M6="Low",T6+120,IF(M6="Fair",T6+120,IF(M6="Neutral",T6+120,"")))))))) -> 42969 | W6: =IF(M6="Critical",IF(U6>10,"SLA Vencido","En SLA"),IF(M6="High",IF(U6>30,"SLA Vencido","En SLA"),IF(M6="Bad",IF(U6>30,"SLA Vencido","En SLA"),IF(M6="Medium",IF(U6>90,"SLA Vencido","En SLA"),IF(M6="Warm",IF(U6>90,"SLA Vencido","En SLA"),IF(M6="Low",IF(U6>120,"SLA Vencido","En SLA"),IF(M6="Fair",IF(U6>120,"SLA Vencido","En SLA"),IF(M6="Neutral",IF(U6>120,"SLA Vencido","En SLA"),"Error")))))))) -> SLA Vencido | X6: Waiver | Y6: 1ª Fecha: 21/12/2019 2ª Fecha: 13/04/2020 | Z6: 1ª Fecha: 30/04/2020 2ª Fecha: 30/06/2020 | AA6: 44025 | AD6: Existe un fallo de diseño en los protocolos SSL 3.0 y TLS 1.0 al utilizar cifrado de bloque en modo CBC. Esto podría ser utilizado por un atacante remoto para revelar información sensible a través de ataques Man in The Middle. | AE6: 44012 | AF6: Fue dado de baja el Lunes 13 de Julio del 2020
A7: 6 | B7: BSNC | C7: Deloitte | D7: Wep App | E7: BSNC-2019-012 | G7: Web de Proveedores | H7: MAN-7446a64b | I7: CO-009-008 | J7: Fuga de información de servidor y versión | L7: Dismissed | M7: Medium | N7: 5.3000002 | P7: 170.169.33.48 | Q7: confirming.santander.com.co | R7: 443 | T7: 43207 | U7: =TODAY()-T7 -> 3002 | V7: =IF(M7="Critical",T7+10,IF(M7="High",T7+30,IF(M7="Bad",T7+30,IF(M7="Medium",T7+90,IF(M7="Warm",T7+90,IF(M7="Low",T7+120,IF(M7="Fair",T7+120,IF(M7="Neutral",T7+120,"")))))))) -> 43297 | W7: =IF(M7="Critical",IF(U7>10,"SLA Vencido","En SLA"),IF(M7="High",IF(U7>30,"SLA Vencido","En SLA"),IF(M7="Bad",IF(U7>30,"SLA Vencido","En SLA"),IF(M7="Medium",IF(U7>90,"SLA Vencido","En SLA"),IF(M7="Warm",IF(U7>90,"SLA Vencido","En SLA"),IF(M7="Low",IF(U7>120,"SLA Vencido","En SLA"),IF(M7="Fair",IF(U7>120,"SLA Vencido","En SLA"),IF(M7="Neutral",IF(U7>120,"SLA Vencido","En SLA"),"Error")))))))) -> SLA Vencido | X7: Waiver | Y7: 1ª Fecha: 21/12/2019 2ª Fecha: 13/04/2020 | Z7: 1ª Fecha: 30/04/2020 2ª Fecha: 30/06/2020 | AA7: 44025 | AB7: Durante la realización de las pruebas se ha detectado que en las respuestas del servidor se muestra información sobre el tipo de servidor donde se aloja la aplicación | AC7: Se recomienda evitar que la aplicación devuelva al usuario información relativa a la estructura interna de la misma, así como de las tecnologías utilizadas para el desarrollo de la misma o de la infraestructura que la sustenta. Este tipo de información puede ser accesible a través de las cabeceras de respuesta de la aplicación, mensajes de error y/o páginas por defecto. | AD7: Se ha detectado que la aplicación devuelve información acerca de las tecnologías utilizadas para desarrollar la aplicación y/o de la infraestructura utilizada para sustentar la misma. Esta información podría ser utilizada por un atacante con el objetivo de recabar información para ataques futuros. | AE7: 44012 | AF7: Fue dado de baja el Lunes 13 de Julio del 2020
A8: 7 | B8: BSNC | C8: Deloitte | D8: Wep App | E8: BSNC-2019-011 | G8: Web de Proveedores | H8: MAN-28ad4540 | I8: CO-004-001 | J8: Divulgación de información httpOnly Cookie en el Servidor Apache HTTP | L8: Dismissed | M8: Medium | N8: 5.3000002 | P8: 170.169.33.48 | Q8: confirming.santander.com.co | R8: 443 | T8: 42608 | U8: =TODAY()-T8 -> 3601 | V8: =IF(M8="Critical",T8+10,IF(M8="High",T8+30,IF(M8="Bad",T8+30,IF(M8="Medium",T8+90,IF(M8="Warm",T8+90,IF(M8="Low",T8+120,IF(M8="Fair",T8+120,IF(M8="Neutral",T8+120,"")))))))) -> 42698 | W8: =IF(M8="Critical",IF(U8>10,"SLA Vencido","En SLA"),IF(M8="High",IF(U8>30,"SLA Vencido","En SLA"),IF(M8="Bad",IF(U8>30,"SLA Vencido","En SLA"),IF(M8="Medium",IF(U8>90,"SLA Vencido","En SLA"),IF(M8="Warm",IF(U8>90,"SLA Vencido","En SLA"),IF(M8="Low",IF(U8>120,"SLA Vencido","En SLA"),IF(M8="Fair",IF(U8>120,"SLA Vencido","En SLA"),IF(M8="Neutral",IF(U8>120,"SLA Vencido","En SLA"),"Error")))))))) -> SLA Vencido | X8: Waiver | Y8: 1ª Fecha: 21/12/2019 2ª Fecha: 13/04/2020 | Z8: 1ª Fecha: 30/04/2020 2ª Fecha: 30/06/2020 | AA8: 44025 | AD8: La exposición de información acerca de las funcionalidades o rutas internas de la aplicación puede implicar a un atacante obtener una mayor comprensión del sistema en uso y, potencialmente, desarrollar más ataques para apuntar a la aplicación web. | AE8: 44012 | AF8: Fue dado de baja el Lunes 13 de Julio del 2020
A9: 8 | B9: BSNC | C9: Deloitte | D9: Wep App | E9: Wep App | G9: Web de Proveedores | H9: MAN-cc489697 | I9: CO-19-AUTO-01-CO-001 | J9: Uso de Software desactualizado | L9: Dismissed | M9: Medium | N9: 5.3000002 | P9: 170.169.33.48 | Q9: confirming.santander.com.co | R9: 443 | T9: 43580 | U9: =TODAY()-T9 -> 2629 | V9: =IF(M9="Critical",T9+10,IF(M9="High",T9+30,IF(M9="Bad",T9+30,IF(M9="Medium",T9+90,IF(M9="Warm",T9+90,IF(M9="Low",T9+120,IF(M9="Fair",T9+120,IF(M9="Neutral",T9+120,"")))))))) -> 43670 | W9: =IF(M9="Critical",IF(U9>10,"SLA Vencido","En SLA"),IF(M9="High",IF(U9>30,"SLA Vencido","En SLA"),IF(M9="Bad",IF(U9>30,"SLA Vencido","En SLA"),IF(M9="Medium",IF(U9>90,"SLA Vencido","En SLA"),IF(M9="Warm",IF(U9>90,"SLA Vencido","En SLA"),IF(M9="Low",IF(U9>120,"SLA Vencido","En SLA"),IF(M9="Fair",IF(U9>120,"SLA Vencido","En SLA"),IF(M9="Neutral",IF(U9>120,"SLA Vencido","En SLA"),"Error")))))))) -> SLA Vencido | X9: Waiver | Y9: 1ª Fecha: 21/12/2019 2ª Fecha: 13/04/2020 | Z9: 1ª Fecha: 30/04/2020 2ª Fecha: 30/06/2020 | AA9: 44025 | AB9: Las librerias Javascript utilizadas se encuentran desactualizadas. [+]Request: GET https://confirming.santander.com.co /WebProveedoresNala/common/js/prototype.js HTTP/1.1 Pragma: no-cache Cache-Control: no-cache Referer: https://confirming.santander.com.co/WebProveedoresNala/WebPipe Acunetix-Aspect: enabled Acunetix-Aspect-Password: 082119f75623eb7abd7bf357698ff66c Acunetix-Aspect-Queries: filelist;aspectalerts Host: confirming.santander.com.co Connection: Keep-alive Accept-Encoding: gzip,deflate User-Agent: Mozilla/5.0 (Windows NT 6.1; WOW64) AppleWebKit/537.36 (KHTML, like Gecko) Chrome/28.0.1500.63 Safari/537.36 Accept: */* [+]Response: HTTP/1.1 200 OK Date: Fri, 22 Mar 2019 07:12:48 GMT Server: Apache Strict-Transport-Security: max-age=63072000; includeSubdomains; X-Frame-Options: SAMEORIGIN X-XSS-Protection: 1; mode=block Last-Modified: Tue, 14 Oct 2014 17:19:04 GMT Content-Length: 124136 Keep-Alive: timeout=10, max=185 Connection: Keep-Alive Content-Type: application/x-javascript Content-Language: en-US /* Prototype JavaScript framework, version 1.6.0 * (c) 2005-2007 Sam Stephenson * * Prototype is freely distributable under the terms of an MIT-style license. * For details, see the Prototype web site: http://www.prototypejs.org/ * *--------------------------------------------------------------------------*/ | AC9: Se recomienda utilizar versiones actualizadas del software y/o plataformas tecnológicas utilizadas, en caso de no ser posible aplicar todas las actualizaciones de seguridad publicadas para la versión utilizada. | AD9: El software o plataforma utilizada no se encuentra actualizado a la última versión disponible. Esto implica que podría ser susceptible de poder ser comprometido mediante vulnerabilidades conocidas que pudieran poner en riesgo el activo afectado. | AE9: 44012 | AF9: Fue dado de baja el Lunes 13 de Julio del 2020
A10: 9 | B10: BSNC | C10: Deloitte | D10: Wep App | E10: BSNC-2019-017 | G10: Web de Proveedores | H10: MAN-73a2e320 | I10: CO-19-MANU-01-AP-002 | J10: Uso de cifrado 3DES | L10: Dismissed | M10: Medium | N10: 4.3000002 | P10: 170.169.33.48 | Q10: confirming.santander.com.co | T10: 43609 | U10: =TODAY()-T10 -> 2600 | V10: =IF(M10="Critical",T10+10,IF(M10="High",T10+30,IF(M10="Bad",T10+30,IF(M10="Medium",T10+90,IF(M10="Warm",T10+90,IF(M10="Low",T10+120,IF(M10="Fair",T10+120,IF(M10="Neutral",T10+120,"")))))))) -> 43699 | W10: =IF(M10="Critical",IF(U10>10,"SLA Vencido","En SLA"),IF(M10="High",IF(U10>30,"SLA Vencido","En SLA"),IF(M10="Bad",IF(U10>30,"SLA Vencido","En SLA"),IF(M10="Medium",IF(U10>90,"SLA Vencido","En SLA"),IF(M10="Warm",IF(U10>90,"SLA Vencido","En SLA"),IF(M10="Low",IF(U10>120,"SLA Vencido","En SLA"),IF(M10="Fair",IF(U10>120,"SLA Vencido","En SLA"),IF(M10="Neutral",IF(U10>120,"SLA Vencido","En SLA"),"Error")))))))) -> SLA Vencido | X10: Waiver | Y10: 1ª Fecha: 21/12/2019 2ª Fecha: 13/04/2020 | Z10: 1ª Fecha: 30/04/2020 2ª Fecha: 30/06/2020 | AA10: 44025 | AB10: El activo "confirming.santander.com" permite el uso del algoritmo de cifrado 3DES | AC10: Se recomienda deshabilitar el uso del algoritmo de cifrado 3DES y reconfigurar el servicio afectado para restringir los métodos de cifrado a aquellos que ofrezcan un nivel de seguridad alto. | AD10: El host analizado permite el uso de cifrados SSL de seguridad media basados en el algoritmo de cifrado 3DES. Este algoritmo de cifrado es vulnerable a un ataque conocido como Sweet32. Debido a que 3DES tiene un tamaño de bloque de 64 bits, existe una alta probabilidad de que, dados los bloques 2^32, se encuentren dos bloques que colisionen. Una vez que se ha encontrado una colisión entre dos bloques en texto cifrado, se puede averiguar cómo se relacionan los bloques en texto plano correspondientes. Este conocimiento combinado con varios otros atributos permite el descifrado del texto cifrado. | AE10: 44012 | AF10: Fue dado de baja el Lunes 13 de Julio del 2020
A11: 10 | B11: BSNC | C11: Deloitte | D11: Wep App | E11: BSNC-2019-019 | G11: Web de Proveedores | H11: MAN-73a2e322 | I11: CO-19-MANU-01-CO-004 | J11: Módulo SSL/TLS Diffie-Hellman < = 1024 Bits (LogJam) | L11: Dismissed | M11: Medium | N11: 4 | P11: 170.169.33.48 | Q11: confirming.santander.com.co | T11: 43609 | U11: =TODAY()-T11 -> 2600 | V11: =IF(M11="Critical",T11+10,IF(M11="High",T11+30,IF(M11="Bad",T11+30,IF(M11="Medium",T11+90,IF(M11="Warm",T11+90,IF(M11="Low",T11+120,IF(M11="Fair",T11+120,IF(M11="Neutral",T11+120,"")))))))) -> 43699 | W11: =IF(M11="Critical",IF(U11>10,"SLA Vencido","En SLA"),IF(M11="High",IF(U11>30,"SLA Vencido","En SLA"),IF(M11="Bad",IF(U11>30,"SLA Vencido","En SLA"),IF(M11="Medium",IF(U11>90,"SLA Vencido","En SLA"),IF(M11="Warm",IF(U11>90,"SLA Vencido","En SLA"),IF(M11="Low",IF(U11>120,"SLA Vencido","En SLA"),IF(M11="Fair",IF(U11>120,"SLA Vencido","En SLA"),IF(M11="Neutral",IF(U11>120,"SLA Vencido","En SLA"),"Error")))))))) -> SLA Vencido | X11: Waiver | Y11: 1ª Fecha: 21/12/2019 2ª Fecha: 13/04/2020 | Z11: 1ª Fecha: 30/04/2020 2ª Fecha: 30/06/2020 | AA11: 44025 | AB11: El activo "confirming.santander.com.co" es vulnerable a LogJam | AC11: Se recomienda configurar el servicio para usar un único módulo de Diffie-Hellman de 2048 bits o mayor. | AD11: El servidor permite conexiones SSL/TLS con uno o más modulos Diffie-Hellman menor o igual a 1024 bits. A través de Criptoanálisis, un usuario malintencionado podría ser capaz de encontrar la clave compartida en un corto periodo de tiempo (dependiendo del tamaño del módulo y de los recursos del atacante). Esto podría permitir al atacante recupera la información en texto plano o violar la integridad de las conexiones. | AE11: 44012 | AF11: Fue dado de baja el Lunes 13 de Julio del 2020
A12: 11 | B12: BSNC | C12: Deloitte | D12: Wep App | E12: BSNC-2019-015 | G12: Web de Proveedores | H12: MAN-a6e6676b | I12: CO-174-001 | J12: Activo vulnerable a Lucky13 (CVE-2013-0169) | L12: Dismissed | M12: Low | N12: 3.7 | O12: CVE-2013-0169 | P12: 170.169.33.48 | Q12: confirming.santander.com.co | R12: 443 | T12: 43207 | U12: =TODAY()-T12 -> 3002 | V12: =IF(M12="Critical",T12+10,IF(M12="High",T12+30,IF(M12="Bad",T12+30,IF(M12="Medium",T12+90,IF(M12="Warm",T12+90,IF(M12="Low",T12+120,IF(M12="Fair",T12+120,IF(M12="Neutral",T12+120,"")))))))) -> 43327 | W12: =IF(M12="Critical",IF(U12>10,"SLA Vencido","En SLA"),IF(M12="High",IF(U12>30,"SLA Vencido","En SLA"),IF(M12="Bad",IF(U12>30,"SLA Vencido","En SLA"),IF(M12="Medium",IF(U12>90,"SLA Vencido","En SLA"),IF(M12="Warm",IF(U12>90,"SLA Vencido","En SLA"),IF(M12="Low",IF(U12>120,"SLA Vencido","En SLA"),IF(M12="Fair",IF(U12>120,"SLA Vencido","En SLA"),IF(M12="Neutral",IF(U12>120,"SLA Vencido","En SLA"),"Error")))))))) -> SLA Vencido | X12: Waiver | Y12: 1ª Fecha: 21/12/2019 2ª Fecha: 13/04/2020 | Z12: 1ª Fecha: 30/04/2020 2ª Fecha: 30/06/2020 | AA12: 44025 | AB12: se ha detectado que el certificado del servidor (www.santander.com.co) ofrece algortimos de cifrado en modo bloque (CBC) | AC12: Deshabilitar el uso de algoritmos cifrado de bloques (CBC) en el servidor remoto. | AD12: El servidor usa algoritmos de cifrado CBC sobre TLS por lo que está afectado por una vulnerabilidad conocida como Lucky13. Según se ha podido determinar el servidor utiliza cifrados CBC sobre TLS, lo que permitiría a un atacante situado en mitad de las comunicaciones (MiTM) implementar una variante del ataque conocido como Padding de Oracle (POODLE). CVEs Asociados •CVE-2013-0169 | AE12: 44012 | AF12: Fue dado de baja el Lunes 13 de Julio del 2020
A13: 12 | B13: BSNC | C13: Deloitte | D13: Wep App | E13: BSNC-2019-010 | G13: Web de Proveedores | H13: MAN-647bb2ad | I13: CO-19-MANU-02-AP-007 | J13: Ausencia de Cabecera CSP (Content-security-Policy) | L13: Dismissed | M13: Low | N13: 3.5 | P13: 170.169.33.48 | Q13: confirming.santander.com.co | T13: 43784 | U13: =TODAY()-T13 -> 2425 | V13: =IF(M13="Critical",T13+10,IF(M13="High",T13+30,IF(M13="Bad",T13+30,IF(M13="Medium",T13+90,IF(M13="Warm",T13+90,IF(M13="Low",T13+120,IF(M13="Fair",T13+120,IF(M13="Neutral",T13+120,"")))))))) -> 43904 | W13: =IF(M13="Critical",IF(U13>10,"SLA Vencido","En SLA"),IF(M13="High",IF(U13>30,"SLA Vencido","En SLA"),IF(M13="Bad",IF(U13>30,"SLA Vencido","En SLA"),IF(M13="Medium",IF(U13>90,"SLA Vencido","En SLA"),IF(M13="Warm",IF(U13>90,"SLA Vencido","En SLA"),IF(M13="Low",IF(U13>120,"SLA Vencido","En SLA"),IF(M13="Fair",IF(U13>120,"SLA Vencido","En SLA"),IF(M13="Neutral",IF(U13>120,"SLA Vencido","En SLA"),"Error")))))))) -> SLA Vencido | X13: Waiver | Y13: 1ª Fecha: 21/12/2019 2ª Fecha: 13/04/2020 | Z13: 1ª Fecha: 30/04/2020 2ª Fecha: 30/06/2020 | AA13: 44025 | AB13: se ha identificado la ausencia de la cabecera CSP (Content_Security_Policy) mediante las cabeceras de respuesta http | AC13: Configure el servidor web para devolver la cabecera Content-Security-Policy HTTP. Es recomendable que se establezca la política “default-src ‘self’ para que el contenido provenga del mismo origen del sitio. Un ejemplo de la política sería: Content-Security-Policy: default-src 'self' | AD13: CSP (Content Security Policy) es una capa añadida de seguridad que ayuda a detectar y mitigar determinados tipos de ataques, incluyendo ataques Cross-Site Scripting (XSS) y de inyección de datos. Estos ataques se pueden utilizar para realizar todo tipo de técnicas, desde el robo de datos hasta site defacement, pasando por la distribución de malware. CSP proporciona una serie de cabeceras HTTP estándar que permiten que los propietarios de los sitios web declaren que fuentes de contenido se consideran legitimas para que los puedan usarlas. Por ejemplo, JavaScript, CSS, tramas HTML, fuentes, imágenes y archivos incrustables como applets Java, ActiveX y archivos de audio y vídeo. | AE13: 44012 | AF13: Fue dado de baja el Lunes 13 de Julio del 2020
A14: 13 | B14: BSNC | C14: Deloitte | D14: Wep App | E14: BSNC-2019-018 | G14: Web de Proveedores | H14: MAN-73a2e327 | I14: CO-19-MANU-01-AP-008 | J14: Fuga de información de rutas internas | L14: Dismissed | M14: Low | N14: 3.2 | P14: 170.169.33.48 | Q14: confirming.santander.com.co | T14: 43609 | U14: =TODAY()-T14 -> 2600 | V14: =IF(M14="Critical",T14+10,IF(M14="High",T14+30,IF(M14="Bad",T14+30,IF(M14="Medium",T14+90,IF(M14="Warm",T14+90,IF(M14="Low",T14+120,IF(M14="Fair",T14+120,IF(M14="Neutral",T14+120,"")))))))) -> 43729 | W14: =IF(M14="Critical",IF(U14>10,"SLA Vencido","En SLA"),IF(M14="High",IF(U14>30,"SLA Vencido","En SLA"),IF(M14="Bad",IF(U14>30,"SLA Vencido","En SLA"),IF(M14="Medium",IF(U14>90,"SLA Vencido","En SLA"),IF(M14="Warm",IF(U14>90,"SLA Vencido","En SLA"),IF(M14="Low",IF(U14>120,"SLA Vencido","En SLA"),IF(M14="Fair",IF(U14>120,"SLA Vencido","En SLA"),IF(M14="Neutral",IF(U14>120,"SLA Vencido","En SLA"),"Error")))))))) -> SLA Vencido | X14: Waiver | Y14: 1ª Fecha: 21/12/2019 2ª Fecha: 13/04/2020 | Z14: 1ª Fecha: 30/04/2020 2ª Fecha: 30/06/2020 | AA14: 44025 | AB14: Se ha detectado que la aplicación devuelve información acerca de rutas internas del sistema de ficheros del servidor. Esta información podría ser utilizada por un atacante con el objetivo de recabar información para ataques futuros. | AC14: Se recomienda evitar que la aplicación devuelva al usuario información relativa al funcionamiento interno del servidor, como pueden ser rutas internas o ubicación de ficheros o directorios dentro del mismo. Para ello, se recomienda modificar la página de error "404 not found". | AD14: Se ha detectado que la aplicación devuelve información acerca de rutas internas del sistema de ficheros del servidor. Esta información podría ser utilizada por un atacante con el objetivo de recabar información para ataques futuros. | AE14: 44012 | AF14: Fue dado de baja el Lunes 13 de Julio del 2020
A15: 14 | B15: BSNC | C15: Deloitte | D15: Wep App | E15: BSNC-2019-020 | G15: Web de Proveedores | H15: MAN-73a2e326 | I15: CO-19-MANU-01-CO-007 | J15: Suite de cifrado SSL de 64-bit Soportada (SWEET32) | L15: Dismissed | M15: Low | N15: 2.5999999 | P15: 170.169.33.48 | Q15: confirming.santander.com.co | T15: 43609 | U15: =TODAY()-T15 -> 2600 | V15: =IF(M15="Critical",T15+10,IF(M15="High",T15+30,IF(M15="Bad",T15+30,IF(M15="Medium",T15+90,IF(M15="Warm",T15+90,IF(M15="Low",T15+120,IF(M15="Fair",T15+120,IF(M15="Neutral",T15+120,"")))))))) -> 43729 | W15: =IF(M15="Critical",IF(U15>10,"SLA Vencido","En SLA"),IF(M15="High",IF(U15>30,"SLA Vencido","En SLA"),IF(M15="Bad",IF(U15>30,"SLA Vencido","En SLA"),IF(M15="Medium",IF(U15>90,"SLA Vencido","En SLA"),IF(M15="Warm",IF(U15>90,"SLA Vencido","En SLA"),IF(M15="Low",IF(U15>120,"SLA Vencido","En SLA"),IF(M15="Fair",IF(U15>120,"SLA Vencido","En SLA"),IF(M15="Neutral",IF(U15>120,"SLA Vencido","En SLA"),"Error")))))))) -> SLA Vencido | X15: Waiver | Y15: 1ª Fecha: 21/12/2019 2ª Fecha: 13/04/2020 | Z15: 1ª Fecha: 30/04/2020 2ª Fecha: 30/06/2020 | AA15: 44025 | AB15: El activo "confirming.santander.com.co " es vulnerable a SWEET32 | AC15: Se recomienda reconfigurar la aplicación afectada, si es posible, para evitar el uso de todos los cifrados de bloques de 64 bits. Como alternativa, coloque limitaciones en el número de solicitudes que se permiten procesar sobre la misma conexión TLS para mitigar esta vulnerabilidad. | AD15: El servidor admite el uso de un cifrado de bloque con bloques de 64 bits en una o más suites de cifrado. Está afectado por una vulnerabilidad, conocida como SWEET32, debido al uso de cifrados débiles. Un ataque Man in the Middle con recursos suficientes puede explotar esta vulnerabilidad. | AE15: 44012 | AF15: Fue dado de baja el Lunes 13 de Julio del 2020
A16: 15 | B16: BSNC | C16: Deloitte | D16: Wep App | E16: A2 20190509_2.3.1.c_CO_20200728_N_06 | G16: Confirming & Factoring\Bot | H16: MAN-18af2323 | I16: CO-19-AUTO-02-CO-002 | J16: Uso de librerias desactualizadas | L16: Solved | M16: Medium | N16: 5.5999999 | P16: 64.76.90.137 | Q16: confirming-factoring.santander.com.co | R16: 443 | T16: 43719 | U16: =TODAY()-T16 -> 2490 | V16: =IF(M16="Critical",T16+10,IF(M16="High",T16+30,IF(M16="Bad",T16+30,IF(M16="Medium",T16+90,IF(M16="Warm",T16+90,IF(M16="Low",T16+120,IF(M16="Fair",T16+120,IF(M16="Neutral",T16+120,"")))))))) -> 43809 | W16: =IF(M16="Critical",IF(U16>10,"SLA Vencido","En SLA"),IF(M16="High",IF(U16>30,"SLA Vencido","En SLA"),IF(M16="Bad",IF(U16>30,"SLA Vencido","En SLA"),IF(M16="Medium",IF(U16>90,"SLA Vencido","En SLA"),IF(M16="Warm",IF(U16>90,"SLA Vencido","En SLA"),IF(M16="Low",IF(U16>120,"SLA Vencido","En SLA"),IF(M16="Fair",IF(U16>120,"SLA Vencido","En SLA"),IF(M16="Neutral",IF(U16>120,"SLA Vencido","En SLA"),"Error")))))))) -> SLA Vencido | X16: Waiver | Y16: 1ª Fecha: 28/12/2020 | Z16: 1ª Fecha: 18/12/2020 | AA16: 44089 | AB16: Se encuentra el uso de funciones de Zoom Search Engine 5.0: /factoring/ayuda/zoom_search.js | AC16: Se recomienda utilizar versiones actualizadas del software y/o plataformas tecnológicas utilizadas, en caso de no ser posible aplicar todas las actualizaciones de seguridad publicadas para la versión utilizada. | AD16: El software o plataforma utilizada no se encuentra actualizado a la última versión disponible. Esto implica que podría ser susceptible de poder ser comprometido mediante vulnerabilidades conocidas que pudieran poner en riesgo el activo afectado. | AE16: Sin definir | AF16: Certificada | AG16: Jaime Orlando Vargas Martinez
